Workbook
Name ConfirmacoesDoR: 'Listas de apoio'!$I$5:$I$7
Name DecisoesRefinement: 'Listas de apoio'!$M$5:$M$7
Name EstadosTarefa: 'Listas de apoio'!$K$5:$K$10
Name Milestones: 'Listas de apoio'!$E$5:$E$8
Name Orcamentos: 'Listas de apoio'!$G$5:$G$12
Name Prioridades: 'Listas de apoio'!$C$5:$C$9
Name TiposTarefa: 'Listas de apoio'!$A$5:$A$18

Sheet Backlog de Projeto
A1: BACKLOG DE PROJETO
A2: IDENTIFICAÇÃO E PLANEAMENTO | J2: ORÇAMENTO E REPARTIÇÃO | N2: CRITÉRIOS, QUALIDADE E DESTINO | V2: CONTROLO E DECISÃO
A3: Issue | B3: Tarefa | C3: Descrição | D3: Objetivo | E3: Tipo | F3: Resultado esperado | G3: Prioridade | H3: Milestone de Entrega prevista | I3: Sprint previsional | J3: Orçamento da tarefa | K3: Pontos do Executor | L3: Pontos do Revisor | M3: Pontos do Auditor | N3: Critérios de aceitação | O3: Evidências do Executor | P3: Verificações do Revisor | Q3: Checklist do Auditor | R3: Dependências | S3: Definition of Done aplicável | T3: Normas, modelos e referências | U3: Pasta de destino | V3: Definition of Ready confirmada | W3: Estado | X3: Decisão do Backlog Refinement | Y3: Data da decisão | Z3: Ata da decisão | AA3: Histórico e observações
A4: I001 | B4: Elaborar Proposta de Sistema | C4: Preparar a Proposta de Sistema do projeto Gestão de Clínica Veterinária, identificando problema, utilizadores, atores e funcionalidades principais. | D4: Definir formalmente o sistema a desenvolver e estabelecer a base para a Declaração de Âmbito e restantes artefactos técnicos. | E4: Documentação | F4: m1-proposta-sistema-v03.pdf | G4: 1 — Crítica | H4: m1 | I4: S01 | J4: 50 | K4: =IF(ISNUMBER(J4),J4*60%,IF(J4="","Por preencher",J4)) -> 30 | L4: =IF(ISNUMBER(J4),J4*30%,IF(J4="","Por preencher",J4)) -> 15 | M4: =IF(ISNUMBER(J4),J4*10%,IF(J4="","Por preencher",J4)) -> 5 | N4: Documento segue o template oficial; identifica sistema, atores e funcionalidades F001 e seguintes; inclui declaração de originalidade; conteúdo coerente e pronto para homologação. | O4: m1-proposta-sistema-v03.pdf; versões de trabalho; histórico de alterações e evidência de submissão para homologação. | P4: Verificar utilização do template, completude, coerência das funcionalidades, originalidade, nomenclatura, versão e consistência com o tema aprovado. | Q4: Confirmar que a revisão foi realizada, que a versão final corresponde à evidência, que o ficheiro está na pasta correta e que não existem campos obrigatórios em falta. | R4: Tema do projeto discutido com o docente. | S4: DoD G08 v01: resultado produzido e acessível; critérios de aceitação cumpridos; revisão e auditoria concluídas; versão final aprovada, corretamente nomeada e arquivada na pasta prevista. | T4: Regulamento de Funcionamento da UC v19; template oficial da Proposta de Sistema. | U4: /projeto/04-artefactos-tecnicos/04.01-proposta-de-sistema-e-declaracao-de-ambito | V4: Sim | W4: Done | X4: Aprovada como Ready | Y4: 46283 | Z4: /projeto/01-artefactos-de-gestao/01.03-reunioes-de-grupo/m1-20260918-backlog-refinement-ata-v01.pdf | AA4: 2026-09-30 — Regularização documental: esta linha reconstitui trabalho efetivamente realizado durante a M1 com base nos artefactos existentes. O registo foi preparado posteriormente para completar a rastreabilidade do processo e não altera o conteúdo técnico entregue. 2026-10-20 — A versão m1 v03 mantém-se histórica; a evolução homologada v04 é registada na rebaseline M3. 2026-10-27 — Retificação da entrada de 2026-10-20 (proposta para o Backlog Refinement do Sprint 05): as versões v04 da Proposta de Sistema e da Declaração de Âmbito ficaram sem efeito. As versões homologadas pelo docente em 2026-10-21 são a Proposta de Sistema v05 (m3-proposta-sistema-v05, reposição integral da v03, sem alteração ao produto) e a Declaração de Âmbito v05 (m3-declaracao-ambito-v05, transição de F005 e F007 para o não-âmbito), com a Checklist de Controlo de Artefactos v07 (evidência: 04.02-homologacao-ps-da-cca/m3-resposta-email-homologacao-ps-da-cca-v03.pdf). O trabalho correspondente é registado em I150.
A5: I002 | B5: Elaborar Declaração de Âmbito | C5: Preparar a Declaração de Âmbito mantendo as funcionalidades da Proposta de Sistema e definindo o trabalho previsto no backend, frontend web e frontend mobile, exclusões e limites. | D5: Delimitar de forma verificável o âmbito do projeto e impedir divergências sobre o que deverá ser implementado nas milestones seguintes. | E5: Documentação | F5: m1-declaracao-ambito-v03.pdf | G5: 1 — Crítica | H5: m1 | I5: S01 | J5: 50 | K5: =IF(ISNUMBER(J5),J5*60%,IF(J5="","Por preencher",J5)) -> 30 | L5: =IF(ISNUMBER(J5),J5*30%,IF(J5="","Por preencher",J5)) -> 15 | M5: =IF(ISNUMBER(J5),J5*10%,IF(J5="","Por preencher",J5)) -> 5 | N5: Mantém todas as funcionalidades da PS pela mesma ordem; identifica backend, web e mobile; explicita elementos fora do âmbito e respetivas justificações; é coerente com a PS. | O5: m1-declaracao-ambito-v03.pdf; versões de trabalho; comparação com a PS; evidência de submissão para homologação. | P5: Comparar funcionalidade a funcionalidade com a PS; verificar limites, exclusões, coerência entre componentes, nomenclatura e completude. | Q5: Confirmar cobertura da revisão, correspondência PS↔DA, versão final, pasta de destino e inexistência de alterações não revistas. | R5: I001 — Proposta de Sistema. | S5: DoD G08 v01: resultado produzido e acessível; critérios de aceitação cumpridos; revisão e auditoria concluídas; versão final aprovada, corretamente nomeada e arquivada na pasta prevista. | T5: Regulamento de Funcionamento da UC v19; template oficial da Declaração de Âmbito; Proposta de Sistema. | U5: /projeto/04-artefactos-tecnicos/04.01-proposta-de-sistema-e-declaracao-de-ambito | V5: Sim | W5: Done | X5: Aprovada como Ready | Y5: 46283 | Z5: /projeto/01-artefactos-de-gestao/01.03-reunioes-de-grupo/m1-20260918-backlog-refinement-ata-v01.pdf | AA5: 2026-09-30 — Regularização documental: esta linha reconstitui trabalho efetivamente realizado durante a M1 com base nos artefactos existentes. O registo foi preparado posteriormente para completar a rastreabilidade do processo e não altera o conteúdo técnico entregue. 2026-10-20 — A versão m1 v03 mantém-se histórica; a evolução homologada v04 é registada na rebaseline M3. 2026-10-27 — Retificação da entrada de 2026-10-20 (proposta para o Backlog Refinement do Sprint 05): as versões v04 da Proposta de Sistema e da Declaração de Âmbito ficaram sem efeito. As versões homologadas pelo docente em 2026-10-21 são a Proposta de Sistema v05 (m3-proposta-sistema-v05, reposição integral da v03, sem alteração ao produto) e a Declaração de Âmbito v05 (m3-declaracao-ambito-v05, transição de F005 e F007 para o não-âmbito), com a Checklist de Controlo de Artefactos v07 (evidência: 04.02-homologacao-ps-da-cca/m3-resposta-email-homologacao-ps-da-cca-v03.pdf). O trabalho correspondente é registado em I150.
A6: I003 | B6: Preparar Checklist de Controlo de Artefactos (CCA) | C6: Preencher e manter a CCA cumulativa com os compromissos técnicos e de qualidade do produto assumidos pelo grupo, respetivas milestones, justificações, pastas e estado. | D6: Formalizar e controlar os artefactos que o grupo se compromete a entregar ao longo do projeto. | E6: Qualidade de processo | F6: m1-checklist-controlo-artefactos-v03.xlsx e m1-checklist-controlo-artefactos-v03.pdf | G6: 1 — Crítica | H6: m1 | I6: S01 | J6: 30 | K6: =IF(ISNUMBER(J6),J6*60%,IF(J6="","Por preencher",J6)) -> 18 | L6: =IF(ISNUMBER(J6),J6*30%,IF(J6="","Por preencher",J6)) -> 9 | M6: =IF(ISNUMBER(J6),J6*10%,IF(J6="","Por preencher",J6)) -> 3 | N6: CCA contém os compromissos aprovados; códigos, milestones, justificações e pastas são coerentes; versão editável e PDF congelado correspondem entre si. | O6: m1-checklist-controlo-artefactos-v03.xlsx; m1-checklist-controlo-artefactos-v03.pdf; histórico de alterações. | P6: Conferir códigos, artefactos, milestones, justificações, pastas e estados; comparar integralmente XLSX e PDF. | Q6: Confirmar revisão completa, coerência XLSX↔PDF, versão correta, assinatura aplicável e armazenamento na pasta regulamentar. | R6: I001; I002; decisões do grupo sobre compromissos adicionais. | S6: DoD G08 v01: resultado produzido e acessível; critérios de aceitação cumpridos; revisão e auditoria concluídas; versão final aprovada, corretamente nomeada e arquivada na pasta prevista. | T6: Regulamento de Funcionamento da UC v19; template oficial da CCA; PS e DA. | U6: /projeto/02-artefactos-de-qualidade-de-processo/02.03-checklist-de-controlo-de-artefactos | V6: Sim | W6: Done | X6: Aprovada como Ready | Y6: 46283 | Z6: /projeto/01-artefactos-de-gestao/01.03-reunioes-de-grupo/m1-20260918-backlog-refinement-ata-v01.pdf | AA6: 2026-09-30 — Regularização documental: esta linha reconstitui trabalho efetivamente realizado durante a M1 com base nos artefactos existentes. O registo foi preparado posteriormente para completar a rastreabilidade do processo e não altera o conteúdo técnico entregue. 2026-10-20 — A CCA histórica mantém-se; a atualização cumulativa da M3 é planeada separadamente.
A7: I004 | B7: Obter e arquivar homologação da PS, DA e CCA | C7: Submeter as versões identificadas da PS, DA e CCA ao docente, obter a homologação expressa por e-mail e preservar a evidência em PDF. | D7: Garantir a validação formal do volume de trabalho e conservar a evidência obrigatória da homologação. | E7: Administração ou logística | F7: m1-resposta-email-homologacao-ps-da-cca-v04.pdf | G7: 1 — Crítica | H7: m1 | I7: S01 | J7: 10 | K7: =IF(ISNUMBER(J7),J7*60%,IF(J7="","Por preencher",J7)) -> 6 | L7: =IF(ISNUMBER(J7),J7*30%,IF(J7="","Por preencher",J7)) -> 3 | M7: =IF(ISNUMBER(J7),J7*10%,IF(J7="","Por preencher",J7)) -> 1 | N7: Pedido identifica inequivocamente as versões de PS, DA e CCA; todos os elementos estão em CC; existe resposta expressa de homologação; e-mail é preservado em PDF. | O7: E-mail enviado com versões identificadas; resposta de homologação; m1-resposta-email-homologacao-ps-da-cca-v04.pdf | P7: Confirmar versões referidas no pedido e na resposta, destinatários/CC, existência de homologação expressa e correspondência com os ficheiros finais. | Q7: Confirmar autenticidade e legibilidade da evidência, correspondência das versões e arquivo no caminho regulamentar. | R7: I001; I002; I003. | S7: DoD G08 v01: resultado produzido e acessível; critérios de aceitação cumpridos; revisão e auditoria concluídas; versão final aprovada, corretamente nomeada e arquivada na pasta prevista. | T7: Regulamento de Funcionamento da UC v19 — homologação obrigatória da PS, DA e CCA. | U7: /projeto/04-artefactos-tecnicos/04.02-homologacao-ps-da-cca | V7: Sim | W7: Done | X7: Aprovada como Ready | Y7: 46283 | Z7: /projeto/01-artefactos-de-gestao/01.03-reunioes-de-grupo/m1-20260918-backlog-refinement-ata-v01.pdf | AA7: 2026-09-30 — Regularização documental: esta linha reconstitui trabalho efetivamente realizado durante a M1 com base nos artefactos existentes. O registo foi preparado posteriormente para completar a rastreabilidade do processo e não altera o conteúdo técnico entregue.
A8: I012 | B8: Especificação de Requisitos | C8: Elaborar a especificação dos requisitos funcionais e não funcionais do sistema de Gestão de Clínica Veterinária, derivados da Proposta de Sistema e da Declaração de Âmbito homologadas, identificando cada requisito de forma única e verificável. | D8: Definir formalmente o comportamento, regras, restrições e características de qualidade do sistema, constituindo a base para os casos de uso, arquitetura, modelos, implementação e testes. | E8: Requisitos | F8: m2-especificacao-requisitos-v01.md | G8: 1 — Crítica | H8: m2 | I8: S02 | J8: 50 | K8: =IF(ISNUMBER(J8),J8*60%,IF(J8="","Por preencher",J8)) -> 30 | L8: =IF(ISNUMBER(J8),J8*30%,IF(J8="","Por preencher",J8)) -> 15 | M8: =IF(ISNUMBER(J8),J8*10%,IF(J8="","Por preencher",J8)) -> 5 | N8: Todos os requisitos abrangidos pela PS e DA estão especificados; cada requisito possui identificador único, título e redação verificável; requisitos funcionais e não funcionais estão distinguidos; não existem requisitos contraditórios com o âmbito homologado; os requisitos cumprem os critérios de qualidade definidos pelo G08 e permitem rastreabilidade posterior na RTM. | O8: m2-especificacao-requisitos-v01.md; histórico de versões/commits; identificação das fontes PS e DA; versão final arquivada na pasta prevista. | P8: Comparar os requisitos com a PS e DA; verificar cobertura das funcionalidades e restrições; confirmar IDs únicos, clareza, completude, consistência, singularidade, verificabilidade e ausência de requisitos fora do âmbito. | Q8: Confirmar independência dos papéis; verificar que a revisão cobre os critérios definidos; confirmar que eventuais defeitos foram tratados; verificar versão final, nomenclatura, rastreabilidade e localização do ficheiro. | R8: I001 — Proposta de Sistema; I002 — Declaração de Âmbito; I009 — Critérios de Qualidade dos Requisitos. | S8: DoD G08 v01: resultado acessível; critérios de aceitação cumpridos; evidências produzidas; revisão e auditoria concluídas; versão final aceite e confirmada; aprovação posterior no Sprint Review. | T8: Regulamento de Funcionamento da UC v19; Proposta de Sistema v03; Declaração de Âmbito v03; Critérios de Qualidade dos Requisitos v01; Definition of Ready v01; Definition of Done v01. | U8: /projeto/04-artefactos-tecnicos/04.03-requisitos-e-rtm | V8: Sim | W8: Done | X8: Aprovada como Ready | Y8: 46296 | Z8: /projeto/01-artefactos-de-gestao/01.03-reunioes-de-grupo/m2-s02-backlog-refinement-ata-v01.pdf | AA8: 2026-10-06 — Tarefa acrescentada ao Backlog durante a preparação da M2; aguarda análise em Backlog Refinement. 2026-10-19 18:56 — Atualização do registo: aprovada como Ready no Backlog Refinement de 2026-10-01 (ata m2-s02-backlog-refinement-ata-v01, secção 4) e passou a Done no Sprint Review de 2026-10-08 (ata m2-s02-20261008-sprint-review-ata-v01, secção 6.6). A entrada de 2026-10-06 sobre aguardar análise fica ultrapassada. 2026-10-20 — A v01 mantém-se histórica; a Especificação de Requisitos v02 é registada na rebaseline M3. 2026-10-27 — Clarificação (proposta para o Backlog Refinement do Sprint 05): as referências à Proposta de Sistema v03 e à Declaração de Âmbito v03 dizem respeito à v01 histórica e mantêm-se. A Especificação de Requisitos v02 da rebaseline M3 tem como referência a Proposta de Sistema v05 e a Declaração de Âmbito v05, homologadas em 2026-10-21. 2026-10-27 — Correção da referência à ata (proposta para o Backlog Refinement do Sprint 05): o ficheiro arquivado chama-se m2-s02-backlog-refinement-ata-v01.pdf; o nome anterior não correspondia a nenhum ficheiro.
A9: I013 | B9: Checklist de Aprovação dos Requisitos | C9: Preencher a Checklist de Aprovação dos Requisitos utilizando o template oficial, avaliando individualmente todos os requisitos funcionais e não funcionais especificados face aos critérios de qualidade definidos pelo Grupo G08. | D9: Demonstrar de forma objetiva e rastreável que cada requisito foi verificado e aprovado segundo os critérios de qualidade definidos pelo grupo. | E9: Qualidade de produto | F9: m2-checklist-aprovacao-requisitos-v01.xlsx | G9: 1 — Crítica | H9: m2 | I9: S02 | J9: 30 | K9: =IF(ISNUMBER(J9),J9*60%,IF(J9="","Por preencher",J9)) -> 18 | L9: =IF(ISNUMBER(J9),J9*30%,IF(J9="","Por preencher",J9)) -> 9 | M9: =IF(ISNUMBER(J9),J9*10%,IF(J9="","Por preencher",J9)) -> 3 | N9: É utilizado o template oficial; existe uma linha por cada requisito da Especificação de Requisitos; cada linha contém o ID e o título correspondentes; existe uma coluna independente por cada critério de qualidade definido pelo grupo; cada critério contém exclusivamente "Cumpre", "Não cumpre" ou "Não aplicável", em caso de não cumprimento ou não aplicável deve indicar-se a causa; o Resultado Final contém exclusivamente "Aprovado" ou "Não aprovado"; todos os requisitos considerados aprovados possuem Resultado Final "Aprovado". | O9: m2-checklist-aprovacao-requisitos-v01.xlsx preenchida; Especificação de Requisitos utilizada como fonte; m1-criterios-qualidade-requisitos-v01.md; histórico de alterações da checklist. | P9: Confirmar correspondência entre todas as linhas da checklist e os requisitos da Especificação de Requisitos; verificar aplicação dos 11 critérios de qualidade; confirmar que "Não cumpre" e "Não aplicável" possuem justificação objetiva; verificar coerência do Resultado Final de cada requisito. | Q9: Confirmar que todos os requisitos foram abrangidos; verificar independência e completude da revisão; confirmar utilização correta do template e dos valores permitidos; verificar correspondência entre requisito, critérios e Resultado Final; confirmar versão, nomenclatura e pasta de destino. | R9: I009 — Critérios de Qualidade dos Requisitos; I012 — Especificação de Requisitos. | S9: DoD G08 v01: resultado produzido e acessível; critérios de aceitação cumpridos; evidências arquivadas; revisão e auditoria concluídas; versão final aceite e confirmada; aprovação no Sprint Review. | T9: Regulamento de Funcionamento da UC v19; m1-criterios-qualidade-requisitos-v01.md; m2-especificacao-requisitos-v01.md; template oficial da Checklist de Aprovação dos Requisitos; Plano de Qualidade do Processo G08; Definition of Done G08 v01. | U9: /projeto/04-artefactos-tecnicos/04.03-requisitos-e-rtm | V9: Sim | W9: Done | X9: Aprovada como Ready | Y9: 46296 | Z9: /projeto/01-artefactos-de-gestao/01.03-reunioes-de-grupo/m2-s02-backlog-refinement-ata-v01.pdf | AA9: 2026-10-06 — Tarefa acrescentada ao Backlog durante a preparação da M2; aguarda análise em Backlog Refinement. 2026-10-19 18:56 — Atualização do registo: aprovada como Ready no Backlog Refinement de 2026-10-01 (ata m2-s02-backlog-refinement-ata-v01, secção 4) e passou a Done no Sprint Review de 2026-10-08 (ata m2-s02-20261008-sprint-review-ata-v01, secção 6.6). A entrada de 2026-10-06 sobre aguardar análise fica ultrapassada. 2026-10-20 — A v01 mantém-se histórica; a Checklist de Aprovação v02 é registada na rebaseline M3. 2026-10-27 — Correção da referência à ata (proposta para o Backlog Refinement do Sprint 05): o ficheiro arquivado chama-se m2-s02-backlog-refinement-ata-v01.pdf; o nome anterior não correspondia a nenhum ficheiro.
A10: I025 | B10: Desenvolver Backend | C10: Contentor do desenvolvimento do backend/API REST para as funcionalidades ativas F001, F002, F003, F004 e F006. O backend deve evoluir da base técnica criada em S03 para a stack corrente do grupo — C# 14, .NET 10, ASP.NET Core 10 e Entity Framework Core 10 — mantendo a arquitetura em camadas e excluindo totalmente gestão financeira e internamento/hospitalização. | D10: Disponibilizar um backend funcional, documentado e coerente com a baseline v02 e com a stack técnica corrente, cobrindo apenas F001, F002, F003, F004 e F006 e servindo de base aos frontends da M4. | E10: Desenvolvimento | F10: Backend funcional e documentado para o âmbito v02 da M3, integrado no repositório e coerente com Requisitos v02, Casos de Uso v02, Modelo de Dados v02, Arquitetura v02 e API v02. | G10: 1 — Crítica | H10: m3 | I10: Não definido | J10: Não aprovado | K10: =IF(ISNUMBER(J10),J10*60%,IF(J10="","Por preencher",J10)) -> Não aprovado | L10: =IF(ISNUMBER(J10),J10*30%,IF(J10="","Por preencher",J10)) -> Não aprovado | M10: =IF(ISNUMBER(J10),J10*10%,IF(J10="","Por preencher",J10)) -> Não aprovado | N10: Contentor: sem critérios próprios. Fica concluído quando todas as tarefas filhas indicadas na descrição estiverem em Done e o resultado agregado descrito em «Resultado esperado» estiver completo e coerente. | O10: Não aplicável — as evidências são produzidas nas tarefas filhas. | P10: Não aplicável — a revisão é feita nas tarefas filhas. | Q10: Não aplicável — a auditoria é feita nas tarefas filhas. Confirmar apenas, no fecho, que nenhuma filha ficou por concluir. | R10: I012, I015, I016, I019, I018, I020 e I026. Articulação com testes, pipeline e documentação da M3. | S10: Contentor, sem DoD própria: fica Done quando todas as tarefas filhas estiverem Done. Cada filha cumpre a DoD G08 v01 (resultado produzido e acessível; critérios de aceitação cumpridos; revisão e auditoria concluídas; versão final aprovada, corretamente nomeada e arquivada na pasta prevista). O contentor não é executado, revisto nem auditado como tarefa autónoma. | T10: Regulamento de Funcionamento da UC v19, secção 19 (04.12-backend/m3-v01); Especificação de Requisitos v02 (I012); Casos de Uso v02 (I015); Modelo de Dados v02 (I016); Arquitetura v02 (I019); Documentação de API v02 (I018); Modelo de Classes Backend v02 (I020). | U10: /projeto/04-artefactos-tecnicos/04.12-backend/m3-v01 | V10: Não | W10: Pendente | X10: Não analisada | AA10: 2026-10-14 23:05 — Proposta de refinamento preparada como versão de trabalho. Esta Issue original passa a contentor (épico) e deixa de ser executada diretamente: o trabalho foi dividido nas tarefas I058, I059, I063, I064, I065, I066, I067, I068, I069, I070, I071, I072, I073, I074, I075, I076, I077, I078, I079, I080, I081, I082, I083, I084, I085. Não tem pontos próprios, para que os pontos não sejam contados em duplicado. Ainda não analisada em Backlog Refinement; a divisão e as decisões estão por ratificar. 2026-10-19 18:56 — Removidas a data e a ata de decisão: esta Issue-contentor não recebeu decisão de Ready no Backlog Refinement de 2026-10-12, por não ser executada diretamente; a v01 citava um nome de ata inexistente (m3-20261012…). A divisão desta Issue em tarefas executáveis foi aprovada no Backlog Refinement de 2026-10-12 (ata m3-s03-20261012-backlog-refinement-ata-v01, secção 6, deliberação 2).
A11: I026 | B11: Preparar migrations, dados iniciais e reposição da base de dados | C11: Contentor da preparação da persistência e dos artefactos de base de dados da baseline v02. As EF Core 10 Migrations constituem a fonte versionada de implementação do esquema SQL Server 2025; dados iniciais, reposição por ambiente e eventuais scripts SQL derivados devem ser coerentes com essas migrations e não criar uma segunda fonte de verdade. | D11: Garantir que qualquer elemento consegue criar, migrar, popular e repor uma instância isolada da base de dados a partir das EF Core Migrations, sem manter um esquema SQL concorrente. | E11: Desenvolvimento | F11: Persistência Entity Framework Core 10.0, migrations, dados fictícios de demonstração e procedimento de reposição coerentes com o Modelo de Dados v02, com scripts SQL derivados das migrations quando exigidos para entrega. | G11: 1 — Crítica | H11: m3 | I11: Não definido | J11: Não aprovado | K11: =IF(ISNUMBER(J11),J11*60%,IF(J11="","Por preencher",J11)) -> Não aprovado | L11: =IF(ISNUMBER(J11),J11*30%,IF(J11="","Por preencher",J11)) -> Não aprovado | M11: =IF(ISNUMBER(J11),J11*10%,IF(J11="","Por preencher",J11)) -> Não aprovado | N11: Contentor: sem critérios próprios. Fica concluído quando todas as tarefas filhas indicadas na descrição estiverem em Done e o resultado agregado descrito em «Resultado esperado» estiver completo e coerente. | O11: Não aplicável — as evidências são produzidas nas tarefas filhas. | P11: Não aplicável — a revisão é feita nas tarefas filhas. | Q11: Não aplicável — a auditoria é feita nas tarefas filhas. Confirmar apenas, no fecho, que nenhuma filha ficou por concluir. | R11: I016 — Modelo de Dados v02; I019 — Documentação da Arquitetura v02; I020 — Modelo de Classes Backend v02. | S11: Contentor, sem DoD própria: fica Done quando todas as tarefas filhas estiverem Done. Cada filha cumpre a DoD G08 v01 (resultado produzido e acessível; critérios de aceitação cumpridos; revisão e auditoria concluídas; versão final aprovada, corretamente nomeada e arquivada na pasta prevista). O contentor não é executado, revisto nem auditado como tarefa autónoma. | T11: Regulamento de Funcionamento da UC v19, secção 19 (04.13) e secção 20.2; Modelo de Dados v02 (I016); Arquitetura v02 (I019); Modelo de Classes Backend v02 (I020); documentação oficial do Entity Framework Core 10. | U11: /projeto/04-artefactos-tecnicos/04.13-scripts-de-base-de-dados/m3-v01 | V11: Não | W11: Pendente | X11: Não analisada | AA11: 2026-10-14 23:05 — Proposta de refinamento preparada como versão de trabalho. Esta Issue original passa a contentor (épico) e deixa de ser executada diretamente: o trabalho foi dividido nas tarefas I060, I061, I062. Não tem pontos próprios, para que os pontos não sejam contados em duplicado. Ainda não analisada em Backlog Refinement; a divisão e as decisões estão por ratificar. 2026-10-19 18:56 — Removidas a data e a ata de decisão: esta Issue-contentor não recebeu decisão de Ready no Backlog Refinement de 2026-10-12, por não ser executada diretamente; a v01 citava um nome de ata inexistente (m3-20261012…). A divisão desta Issue em tarefas executáveis foi aprovada no Backlog Refinement de 2026-10-12 (ata m3-s03-20261012-backlog-refinement-ata-v01, secção 6, deliberação 2).
A12: I031 | B12: Implementar e Executar Testes de Integração do Backend | C12: Contentor da infraestrutura, implementação e execução dos testes de integração do backend para as áreas ativas F001, F002, F003, F004 e F006. Deve validar integração real entre API, autorização, persistência SQL Server, migrations, propriedade dos dados e regras de concorrência aplicáveis, produzindo no final evidência formal dos resultados. | D12: Comprovar automaticamente que os componentes do backend funcionam em conjunto, incluindo persistência, autorização por perfil/propriedade e regras de concorrência aplicáveis. | E12: Teste | F12: Código dos testes de integração no projeto de testes do backend (04.12-backend/m3-v01) e m3-resultados-testes-integracao-backend-v01.pdf. | G12: 1 — Crítica | H12: m3 | I12: Não definido | J12: Não aprovado | K12: =IF(ISNUMBER(J12),J12*60%,IF(J12="","Por preencher",J12)) -> Não aprovado | L12: =IF(ISNUMBER(J12),J12*30%,IF(J12="","Por preencher",J12)) -> Não aprovado | M12: =IF(ISNUMBER(J12),J12*10%,IF(J12="","Por preencher",J12)) -> Não aprovado | N12: Contentor: sem critérios próprios. Fica concluído quando todas as tarefas filhas indicadas na descrição estiverem em Done e o resultado agregado descrito em «Resultado esperado» estiver completo e coerente. | O12: Não aplicável — as evidências são produzidas nas tarefas filhas. | P12: Não aplicável — a revisão é feita nas tarefas filhas. | Q12: Não aplicável — a auditoria é feita nas tarefas filhas. Confirmar apenas, no fecho, que nenhuma filha ficou por concluir. | R12: I025, I026 e I030. | S12: Contentor, sem DoD própria: fica Done quando todas as tarefas filhas estiverem Done. Cada filha cumpre a DoD G08 v01 (resultado produzido e acessível; critérios de aceitação cumpridos; revisão e auditoria concluídas; versão final aprovada, corretamente nomeada e arquivada na pasta prevista). O contentor não é executado, revisto nem auditado como tarefa autónoma. | T12: Regulamento de Funcionamento da UC v19, secção 19 (03.01.03-testes-de-integracao); Especificação de Testes de Integração (I030); Documentação de API v02 (I018). | U12: /projeto/03-artefactos-de-qualidade-de-produto/03.01-backend/03.01.03-testes-de-integracao | V12: Não | W12: Pendente | X12: Não analisada | AA12: 2026-10-14 23:05 — Proposta de refinamento preparada como versão de trabalho. Esta Issue original passa a contentor (épico) e deixa de ser executada diretamente: o trabalho foi dividido nas tarefas I091, I092, I093, I094, I095, I096, I097. Não tem pontos próprios, para que os pontos não sejam contados em duplicado. Ainda não analisada em Backlog Refinement; a divisão e as decisões estão por ratificar. 2026-10-19 18:56 — Removidas a data e a ata de decisão: esta Issue-contentor não recebeu decisão de Ready no Backlog Refinement de 2026-10-12, por não ser executada diretamente; a v01 citava um nome de ata inexistente (m3-20261012…). A divisão desta Issue em tarefas executáveis foi aprovada no Backlog Refinement de 2026-10-12 (ata m3-s03-20261012-backlog-refinement-ata-v01, secção 6, deliberação 2).
A13: I035 | B13: Implementar a pipeline CI/CD do backend | C13: Contentor da pipeline CI/CD do backend em GitHub Actions, executada em runner ubuntu-latest. Deve incluir restore, compilação sem erros, formatação, testes unitários e de integração, cobertura mínima de 70%, análise estática, execução da Collection Postman quando integrada e restantes quality gates aplicáveis, bloqueando o Pull Request quando alguma verificação obrigatória falha. | D13: Garantir que cada alteração ao backend é verificada automaticamente e que nenhuma integração avança quando falha um quality gate obrigatório. | E13: DevOps / CI/CD | F13: Workflows de GitHub Actions da M3 versionados no repositório e arquivados em 04.16-ci-cd/m3-v01, com pipeline do backend funcional e quality gates aplicáveis. | G13: 1 — Crítica | H13: m3 | I13: Não definido | J13: Não aprovado | K13: =IF(ISNUMBER(J13),J13*60%,IF(J13="","Por preencher",J13)) -> Não aprovado | L13: =IF(ISNUMBER(J13),J13*30%,IF(J13="","Por preencher",J13)) -> Não aprovado | M13: =IF(ISNUMBER(J13),J13*10%,IF(J13="","Por preencher",J13)) -> Não aprovado | N13: Contentor: sem critérios próprios. Fica concluído quando todas as tarefas filhas indicadas na descrição estiverem em Done e o resultado agregado descrito em «Resultado esperado» estiver completo e coerente. | O13: Não aplicável — as evidências são produzidas nas tarefas filhas. | P13: Não aplicável — a revisão é feita nas tarefas filhas. | Q13: Não aplicável — a auditoria é feita nas tarefas filhas. Confirmar apenas, no fecho, que nenhuma filha ficou por concluir. | R13: I019 e estrutura do projeto (I025), com integração progressiva dos testes (I029 e I031) e da análise estática (I034). | S13: Contentor, sem DoD própria: fica Done quando todas as tarefas filhas estiverem Done. Cada filha cumpre a DoD G08 v01 (resultado produzido e acessível; critérios de aceitação cumpridos; revisão e auditoria concluídas; versão final aprovada, corretamente nomeada e arquivada na pasta prevista). O contentor não é executado, revisto nem auditado como tarefa autónoma. | T13: Regulamento de Funcionamento da UC v19, secção 19 (04.16-ci-cd) e secção 17; Regulamento Interno do Grupo G08 v02 (proposta); documentação oficial do GitHub Actions. | U13: /projeto/04-artefactos-tecnicos/04.16-ci-cd/m3-v01 | V13: Não | W13: Pendente | X13: Não analisada | AA13: 2026-10-14 23:05 — Proposta de refinamento preparada como versão de trabalho. Esta Issue original passa a contentor (épico) e deixa de ser executada diretamente: o trabalho foi dividido nas tarefas I102, I103, I104. Não tem pontos próprios, para que os pontos não sejam contados em duplicado. Ainda não analisada em Backlog Refinement; a divisão e as decisões estão por ratificar. 2026-10-19 18:56 — Removidas a data e a ata de decisão: esta Issue-contentor não recebeu decisão de Ready no Backlog Refinement de 2026-10-12, por não ser executada diretamente; a v01 citava um nome de ata inexistente (m3-20261012…). A divisão desta Issue em tarefas executáveis foi aprovada no Backlog Refinement de 2026-10-12 (ata m3-s03-20261012-backlog-refinement-ata-v01, secção 6, deliberação 2).
A14: I040 | B14: Desenvolver Frontend Web | C14: Contentor do desenvolvimento do Frontend Web para Administrador, Rececionista, Veterinário e Auxiliar Veterinário, usando TypeScript 6.0, React 19.3, Node.js 24 LTS, Vite 8.3 e npm 12. Abrange apenas F001, F002, F003, F004 e F006 e consome a API; gestão financeira e internamento ficam excluídos. | D14: Disponibilizar o Frontend Web funcional e integrado com o backend para todo o âmbito Web ativo da baseline v02. | E14: Desenvolvimento | F14: Código-fonte do frontend web em React 19.3/TypeScript 6.0, integrado com o backend e executável, arquivado em /projeto/04-artefactos-tecnicos/04.14-frontend-web/m4-v01. | G14: 1 — Crítica | H14: m4 | I14: Não definido | J14: Não aprovado | K14: =IF(ISNUMBER(J14),J14*60%,IF(J14="","Por preencher",J14)) -> Não aprovado | L14: =IF(ISNUMBER(J14),J14*30%,IF(J14="","Por preencher",J14)) -> Não aprovado | M14: =IF(ISNUMBER(J14),J14*10%,IF(J14="","Por preencher",J14)) -> Não aprovado | N14: Contentor: sem critérios próprios. Fica concluído quando todas as tarefas filhas indicadas na descrição estiverem em Done e o resultado agregado descrito em «Resultado esperado» estiver completo e coerente. | O14: Não aplicável — as evidências são produzidas nas tarefas filhas. | P14: Não aplicável — a revisão é feita nas tarefas filhas. | Q14: Não aplicável — a auditoria é feita nas tarefas filhas. Confirmar apenas, no fecho, que nenhuma filha ficou por concluir. | R14: I012, I015, I018, I017, I021 e backend M3 (I025). | S14: Contentor, sem DoD própria: fica Done quando todas as tarefas filhas estiverem Done. Cada filha cumpre a DoD G08 v01 (resultado produzido e acessível; critérios de aceitação cumpridos; revisão e auditoria concluídas; versão final aprovada, corretamente nomeada e arquivada na pasta prevista). O contentor não é executado, revisto nem auditado como tarefa autónoma. | T14: Regulamento de Funcionamento da UC v19, secção 19 (04.14-frontend-web/m4-v01); Regulamento Interno do Grupo G08 v02 (proposta); Protótipo v02 (I017); Modelo de Classes Frontend Web v02 (I021); Documentação de API v02 (I018); documentação oficial de React 19.3, TypeScript 6, Node.js 24 LTS e Vite 8.3. | U14: /projeto/04-artefactos-tecnicos/04.14-frontend-web/m4-v01 | V14: Não | W14: Pendente | X14: Não analisada | AA14: 2026-10-14 23:05 — Proposta de refinamento preparada como versão de trabalho. Esta Issue original passa a contentor (épico) e deixa de ser executada diretamente: o trabalho foi dividido nas tarefas I107, I108, I109, I110, I111, I112, I113, I114, I115, I116, I117, I118, I119. Não tem pontos próprios, para que os pontos não sejam contados em duplicado. Ainda não analisada em Backlog Refinement; a divisão e as decisões estão por ratificar.
A15: I041 | B15: Desenvolver Frontend Mobile | C15: Contentor do desenvolvimento da aplicação Android destinada exclusivamente ao perfil Cliente, usando Kotlin 2.2, Jetpack Compose, Material 3, Android SDK API 37 com minSdk 26, JDK 21, Gradle 9.6 e Android Gradle Plugin 9.4. A aplicação permite autenticação e consulta dos próprios animais, Consultas futuras, histórico administrativo e boletim de vacinação/desparasitação, sem financeiro, registo clínico ou internamento. | D15: Disponibilizar a aplicação Android funcional e integrada com o backend para todo o âmbito Mobile do Cliente previsto na baseline v02. | E15: Desenvolvimento | F15: Código-fonte do frontend mobile Android em Kotlin 2.2/Jetpack Compose, integrado com o backend e executável, arquivado em /projeto/04-artefactos-tecnicos/04.15-frontend-mobile/m4-v01. | G15: 1 — Crítica | H15: m4 | I15: Não definido | J15: Não aprovado | K15: =IF(ISNUMBER(J15),J15*60%,IF(J15="","Por preencher",J15)) -> Não aprovado | L15: =IF(ISNUMBER(J15),J15*30%,IF(J15="","Por preencher",J15)) -> Não aprovado | M15: =IF(ISNUMBER(J15),J15*10%,IF(J15="","Por preencher",J15)) -> Não aprovado | N15: Contentor: sem critérios próprios. Fica concluído quando todas as tarefas filhas indicadas na descrição estiverem em Done e o resultado agregado descrito em «Resultado esperado» estiver completo e coerente. | O15: Não aplicável — as evidências são produzidas nas tarefas filhas. | P15: Não aplicável — a revisão é feita nas tarefas filhas. | Q15: Não aplicável — a auditoria é feita nas tarefas filhas. Confirmar apenas, no fecho, que nenhuma filha ficou por concluir. | R15: I012, I015, I018, I017, I022 e backend M3 (I025). | S15: Contentor, sem DoD própria: fica Done quando todas as tarefas filhas estiverem Done. Cada filha cumpre a DoD G08 v01 (resultado produzido e acessível; critérios de aceitação cumpridos; revisão e auditoria concluídas; versão final aprovada, corretamente nomeada e arquivada na pasta prevista). O contentor não é executado, revisto nem auditado como tarefa autónoma. | T15: Regulamento de Funcionamento da UC v19, secção 19 (04.15-frontend-mobile/m4-v01); Regulamento Interno do Grupo G08 v02 (proposta); Protótipo v02 (I017); Modelo de Classes Frontend Mobile v02 (I022); Documentação de API v02 (I018); documentação oficial de Kotlin 2.2, Jetpack Compose, Material 3, Android API 37, JDK 21 e Gradle/AGP. | U15: /projeto/04-artefactos-tecnicos/04.15-frontend-mobile/m4-v01 | V15: Não | W15: Pendente | X15: Não analisada | AA15: 2026-10-14 23:05 — Proposta de refinamento preparada como versão de trabalho. Esta Issue original passa a contentor (épico) e deixa de ser executada diretamente: o trabalho foi dividido nas tarefas I120, I121, I122, I123, I124. Não tem pontos próprios, para que os pontos não sejam contados em duplicado. Ainda não analisada em Backlog Refinement; a divisão e as decisões estão por ratificar.
A16: I042 | B16: Integrar Frontends com Backend | C16: Contentor da validação integrada dos Frontends Web e Mobile com o backend: configuração de URLs/CORS, autenticação e sessão, tratamento coerente de erros, autorização por perfil/propriedade e execução ponta a ponta dos fluxos ativos. Os defeitos de integração devem ser corrigidos ou registados com rastreabilidade. | D16: Garantir que Web e Mobile funcionam ponta a ponta com o backend e respeitam autenticação, autorização, propriedade e tratamento de erros definidos. | E16: Desenvolvimento | F16: Fluxos web e mobile validados contra o backend, defeitos de integração corrigidos ou registados e evidência de execução. | G16: 1 — Crítica | H16: m4 | I16: Não definido | J16: Não aprovado | K16: =IF(ISNUMBER(J16),J16*60%,IF(J16="","Por preencher",J16)) -> Não aprovado | L16: =IF(ISNUMBER(J16),J16*30%,IF(J16="","Por preencher",J16)) -> Não aprovado | M16: =IF(ISNUMBER(J16),J16*10%,IF(J16="","Por preencher",J16)) -> Não aprovado | N16: Contentor: sem critérios próprios. Fica concluído quando todas as tarefas filhas indicadas na descrição estiverem em Done e o resultado agregado descrito em «Resultado esperado» estiver completo e coerente. | O16: Não aplicável — as evidências são produzidas nas tarefas filhas. | P16: Não aplicável — a revisão é feita nas tarefas filhas. | Q16: Não aplicável — a auditoria é feita nas tarefas filhas. Confirmar apenas, no fecho, que nenhuma filha ficou por concluir. | R16: I040, I041 e backend da M3 (I025). | S16: Contentor, sem DoD própria: fica Done quando todas as tarefas filhas estiverem Done. Cada filha cumpre a DoD G08 v01 (resultado produzido e acessível; critérios de aceitação cumpridos; revisão e auditoria concluídas; versão final aprovada, corretamente nomeada e arquivada na pasta prevista). O contentor não é executado, revisto nem auditado como tarefa autónoma. | T16: Regulamento de Funcionamento da UC v19, secção 19 (04.14 e 04.15); Arquitetura v02 (I019); Documentação de API v02 (I018); bases dos frontends Web (I040) e Mobile (I041). | U16: /projeto/04-artefactos-tecnicos/04.14-frontend-web/m4-v01; /projeto/04-artefactos-tecnicos/04.15-frontend-mobile/m4-v01 | V16: Não | W16: Pendente | X16: Não analisada | AA16: 2026-10-14 23:05 — Proposta de refinamento preparada como versão de trabalho. Esta Issue original passa a contentor (épico) e deixa de ser executada diretamente: o trabalho foi dividido nas tarefas I125, I126, I127. Não tem pontos próprios, para que os pontos não sejam contados em duplicado. Ainda não analisada em Backlog Refinement; a divisão e as decisões estão por ratificar.
A17: I052 | B17: Atualizar Pipeline CI/CD para sistema completo | C17: Contentor da evolução da pipeline para o sistema completo em GitHub Actions, integrando backend, Frontend Web e Frontend Mobile. Deve aplicar os quality gates do Regulamento aos três componentes, produzir os artefactos previstos e bloquear integração/entrega perante qualquer incumprimento obrigatório. | D17: Garantir que backend, Frontend Web e aplicação Android são verificados automaticamente em cada alteração pelos quality gates aplicáveis. | E17: DevOps / CI/CD | F17: Configuração GitHub Actions atualizada para o sistema completo, arquivada em 04.16-ci-cd/m4-v02, e m4-descricao-pipeline-ci-cd-v02.md. | G17: 1 — Crítica | H17: m4 | I17: Não definido | J17: Não aprovado | K17: =IF(ISNUMBER(J17),J17*60%,IF(J17="","Por preencher",J17)) -> Não aprovado | L17: =IF(ISNUMBER(J17),J17*30%,IF(J17="","Por preencher",J17)) -> Não aprovado | M17: =IF(ISNUMBER(J17),J17*10%,IF(J17="","Por preencher",J17)) -> Não aprovado | N17: Contentor: sem critérios próprios. Fica concluído quando todas as tarefas filhas indicadas na descrição estiverem em Done e o resultado agregado descrito em «Resultado esperado» estiver completo e coerente. | O17: Não aplicável — as evidências são produzidas nas tarefas filhas. | P17: Não aplicável — a revisão é feita nas tarefas filhas. | Q17: Não aplicável — a auditoria é feita nas tarefas filhas. Confirmar apenas, no fecho, que nenhuma filha ficou por concluir. | R17: I035, I040, I041, I046 e I050. | S17: Contentor, sem DoD própria: fica Done quando todas as tarefas filhas estiverem Done. Cada filha cumpre a DoD G08 v01 (resultado produzido e acessível; critérios de aceitação cumpridos; revisão e auditoria concluídas; versão final aprovada, corretamente nomeada e arquivada na pasta prevista). O contentor não é executado, revisto nem auditado como tarefa autónoma. | T17: Regulamento de Funcionamento da UC v19, secção 19 (04.16-ci-cd/m4-v02) e secção 17; Regulamento Interno do Grupo G08 v02 (proposta); documentação oficial do GitHub Actions. | U17: /projeto/04-artefactos-tecnicos/04.16-ci-cd/m4-v02 | V17: Não | W17: Pendente | X17: Não analisada | AA17: 2026-10-14 23:05 — Proposta de refinamento preparada como versão de trabalho. Esta Issue original passa a contentor (épico) e deixa de ser executada diretamente: o trabalho foi dividido nas tarefas I142, I143, I144. Não tem pontos próprios, para que os pontos não sejam contados em duplicado. Ainda não analisada em Backlog Refinement; a divisão e as decisões estão por ratificar.
A18: I058 | B18: Criar a solução .NET 8 do backend e a infraestrutura transversal da API | C18: Criar a solução .NET 8 com os projetos Api, Application, Domain e Infrastructure e os projetos de teste xUnit (unitários e de integração), segundo a Documentação da Arquitetura (I019) e o Modelo de Classes do Backend (I020). Configurar injeção de dependências, configuração por ambiente (ficheiro e variáveis de ambiente), Swagger/OpenAPI com esquema Bearer, CORS para o frontend web, registo de logs e um middleware único de tratamento de erros que converte exceções de validação, autenticação, autorização, recurso inexistente, conflito e regra de negócio nos códigos 400, 401, 403, 404, 409 e 422 do contrato. Não inclui endpoints de negócio nem acesso a dados. | D18: Dar à equipa uma base reproduzível e comum, para que as restantes tarefas do backend avancem em paralelo, sem conflitos de estrutura nem respostas de erro inconsistentes. | E18: Desenvolvimento | F18: Solução .NET 8 compilável e executável, com middleware de erros e Swagger a funcionar e README técnico do projeto, no repositório do backend (arquivo final em /projeto/04-artefactos-tecnicos/04.12-backend/m3-v01). | G18: 1 — Crítica | H18: m3 | I18: S03 | J18: 50 | K18: =IF(ISNUMBER(J18),J18*60%,IF(J18="","Por preencher",J18)) -> 30 | L18: =IF(ISNUMBER(J18),J18*30%,IF(J18="","Por preencher",J18)) -> 15 | M18: =IF(ISNUMBER(J18),J18*10%,IF(J18="","Por preencher",J18)) -> 5 | N18: 1. `dotnet build` e `dotnet test` terminam sem erros num clone limpo, com SDK .NET 8; os projetos de teste existem e executam (ainda sem casos de negócio). 2. A estrutura de projetos e dependências cumpre I019/I020: o projeto Domain não referencia nenhum outro projeto e a Api só depende de Application e Infrastructure. 3. A cadeia de ligação, a chave JWT, a validade do token (8 h) e o CORS são lidos de ficheiro por ambiente e de variáveis de ambiente; não há segredos versionados e existe um ficheiro de exemplo sem valores reais. 4. O middleware devolve sempre JSON com o mesmo formato (código, mensagem e detalhe de validação) para 400, 401, 403, 404, 409 e 422, demonstrado com uma exceção de cada tipo. 5. O Swagger/OpenAPI está disponível em ambiente de desenvolvimento com autorização Bearer configurada. 6. Os logs registam pedido, resultado e erros sem escrever palavras-passe nem tokens. 7. O README explica pré-requisitos, como compilar, configurar e arrancar a API localmente. | O18: 1. Merge Request com a solução e o README técnico. 2. Registo da execução de `dotnet build` e `dotnet test` (consola ou log da pipeline). 3. Exemplos de respostas de erro para cada código tratado. 4. Lista das variáveis de configuração necessárias. | P18: 1. Clonar o repositório, compilar e arrancar a API num ambiente limpo, seguindo apenas o README. 2. Verificar as referências entre projetos e confirmar que Domain não depende de Infrastructure. 3. Pesquisar no histórico Git a presença de segredos (cadeias de ligação, chaves). 4. Provocar cada tipo de erro e confirmar formato e código HTTP; confirmar que os logs não expõem dados sensíveis. | Q18: Checklist de auditoria 02.05 completa: independência dos três papéis, relatório de revisão 02.04, prazos de 48 h e 24 h, pontos, versão final e pasta. Confirmar que a estrutura criada corresponde à arquitetura aprovada e que o README permite reproduzir o arranque sem ajuda do Executor. | R18: I019 — Documentação da Arquitetura; I020 — Modelo de Classes - Backend; I018 — Documentação de API. | S18: DoD G08 v01: resultado produzido e acessível; critérios de aceitação cumpridos; revisão e auditoria concluídas; versão final aprovada, corretamente nomeada e arquivada na pasta prevista. Em código: integrado no repositório por Merge Request aprovado pelo Revisor, conforme o regulamento interno do grupo; compila e passa na verificação local sem erros; sem segredos no repositório; divergências face à Documentação de API ou ao Modelo de Dados registadas e decididas. | T18: Documentação da Arquitetura m2 (I019); Modelo de Classes - Backend (I020); Documentação de API (I018); documentação oficial ASP.NET Core 8; Regulamento de Funcionamento da UC v19, secção 19 (04.12). | U18: /projeto/04-artefactos-tecnicos/04.12-backend/m3-v01 (código desenvolvido no repositório Git do grupo e arquivado nesta pasta na entrega da M3) | V18: Sim | W18: Done | X18: Aprovada como Ready | Y18: 46307 | Z18: /projeto/01-artefactos-de-gestao/01.03-reunioes-de-grupo/m3-s03-20261012-backlog-refinement-ata-v01.pdf | AA18: 2026-10-14 23:05 — Tarefa criada na proposta de refinamento (versão de trabalho), por divisão da Issue original I025 «Desenvolver Backend». Ainda não analisada em Backlog Refinement: orçamento, DoR e decisão por ratificar. 2026-10-19 18:56 — Reconciliação documental para a versão de trabalho v02 (a apreciar no Backlog Refinement de 2026-10-19; os PDFs já assinados não são alterados). O orçamento 50/30/15/5 e a decisão «Aprovada como Ready» foram aprovados no Backlog Refinement de 2026-10-12 (ata m3-s03-20261012-backlog-refinement-ata-v01, secção 4), que a v01 ainda registava como «Não analisada» / «Por verificar». Executada no Sprint 03: PR #150 (commit c923cd5 em develop; promovida para main pela PR #155, commit 6802187). Revisão e auditoria concluídas em 2026-10-17 (relatório de revisão e checklist de auditoria da I058); o Sprint Review de 2026-10-17 (ata m3-s03-20261017-sprint-review-ata-v01) aprovou a passagem a Done. Estado atualizado de Pendente para Done.
A19: I059 | B19: Implementar a camada de persistência com Entity Framework Core | C19: Antes de implementar a persistência funcional, migrar a solução backend criada em S03 de .NET 8 para .NET 10 e atualizar os pacotes compatíveis, preservando a arquitetura e o comportamento transversal já aprovado. Depois, implementar na Infrastructure o DbContext e os mapeamentos EF Core 10/Fluent API segundo o Modelo de Dados v02, incluindo relações, índices, restrições, enumerações, DeleteBehavior.Restrict e a coluna calculada da próxima administração. | D19: Disponibilizar uma persistência EF Core 10 coerente com o Modelo de Dados v02 e com a Arquitetura v02, após migração controlada da base técnica para .NET 10. | E19: Desenvolvimento | F19: Camada Infrastructure com DbContext, entidades e mapeamentos Entity Framework Core 10.0 coerentes com o Modelo de Dados v02, integrada no repositório do backend (arquivo final em /projeto/04-artefactos-tecnicos/04.12-backend/m3-v01). | G19: 1 — Crítica | H19: m3 | I19: S04 | J19: 50 | K19: =IF(ISNUMBER(J19),J19*60%,IF(J19="","Por preencher",J19)) -> 30 | L19: =IF(ISNUMBER(J19),J19*30%,IF(J19="","Por preencher",J19)) -> 15 | M19: =IF(ISNUMBER(J19),J19*10%,IF(J19="","Por preencher",J19)) -> 5 | N19: O mapeamento EF cobre as 19 tabelas ativas do Modelo de Dados v02; PK/FK, cardinalidades, CHECK, UNIQUE, índices e DeleteBehavior.Restrict estão coerentes; Cliente.UtilizadorId é opcional e único quando preenchido; não existem entidades/tabelas de F005/F007; migrations executam sem divergências. | O19: 1. Merge Request com entidades, mapeamentos e repositórios. 2. Resultado da comparação modelo EF ↔ esquema (ou lista de diferenças e decisão). 3. Registo da criação da base de dados numa instância vazia. | P19: 1. Rever o mapeamento Entity Framework Core contra o Modelo de Dados v02, confirmando entidades, PK/FK, cardinalidades, restrições, índices e DeleteBehavior aplicáveis. 2. Criar a base através das migrations numa instância limpa e comparar o esquema resultante com o modelo, incluindo Cliente opcionalmente associado a Utilizador, Consulta, horários, registo clínico e profilaxia. 3. Confirmar que não existem entidades/tabelas de F005/F007 nem SQL construído de forma insegura. | Q19: Checklist de auditoria 02.05 completa: independência dos três papéis, relatório de revisão 02.04, prazos de 48 h e 24 h, pontos, versão final e pasta. Confirmar que o mapeamento não altera o Modelo de Dados aprovado sem decisão registada e que as dependências com I060 estão cumpridas. | R19: I058; I016; I019; I020. | S19: DoD G08 v01: resultado produzido e acessível; critérios de aceitação cumpridos; revisão e auditoria concluídas; versão final aprovada, corretamente nomeada e arquivada na pasta prevista. Em código: integrado no repositório por Merge Request aprovado pelo Revisor, conforme o regulamento interno do grupo; compila e passa na verificação local sem erros; sem segredos no repositório; divergências face à Documentação de API ou ao Modelo de Dados registadas e decididas. | T19: Modelo de Dados v02 (I016); Arquitetura v02 (I019); Modelo de Classes Backend v02 (I020); Regulamento Interno do Grupo G08 v02 (proposta); documentação oficial do Entity Framework Core 10; Regulamento de Funcionamento da UC v19, secção 19 (04.12). | U19: /projeto/04-artefactos-tecnicos/04.12-backend/m3-v01 (código desenvolvido no repositório Git do grupo e arquivado nesta pasta na entrega da M3) | V19: Sim | W19: Done | X19: Aprovada como Ready | Y19: 46314 | Z19: /projeto/01-artefactos-de-gestao/01.03-reunioes-de-grupo/m3-s04-20261019-backlog-refinement-ata-v01.pdf | AA19: 2026-10-14 23:05 — Tarefa criada na proposta de refinamento (versão de trabalho), por divisão da Issue original I025 «Desenvolver Backend». Ainda não analisada em Backlog Refinement: orçamento, DoR e decisão por ratificar. 2026-10-21 15:30 — Versão de trabalho v03: registada a decisão do Backlog Refinement de 2026-10-19 (Aprovada como Ready; DoR = Sim; orçamento 50; ata m3-20261019-s04-ata-backlog-refinement-v01.pdf, secção 4 e deliberação 3). A redação desta Issue foi atualizada em 2026-10-20 na rebaseline M3 (retirada de F005/F007 do âmbito, requisitos RF, API v02). O Sprint Planning S04 (2026-10-20 a 2026-10-21) manteve o texto aprovado em 2026-10-19; a alteração de redação será apreciada no Backlog Refinement do Sprint 05. 2026-10-27 — Correção da referência à ata (proposta para o Backlog Refinement do Sprint 05): o ficheiro arquivado chama-se m3-s04-20261019-backlog-refinement-ata-v01.pdf; o nome anterior não correspondia a nenhum ficheiro. 2026-10-27 — Sprint Review do Sprint 04: tarefa aceite e estado alterado para Done (m3-s04-20261027-sprint-review-ata-v01.pdf).
A20: I060 | B20: Escrever o script de criação do esquema da base de dados | C20: Escrever o script T-SQL de criação da base de dados clinica-veterinaria a partir do Modelo de Dados (I016): tabelas, chaves primárias e estrangeiras, tipos, restrições CHECK e UNIQUE, valores por omissão e índices de pesquisa (clientes, animais, consultas por veterinário e data, contas por cliente). O script deve ser reexecutável (verifica a existência antes de criar) e dividido em ficheiros numerados por ordem de execução. | D20: Obter um esquema físico fiel ao modelo aprovado, criado de forma automática e repetível, que sirva de referência à persistência EF Core e aos ambientes individuais. | E20: Desenvolvimento | F20: Scripts SQL numerados de criação do esquema em /projeto/04-artefactos-tecnicos/04.13-scripts-de-base-de-dados/m3-v01, executáveis numa instância SQL Server vazia. | G20: 1 — Crítica | H20: m3 | I20: S03 | J20: 50 | K20: =IF(ISNUMBER(J20),J20*60%,IF(J20="","Por preencher",J20)) -> 30 | L20: =IF(ISNUMBER(J20),J20*30%,IF(J20="","Por preencher",J20)) -> 15 | M20: =IF(ISNUMBER(J20),J20*10%,IF(J20="","Por preencher",J20)) -> 5 | N20: 1. Os scripts correm do início ao fim numa instância SQL Server vazia, sem erros, por ordem numérica. 2. Todas as tabelas, colunas, chaves, relações e cardinalidades do Modelo de Dados (I016) estão criadas e coincidem em nomes e tipos. 3. Existem restrições UNIQUE para e-mail de utilizador, NIF e e-mail de cliente e CHECK para valores positivos (peso, valores monetários, intervalo em dias). 4. Os scripts são reexecutáveis: uma segunda execução não falha nem duplica objetos. 5. Cada ficheiro tem cabeçalho com finalidade, ordem de execução e pré-requisitos; não há dados pessoais reais nem palavras-passe. | O20: 1. Ficheiros SQL no repositório (e na pasta de scripts). 2. Registo da execução numa base vazia e numa segunda execução. 3. Quadro de correspondência tabela do modelo ↔ tabela criada. | P20: 1. Executar os scripts numa instância limpa, duas vezes, e comparar objetos criados com o Modelo de Dados. 2. Confirmar chaves estrangeiras, UNIQUE e CHECK com inserções válidas e inválidas. 3. Verificar que não há dados reais nem segredos nos scripts. | Q20: Checklist de auditoria 02.05 completa: independência dos três papéis, relatório de revisão 02.04, prazos de 48 h e 24 h, pontos, versão final e pasta. Confirmar que o esquema criado cobre todas as entidades do modelo e que a ordem dos ficheiros permite execução automática pela pipeline. | R20: I016 — Modelo de Dados (Base de dados clinica-veterinaria); I019 — Documentação da Arquitetura. | S20: DoD G08 v01: resultado produzido e acessível; critérios de aceitação cumpridos; revisão e auditoria concluídas; versão final aprovada, corretamente nomeada e arquivada na pasta prevista. Em código: integrado no repositório por Merge Request aprovado pelo Revisor, conforme o regulamento interno do grupo; compila e passa na verificação local sem erros; sem segredos no repositório; divergências face à Documentação de API ou ao Modelo de Dados registadas e decididas. | T20: Modelo de Dados m2 (I016); Documentação da Arquitetura (I019); Regulamento de Funcionamento da UC v19, secção 19 (04.13-scripts-de-base-de-dados). | U20: /projeto/04-artefactos-tecnicos/04.13-scripts-de-base-de-dados/m3-v01 | V20: Sim | W20: Done | X20: Aprovada como Ready | Y20: 46307 | Z20: /projeto/01-artefactos-de-gestao/01.03-reunioes-de-grupo/m3-s03-20261012-backlog-refinement-ata-v01.pdf | AA20: 2026-10-14 23:05 — Tarefa criada na proposta de refinamento (versão de trabalho), por divisão da Issue original I026 «Implementar Scripts de Bases de Dados». Ainda não analisada em Backlog Refinement: orçamento, DoR e decisão por ratificar. 2026-10-19 18:56 — Reconciliação documental para a versão de trabalho v02 (a apreciar no Backlog Refinement de 2026-10-19; os PDFs já assinados não são alterados). O orçamento 50/30/15/5 e a decisão «Aprovada como Ready» foram aprovados no Backlog Refinement de 2026-10-12 (ata m3-s03-20261012-backlog-refinement-ata-v01, secção 4), que a v01 ainda registava como «Não analisada» / «Por verificar». Executada no Sprint 03: PR #152 (commit 2329042; main f300c52) e evidências de execução na PR #153 (commit 1a43c22; main 052f366). Revisão e auditoria concluídas em 2026-10-17 (relatório de revisão e checklist de auditoria da I060); o Sprint Review de 2026-10-17 (ata m3-s03-20261017-sprint-review-ata-v01) aprovou a passagem a Done. Estado atualizado de Pendente para Done.
A21: I061 | B21: Preparar dados iniciais e de demonstração da base de dados | C21: Preparar dados iniciais e de demonstração sintéticos coerentes com a baseline v02: clínica/configurações, horários de funcionamento, horários regulares de Veterinários, contas dos cinco perfis, Clientes com e sem conta de acesso, pacientes, Consultas em estados válidos, notas de apoio, informação clínica e vacinação/desparasitação. Não incluir dados financeiros nem de internamento; credenciais reais não são versionadas. | D21: Permitir arrancar e demonstrar o sistema com dados fictícios mínimos, coerentes com todo o âmbito ativo, sem depender de criação manual de dados. | E21: Desenvolvimento | F21: Scripts SQL de dados iniciais e de demonstração em /projeto/04-artefactos-tecnicos/04.13-scripts-de-base-de-dados/m3-v01, executáveis a seguir ao esquema. | G21: 1 — Crítica | H21: m3 | I21: S04 | J21: 30 | K21: =IF(ISNUMBER(J21),J21*60%,IF(J21="","Por preencher",J21)) -> 18 | L21: =IF(ISNUMBER(J21),J21*30%,IF(J21="","Por preencher",J21)) -> 9 | M21: =IF(ISNUMBER(J21),J21*10%,IF(J21="","Por preencher",J21)) -> 3 | N21: Dados exclusivamente fictícios; cobrem os cinco perfis, Cliente com/sem conta, vários pacientes, horários, Consultas, clínico e profilaxia; respeitam todas as FKs e regras; não incluem F005/F007. | O21: 1. Ficheiros SQL no repositório. 2. Registo da execução sobre o esquema novo. 3. Lista das contas de teste e dos dados de demonstração criados (sem palavras-passe em claro no repositório). | P21: 1. Correr esquema + dados iniciais e iniciar sessão com cada conta de teste na API. 2. Confirmar a coerência referencial e a cobertura dos cenários listados. 3. Verificar que não existem dados pessoais reais. | Q21: Checklist de auditoria 02.05 completa: independência dos três papéis, relatório de revisão 02.04, prazos de 48 h e 24 h, pontos, versão final e pasta. Confirmar a licitude dos dados (todos fictícios), a existência de contas de avaliação limitadas e que as credenciais ficam apenas no ficheiro apropriado. | R21: I059; I060. | S21: DoD G08 v01: resultado produzido e acessível; critérios de aceitação cumpridos; revisão e auditoria concluídas; versão final aprovada, corretamente nomeada e arquivada na pasta prevista. Em código: integrado no repositório por Merge Request aprovado pelo Revisor, conforme o regulamento interno do grupo; compila e passa na verificação local sem erros; sem segredos no repositório; divergências face à Documentação de API ou ao Modelo de Dados registadas e decididas. | T21: Modelo de Dados v02 (I016); Especificação de Requisitos v02 (I012); Casos de Uso v02 (I015); Regulamento de Funcionamento da UC v19, secção 19 (04.13; credenciais de avaliação em 00-indice-e-submissao). | U21: /projeto/04-artefactos-tecnicos/04.13-scripts-de-base-de-dados/m3-v01 | V21: Sim | W21: Done | X21: Aprovada como Ready | Y21: 46314 | Z21: /projeto/01-artefactos-de-gestao/01.03-reunioes-de-grupo/m3-s04-20261019-backlog-refinement-ata-v01.pdf | AA21: 2026-10-14 23:05 — Tarefa criada na proposta de refinamento (versão de trabalho), por divisão da Issue original I026 «Implementar Scripts de Bases de Dados». Ainda não analisada em Backlog Refinement: orçamento, DoR e decisão por ratificar. 2026-10-21 15:30 — Versão de trabalho v03: registada a decisão do Backlog Refinement de 2026-10-19 (Aprovada como Ready; DoR = Sim; orçamento 30; ata m3-20261019-s04-ata-backlog-refinement-v01.pdf, secção 4 e deliberação 3). A redação desta Issue foi atualizada em 2026-10-20 na rebaseline M3 (retirada de F005/F007 do âmbito, requisitos RF, API v02). O Sprint Planning S04 (2026-10-20 a 2026-10-21) manteve o texto aprovado em 2026-10-19; a alteração de redação será apreciada no Backlog Refinement do Sprint 05. 2026-10-27 — Correção da referência à ata (proposta para o Backlog Refinement do Sprint 05): o ficheiro arquivado chama-se m3-s04-20261019-backlog-refinement-ata-v01.pdf; o nome anterior não correspondia a nenhum ficheiro. 2026-10-27 — Sprint Review do Sprint 04: tarefa aceite e estado alterado para Done (m3-s04-20261027-sprint-review-ata-v01.pdf).
A22: I062 | B22: Preparar migrations e reposição da base de dados por ambiente | C22: Gerar e versionar as EF Core 10 Migrations a partir do modelo de persistência aprovado e preparar um procedimento reprodutível para apagar/criar a base, aplicar migrations e carregar dados de demonstração por ambiente. Validar o processo numa instância SQL Server 2025 limpa; qualquer script SQL de esquema futuro deve ser gerado a partir das migrations. | D22: Assegurar que cada elemento e a pipeline conseguem recriar rapidamente uma base SQL Server isolada e coerente através das EF Core 10 Migrations. | E22: Desenvolvimento | F22: Migrations Entity Framework Core 10.0 e procedimento de reposição documentado em /projeto/04-artefactos-tecnicos/04.13-scripts-de-base-de-dados/m3-v01, testados numa instância limpa. | G22: 1 — Crítica | H22: m3 | I22: S04 | J22: 30 | K22: =IF(ISNUMBER(J22),J22*60%,IF(J22="","Por preencher",J22)) -> 18 | L22: =IF(ISNUMBER(J22),J22*30%,IF(J22="","Por preencher",J22)) -> 9 | M22: =IF(ISNUMBER(J22),J22*10%,IF(J22="","Por preencher",J22)) -> 3 | N22: Reposição automatizada numa base vazia; migrations são a fonte de implementação; seed aplica sem erros; ligação é configurável; o resultado coincide com o Modelo de Dados v02; não há credenciais reais. | O22: 1. Migrações e script no repositório. 2. Registo de duas reposições consecutivas (máquina do Executor e do Revisor). 3. Texto de utilização incluído no manual técnico de bases de dados. | P22: 1. Repor a base numa máquina própria seguindo apenas o procedimento documentado. 2. Repetir a reposição e confirmar que migrations e seed produzem novamente um ambiente funcional e isolado, sem ligações por omissão a ambientes partilhados. 3. Comparar o esquema resultante com o Modelo de Dados v02 e com as migrations que constituem a fonte de implementação. | Q22: Checklist de auditoria 02.05 completa: independência dos três papéis, relatório de revisão 02.04, prazos de 48 h e 24 h, pontos, versão final e pasta. Confirmar que o procedimento serve o requisito de ambientes individuais isolados da secção 20.2 e que não há credenciais partilhadas. | R22: I059; I061. | S22: DoD G08 v01: resultado produzido e acessível; critérios de aceitação cumpridos; revisão e auditoria concluídas; versão final aprovada, corretamente nomeada e arquivada na pasta prevista. Em código: integrado no repositório por Merge Request aprovado pelo Revisor, conforme o regulamento interno do grupo; compila e passa na verificação local sem erros; sem segredos no repositório; divergências face à Documentação de API ou ao Modelo de Dados registadas e decididas. | T22: Modelo de Dados v02 (I016); Arquitetura v02 (I019); documentação oficial do Entity Framework Core 10; Regulamento de Funcionamento da UC v19, secção 19 (04.13) e secção 20.2. | U22: /projeto/04-artefactos-tecnicos/04.13-scripts-de-base-de-dados/m3-v01 | V22: Sim | W22: Done | X22: Aprovada como Ready | Y22: 46314 | Z22: /projeto/01-artefactos-de-gestao/01.03-reunioes-de-grupo/m3-s04-20261019-backlog-refinement-ata-v01.pdf | AA22: 2026-10-14 23:05 — Tarefa criada na proposta de refinamento (versão de trabalho), por divisão da Issue original I026 «Implementar Scripts de Bases de Dados». Ainda não analisada em Backlog Refinement: orçamento, DoR e decisão por ratificar. 2026-10-21 15:30 — Versão de trabalho v03: registada a decisão do Backlog Refinement de 2026-10-19 (Aprovada como Ready; DoR = Sim; orçamento 30; ata m3-20261019-s04-ata-backlog-refinement-v01.pdf, secção 4 e deliberação 3). A redação desta Issue foi atualizada em 2026-10-20 na rebaseline M3 (retirada de F005/F007 do âmbito, requisitos RF, API v02). O Sprint Planning S04 (2026-10-20 a 2026-10-21) manteve o texto aprovado em 2026-10-19; a alteração de redação será apreciada no Backlog Refinement do Sprint 05. 2026-10-27 — Correção da referência à ata (proposta para o Backlog Refinement do Sprint 05): o ficheiro arquivado chama-se m3-s04-20261019-backlog-refinement-ata-v01.pdf; o nome anterior não correspondia a nenhum ficheiro. 2026-10-27 — Sprint Review do Sprint 04: tarefa aceite e estado alterado para Done (m3-s04-20261027-sprint-review-ata-v01.pdf).
A23: I063 | B23: Implementar autenticação JWT e controlo de acesso por perfil (RF001, RF002, RF004, RF005) | C23: Implementar RF001, RF002, RF004 e RF005: autenticação por credenciais, validação de conta ativa, emissão/validação de JWT e identificação do perfil autenticado, aplicando as políticas de autorização dos cinco perfis. A chave e restantes segredos são fornecidos por configuração segura; o fim de sessão é tratado em I064. | D23: Permitir acesso autenticado aos cinco perfis e estabelecer a base comum de autorização para todas as operações do sistema. | E23: Desenvolvimento | F23: Operações da API v02 correspondentes a RF001, RF002, RF004 e RF005 implementadas, integradas no repositório do backend e verificadas manualmente (arquivo final em /projeto/04-artefactos-tecnicos/04.12-backend/m3-v01). | G23: 1 — Crítica | H23: m3 | I23: S04 | J23: 50 | K23: =IF(ISNUMBER(J23),J23*60%,IF(J23="","Por preencher",J23)) -> 30 | L23: =IF(ISNUMBER(J23),J23*30%,IF(J23="","Por preencher",J23)) -> 15 | M23: =IF(ISNUMBER(J23),J23*10%,IF(J23="","Por preencher",J23)) -> 5 | N23: 1. Uma conta registada, ativa e com credenciais válidas consegue autenticar-se e recebe uma credencial de acesso válida segundo o contrato da API v02. 2. Credenciais inválidas ou uma conta sem acesso permitido são rejeitadas sem revelar informação sensível sobre a existência da conta. 3. A identidade autenticada fica associada ao perfil registado e as operações protegidas aplicam as permissões previstas para Administrador, Rececionista, Veterinário, Auxiliar Veterinário e Cliente. 4. Credenciais de acesso inválidas, adulteradas ou expiradas deixam de permitir acesso autenticado. 5. As palavras-passe são verificadas de forma segura e nunca são devolvidas ou registadas em claro. 6. O isolamento dos dados do Cliente é aplicado às operações que dependem da propriedade dos dados. 7. As tentativas de autenticação e rejeições relevantes ficam registadas sem expor palavras-passe ou tokens. | O23: 1. Merge Request com código, validações e descrição das verificações manuais. 2. Pedidos e respostas obtidos para operação correspondente da API v02 e operação correspondente da API v02 (ficheiro de pedidos ou capturas do Swagger/Postman). 3. Commits ligados à Issue e eventuais alterações ao esquema comunicadas à tarefa de scripts de base de dados. | P23: 1. Executar a API a partir de um clone limpo e repetir, no mínimo, um pedido válido e um pedido de erro por operação. 2. Testar tokens expirados, adulterados e de conta bloqueada; verificar o hash na base de dados; confirmar que perfil e jti constam do token e que uma política por perfil rejeita os restantes. 3. Confirmar que cada perfil autorizado consegue e um perfil não autorizado não consegue, que os códigos HTTP e as mensagens correspondem à Documentação de API e que as divergências foram registadas. | Q23: Checklist de auditoria 02.05 completa: independência dos três papéis, relatório de revisão 02.04, prazos de 48 h e 24 h, pontos, versão final e pasta. Confirmar que o tempo de validade e o algoritmo correspondem ao contrato e que a chave JWT não está no repositório. | R23: I058; I018; I020; I059. | S23: DoD G08 v01: resultado produzido e acessível; critérios de aceitação cumpridos; revisão e auditoria concluídas; versão final aprovada, corretamente nomeada e arquivada na pasta prevista. Em código: integrado no repositório por Merge Request aprovado pelo Revisor, conforme o regulamento interno do grupo; compila e passa na verificação local sem erros; sem segredos no repositório; divergências face à Documentação de API ou ao Modelo de Dados registadas e decididas. | T23: Documentação de API v02 (I018); Especificação de Requisitos v02 (I012), RF001, RF002, RF004 e RF005; Casos de Uso v02 (I015); Modelo de Dados v02 (I016); Modelo de Classes Backend v02 (I020); Arquitetura v02 (I019); Regulamento de Funcionamento da UC v19; Regulamento Interno do Grupo G08 v02 (proposta). | U23: /projeto/04-artefactos-tecnicos/04.12-backend/m3-v01 (código desenvolvido no repositório Git do grupo e arquivado nesta pasta na entrega da M3) | V23: Sim | W23: Done | X23: Aprovada como Ready | Y23: 46314 | Z23: /projeto/01-artefactos-de-gestao/01.03-reunioes-de-grupo/m3-s04-20261019-backlog-refinement-ata-v01.pdf | AA23: 2026-10-14 23:05 — Tarefa criada na proposta de refinamento (versão de trabalho), por divisão da Issue original I025 «Desenvolver Backend». Ainda não analisada em Backlog Refinement: orçamento, DoR e decisão por ratificar. 2026-10-21 15:30 — Versão de trabalho v03: registada a decisão do Backlog Refinement de 2026-10-19 (Aprovada como Ready; DoR = Sim; orçamento 50; ata m3-20261019-s04-ata-backlog-refinement-v01.pdf, secção 4 e deliberação 3). A redação desta Issue foi atualizada em 2026-10-20 na rebaseline M3 (retirada de F005/F007 do âmbito, requisitos RF, API v02). O Sprint Planning S04 (2026-10-20 a 2026-10-21) manteve o texto aprovado em 2026-10-19; a alteração de redação será apreciada no Backlog Refinement do Sprint 05. 2026-10-27 — Correção da referência à ata (proposta para o Backlog Refinement do Sprint 05): o ficheiro arquivado chama-se m3-s04-20261019-backlog-refinement-ata-v01.pdf; o nome anterior não correspondia a nenhum ficheiro. 2026-10-27 — Sprint Review do Sprint 04: tarefa aceite e estado alterado para Done (m3-s04-20261027-sprint-review-ata-v01.pdf).
A24: I067 | B24: Implementar dados gerais da clínica e gestão de horários (RF012, RF013, RF019, RF055) | C24: Implementar RF012, RF013, RF019 e RF055: consulta/atualização dos dados gerais e configurações da clínica e gestão, pelo Administrador, dos horários de funcionamento e dos horários regulares de atendimento dos Veterinários. Os horários admitem múltiplos períodos por dia e alimentam diretamente o cálculo de disponibilidade. | D24: Fornecer a configuração única da clínica e dos horários que determina a disponibilidade efetiva dos Veterinários. | E24: Desenvolvimento | F24: Operações da API v02 correspondentes a RF012, RF013, RF019 e RF055 implementadas, integradas no repositório do backend e verificadas manualmente (arquivo final em /projeto/04-artefactos-tecnicos/04.12-backend/m3-v01). | G24: 1 — Crítica | H24: m3 | I24: S04 | J24: 20 | K24: =IF(ISNUMBER(J24),J24*60%,IF(J24="","Por preencher",J24)) -> 12 | L24: =IF(ISNUMBER(J24),J24*30%,IF(J24="","Por preencher",J24)) -> 6 | M24: =IF(ISNUMBER(J24),J24*10%,IF(J24="","Por preencher",J24)) -> 2 | N24: 1. O Administrador consegue consultar e atualizar os dados gerais da clínica e as configurações do sistema previstos na baseline v02. 2. O Administrador consegue definir e atualizar o horário de funcionamento da clínica com um ou mais períodos por dia. 3. Cada período possui início anterior ao fim e não se sobrepõe a outro período do mesmo dia; uma configuração inválida é rejeitada sem gravação parcial. 4. Um dia pode não possuir períodos de funcionamento. 5. Depois da confirmação, os valores persistidos são devolvidos de forma coerente e utilizados pelas operações dependentes da configuração da clínica. 6. Os restantes perfis não conseguem executar operações administrativas reservadas ao Administrador. | O24: 1. Merge Request com código, validações e descrição das verificações manuais. 2. Pedidos e respostas obtidos para operação correspondente da API v02 e operação correspondente da API v02 (ficheiro de pedidos ou capturas do Swagger/Postman). 3. Commits ligados à Issue e eventuais alterações ao esquema comunicadas à tarefa de scripts de base de dados. | P24: 1. Executar a API a partir de um clone limpo e repetir, no mínimo, um pedido válido e um pedido de erro por operação. 2. Gravar horários válidos e inválidos (sobrepostos, fecho ≤ abertura) e confirmar que o anterior se mantém nos casos de erro. 3. Confirmar que cada perfil autorizado consegue e um perfil não autorizado não consegue, que os códigos HTTP e as mensagens correspondem à Documentação de API e que as divergências foram registadas. | Q24: Checklist de auditoria 02.05 completa: independência dos três papéis, relatório de revisão 02.04, prazos de 48 h e 24 h, pontos, versão final e pasta. Confirmar que o horário é lido de um único local e que a atomicidade foi verificada. | R24: I063; I016; I018; I020; I059. | S24: DoD G08 v01: resultado produzido e acessível; critérios de aceitação cumpridos; revisão e auditoria concluídas; versão final aprovada, corretamente nomeada e arquivada na pasta prevista. Em código: integrado no repositório por Merge Request aprovado pelo Revisor, conforme o regulamento interno do grupo; compila e passa na verificação local sem erros; sem segredos no repositório; divergências face à Documentação de API ou ao Modelo de Dados registadas e decididas. | T24: Documentação de API v02 (I018); Especificação de Requisitos v02 (I012), RF012, RF013 e RF019; Casos de Uso v02 (I015); Modelo de Dados v02 (I016); Modelo de Classes Backend v02 (I020); Arquitetura v02 (I019); Regulamento de Funcionamento da UC v19; Regulamento Interno do Grupo G08 v02 (proposta). | U24: /projeto/04-artefactos-tecnicos/04.12-backend/m3-v01 (código desenvolvido no repositório Git do grupo e arquivado nesta pasta na entrega da M3) | V24: Sim | W24: Done | X24: Aprovada como Ready | Y24: 46314 | Z24: /projeto/01-artefactos-de-gestao/01.03-reunioes-de-grupo/m3-s04-20261019-backlog-refinement-ata-v01.pdf | AA24: 2026-10-14 23:05 — Tarefa criada na proposta de refinamento (versão de trabalho), por divisão da Issue original I025 «Desenvolver Backend». Ainda não analisada em Backlog Refinement: orçamento, DoR e decisão por ratificar. 2026-10-21 15:30 — Versão de trabalho v03: registada a decisão do Backlog Refinement de 2026-10-19 (Aprovada como Ready; DoR = Sim; orçamento 20; ata m3-20261019-s04-ata-backlog-refinement-v01.pdf, secção 4 e deliberação 3). A redação desta Issue foi atualizada em 2026-10-20 na rebaseline M3 (retirada de F005/F007 do âmbito, requisitos RF, API v02). O Sprint Planning S04 (2026-10-20 a 2026-10-21) manteve o texto aprovado em 2026-10-19; a alteração de redação será apreciada no Backlog Refinement do Sprint 05. 2026-10-27 — Correção da referência à ata (proposta para o Backlog Refinement do Sprint 05): o ficheiro arquivado chama-se m3-s04-20261019-backlog-refinement-ata-v01.pdf; o nome anterior não correspondia a nenhum ficheiro. 2026-10-27 — Sprint Review do Sprint 04: tarefa aceite e estado alterado para Done (m3-s04-20261027-sprint-review-ata-v01.pdf).
A25: I068 | B25: Implementar gestão administrativa de Clientes e contas de acesso (RF010, RF011, RF053, RF054) | C25: Implementar RF010, RF011, RF053 e RF054 distinguindo o registo administrativo de Cliente da conta de acesso. O Rececionista regista e atualiza dados administrativos; Administrador e Rececionista criam/atualizam a conta de acesso quando aplicável. Um Cliente pode existir sem Utilizador e alterações administrativas não devem alterar automaticamente credenciais. | D25: Permitir gerir corretamente o Cliente enquanto entidade administrativa e, separadamente, a sua conta de acesso opcional. | E25: Desenvolvimento | F25: Operações da API v02 correspondentes a RF010, RF011, RF053 e RF054 implementadas, integradas no repositório do backend e verificadas manualmente (arquivo final em /projeto/04-artefactos-tecnicos/04.12-backend/m3-v01). | G25: 1 — Crítica | H25: m3 | I25: S04 | J25: 30 | K25: =IF(ISNUMBER(J25),J25*60%,IF(J25="","Por preencher",J25)) -> 18 | L25: =IF(ISNUMBER(J25),J25*30%,IF(J25="","Por preencher",J25)) -> 9 | M25: =IF(ISNUMBER(J25),J25*10%,IF(J25="","Por preencher",J25)) -> 3 | N25: 1. As operações implementadas permitem ao Administrador e ao Rececionista criar uma conta de acesso para um Cliente administrativo previamente registado e ainda sem conta associada. 2. A criação é rejeitada quando o Cliente não existe, já possui uma conta de acesso ou os dados obrigatórios da conta são inválidos. 3. Administrador e Rececionista conseguem atualizar os dados editáveis da conta sem alterar a associação ao respetivo Cliente. 4. Criar ou atualizar a conta de acesso não cria nem altera automaticamente os dados administrativos do Cliente. 5. A conta criada permite autenticação exclusivamente segundo o perfil Cliente e as respetivas permissões. 6. Pedidos sem autenticação ou de perfis não autorizados são rejeitados segundo o contrato da API v02. | O25: 1. Merge Request com código, validações e descrição das verificações manuais. 2. Pedidos e respostas obtidos para operações correspondentes da API v02 (ficheiro de pedidos ou capturas do Swagger/Postman). 3. Commits ligados à Issue e eventuais alterações ao esquema comunicadas à tarefa de scripts de base de dados. | P25: 1. Executar a API a partir de um clone limpo e criar uma conta de acesso para um Cliente administrativo existente sem conta associada. 2. Confirmar a rejeição quando o Cliente não existe, já possui conta de acesso ou são fornecidos dados de conta inválidos; verificar também a atualização posterior dos dados editáveis da conta. 3. Confirmar que criar/atualizar a conta não altera automaticamente os dados administrativos do Cliente e que apenas os perfis autorizados executam estas operações segundo a API v02. | Q25: Checklist de auditoria 02.05 completa: independência dos três papéis, relatório de revisão 02.04, prazos de 48 h e 24 h, pontos, versão final e pasta. Confirmar a validação do NIF e que a atualização não permite colidir com outro cliente. | R25: I063; I018; I020; I059. | S25: DoD G08 v01: resultado produzido e acessível; critérios de aceitação cumpridos; revisão e auditoria concluídas; versão final aprovada, corretamente nomeada e arquivada na pasta prevista. Em código: integrado no repositório por Merge Request aprovado pelo Revisor, conforme o regulamento interno do grupo; compila e passa na verificação local sem erros; sem segredos no repositório; divergências face à Documentação de API ou ao Modelo de Dados registadas e decididas. | T25: Documentação de API v02 (I018); Especificação de Requisitos v02 (I012), RF010 e RF011; Casos de Uso v02 (I015); Modelo de Dados v02 (I016); Modelo de Classes Backend v02 (I020); Arquitetura v02 (I019); Regulamento de Funcionamento da UC v19; Regulamento Interno do Grupo G08 v02 (proposta). | U25: /projeto/04-artefactos-tecnicos/04.12-backend/m3-v01 (código desenvolvido no repositório Git do grupo e arquivado nesta pasta na entrega da M3) | V25: Sim | W25: Done | X25: Aprovada como Ready | Y25: 46314 | Z25: /projeto/01-artefactos-de-gestao/01.03-reunioes-de-grupo/m3-s04-20261019-backlog-refinement-ata-v01.pdf | AA25: 2026-10-14 23:05 — Tarefa criada na proposta de refinamento (versão de trabalho), por divisão da Issue original I025 «Desenvolver Backend». Ainda não analisada em Backlog Refinement: orçamento, DoR e decisão por ratificar. 2026-10-21 15:30 — Versão de trabalho v03: registada a decisão do Backlog Refinement de 2026-10-19 (Aprovada como Ready; DoR = Sim; orçamento 30; ata m3-20261019-s04-ata-backlog-refinement-v01.pdf, secção 4 e deliberação 3). A redação desta Issue foi atualizada em 2026-10-20 na rebaseline M3 (retirada de F005/F007 do âmbito, requisitos RF, API v02). O Sprint Planning S04 (2026-10-20 a 2026-10-21) manteve o texto aprovado em 2026-10-19; a alteração de redação será apreciada no Backlog Refinement do Sprint 05. 2026-10-27 — Correção da referência à ata (proposta para o Backlog Refinement do Sprint 05): o ficheiro arquivado chama-se m3-s04-20261019-backlog-refinement-ata-v01.pdf; o nome anterior não correspondia a nenhum ficheiro. 2026-10-27 — Sprint Review do Sprint 04: tarefa aceite e estado alterado para Done (m3-s04-20261027-sprint-review-ata-v01.pdf).
A26: I069 | B26: Implementar a gestão de pacientes (RF014–RF017) | C26: Implementar RF014–RF017: registo, consulta/pesquisa e atualização dos dados administrativos dos pacientes, mantendo associação inequívoca ao proprietário Cliente e os campos previstos, incluindo espécie, raça, idade e peso. Rececionista e Veterinário escrevem nos limites definidos; Auxiliar consulta; dados clínicos ficam fora deste módulo. | D26: Permitir identificar e manter os pacientes e a respetiva associação ao proprietário, fornecendo a base administrativa às Consultas e ao histórico clínico. | E26: Desenvolvimento | F26: Operações da API v02 correspondentes a RF014–RF017 implementadas, integradas no repositório do backend e verificadas manualmente (arquivo final em /projeto/04-artefactos-tecnicos/04.12-backend/m3-v01). | G26: 1 — Crítica | H26: m3 | I26: S04 | J26: 30 | K26: =IF(ISNUMBER(J26),J26*60%,IF(J26="","Por preencher",J26)) -> 18 | L26: =IF(ISNUMBER(J26),J26*30%,IF(J26="","Por preencher",J26)) -> 9 | M26: =IF(ISNUMBER(J26),J26*10%,IF(J26="","Por preencher",J26)) -> 3 | N26: 1. Rececionista e Veterinário conseguem registar um paciente associado inequivocamente a um Cliente previamente registado, com os dados administrativos definidos na baseline v02, incluindo espécie, raça, idade e peso. 2. Rececionista, Veterinário e Auxiliar Veterinário conseguem consultar a ficha administrativa; apenas Rececionista e Veterinário a podem atualizar. 3. Rececionista e Veterinário conseguem pesquisar os pacientes associados a um Cliente. 4. Dados administrativos inválidos são rejeitados sem alteração persistente. 5. A ficha não concede ao Rececionista nem ao Auxiliar permissões de alteração de informação clínica. 6. A associação ao proprietário é preservada de forma inequívoca. | O26: 1. Merge Request com código, validações e descrição das verificações manuais. 2. Pedidos e respostas obtidos para operações correspondentes da API v02 (ficheiro de pedidos ou capturas do Swagger/Postman). 3. Commits ligados à Issue e eventuais alterações ao esquema comunicadas à tarefa de scripts de base de dados. | P26: 1. Executar a API a partir de um clone limpo e registar, consultar e atualizar pacientes com dados administrativos válidos, confirmando sempre a associação ao Cliente existente. 2. Testar dados administrativos inválidos e a pesquisa dos pacientes por proprietário. 3. Confirmar as permissões de Rececionista, Veterinário e Auxiliar Veterinário e que a consulta administrativa não concede ao Rececionista nem ao Auxiliar operações sobre informação clínica. | Q26: Checklist de auditoria 02.05 completa: independência dos três papéis, relatório de revisão 02.04, prazos de 48 h e 24 h, pontos, versão final e pasta. Confirmar que a ficha do Auxiliar Veterinário não expõe dados clínicos. | R26: I016; I018; I020; I059. | S26: DoD G08 v01: resultado produzido e acessível; critérios de aceitação cumpridos; revisão e auditoria concluídas; versão final aprovada, corretamente nomeada e arquivada na pasta prevista. Em código: integrado no repositório por Merge Request aprovado pelo Revisor, conforme o regulamento interno do grupo; compila e passa na verificação local sem erros; sem segredos no repositório; divergências face à Documentação de API ou ao Modelo de Dados registadas e decididas. | T26: Documentação de API v02 (I018); Especificação de Requisitos v02 (I012), RF014–RF017; Casos de Uso v02 (I015); Modelo de Dados v02 (I016); Modelo de Classes Backend v02 (I020); Arquitetura v02 (I019); Regulamento de Funcionamento da UC v19; Regulamento Interno do Grupo G08 v02 (proposta). | U26: /projeto/04-artefactos-tecnicos/04.12-backend/m3-v01 (código desenvolvido no repositório Git do grupo e arquivado nesta pasta na entrega da M3) | V26: Sim | W26: Done | X26: Aprovada como Ready | Y26: 46314 | Z26: /projeto/01-artefactos-de-gestao/01.03-reunioes-de-grupo/m3-s04-20261019-backlog-refinement-ata-v01.pdf | AA26: 2026-10-14 23:05 — Tarefa criada na proposta de refinamento (versão de trabalho), por divisão da Issue original I025 «Desenvolver Backend». Ainda não analisada em Backlog Refinement: orçamento, DoR e decisão por ratificar. 2026-10-21 15:30 — Versão de trabalho v03: registada a decisão do Backlog Refinement de 2026-10-19 (Aprovada como Ready; DoR = Sim; orçamento 30; ata m3-20261019-s04-ata-backlog-refinement-v01.pdf, secção 4 e deliberação 3). A redação desta Issue foi atualizada em 2026-10-20 na rebaseline M3 (retirada de F005/F007 do âmbito, requisitos RF, API v02). O Sprint Planning S04 (2026-10-20 a 2026-10-21) manteve o texto aprovado em 2026-10-19; a alteração de redação será apreciada no Backlog Refinement do Sprint 05. 2026-10-27 — Correção da referência à ata (proposta para o Backlog Refinement do Sprint 05): o ficheiro arquivado chama-se m3-s04-20261019-backlog-refinement-ata-v01.pdf; o nome anterior não correspondia a nenhum ficheiro. 2026-10-27 — Sprint Review do Sprint 04: tarefa aceite e estado alterado para Done (m3-s04-20261027-sprint-review-ata-v01.pdf).
A27: I071 | B27: Implementar o cálculo de disponibilidade dos Veterinários (RF020) | C27: Implementar RF020: cálculo da disponibilidade de um Veterinário para um intervalo solicitado pela interseção entre horário da clínica e horário regular do Veterinário, removendo Consultas não canceladas. O intervalo completo e respetiva duração devem caber numa janela válida; a disponibilidade é calculada e não persistida. | D27: Permitir à Rececionista obter horários realmente disponíveis para cada Veterinário, considerando clínica, atendimento regular e Consultas existentes. | E27: Desenvolvimento | F27: Operação da API v02 correspondente a RF020 implementada, integrada no repositório do backend e verificada manualmente (arquivo final em /projeto/04-artefactos-tecnicos/04.12-backend/m3-v01). | G27: 1 — Crítica | H27: m3 | I27: S05 | J27: 50 | K27: =IF(ISNUMBER(J27),J27*60%,IF(J27="","Por preencher",J27)) -> 30 | L27: =IF(ISNUMBER(J27),J27*30%,IF(J27="","Por preencher",J27)) -> 15 | M27: =IF(ISNUMBER(J27),J27*10%,IF(J27="","Por preencher",J27)) -> 5 | N27: 1. O Administrador consegue definir e atualizar os horários regulares de atendimento de cada Veterinário. 2. Cada período possui início anterior ao fim, não se sobrepõe a outro período do mesmo Veterinário no mesmo dia e encontra-se dentro do horário de funcionamento da clínica. 3. O Rececionista consegue consultar a disponibilidade de um Veterinário para um determinado período. 4. A disponibilidade resulta da interseção entre o horário de funcionamento da clínica, o horário regular do Veterinário e os intervalos não ocupados por Consultas não canceladas. 5. Consultas Canceladas não ocupam disponibilidade. 6. Dados inválidos ou Veterinário inexistente são rejeitados segundo o contrato da API v02. | O27: 1. Merge Request com código, validações e descrição das verificações manuais. 2. Pedidos e respostas obtidos para operação correspondente da API v02 e operação correspondente da API v02 (ficheiro de pedidos ou capturas do Swagger/Postman). 3. Commits ligados à Issue e eventuais alterações ao esquema comunicadas à tarefa de scripts de base de dados. | P27: 1. Executar a API a partir de um clone limpo e configurar horários regulares válidos e inválidos para um Veterinário. 2. Verificar que a disponibilidade apresentada resulta simultaneamente do horário de funcionamento da clínica, do horário regular do Veterinário e das Consultas não canceladas, incluindo períodos ocupados e Consultas canceladas. 3. Confirmar que apenas os perfis autorizados executam cada operação e que o comportamento corresponde à Documentação da API v02. | Q27: Checklist de auditoria 02.05 completa: independência dos três papéis, relatório de revisão 02.04, prazos de 48 h e 24 h, pontos, versão final e pasta. Confirmar que o algoritmo está isolado da camada de dados e que as fronteiras estão documentadas. | R27: I067; I016; I018; I020; I059. | S27: DoD G08 v01: resultado produzido e acessível; critérios de aceitação cumpridos; revisão e auditoria concluídas; versão final aprovada, corretamente nomeada e arquivada na pasta prevista. Em código: integrado no repositório por Merge Request aprovado pelo Revisor, conforme o regulamento interno do grupo; compila e passa na verificação local sem erros; sem segredos no repositório; divergências face à Documentação de API ou ao Modelo de Dados registadas e decididas. | T27: Documentação de API v02 (I018); Especificação de Requisitos v02 (I012), RF020 e RF055; Casos de Uso v02 (I015); Modelo de Dados v02 (I016); Modelo de Classes Backend v02 (I020); Arquitetura v02 (I019); Regulamento de Funcionamento da UC v19; Regulamento Interno do Grupo G08 v02 (proposta). | U27: /projeto/04-artefactos-tecnicos/04.12-backend/m3-v01 (código desenvolvido no repositório Git do grupo e arquivado nesta pasta na entrega da M3) | V27: Sim | W27: Pendente | X27: Aprovada como Ready | Y27: 46314 | Z27: /projeto/01-artefactos-de-gestao/01.03-reunioes-de-grupo/m3-s04-20261019-backlog-refinement-ata-v01.pdf | AA27: 2026-10-14 23:05 — Tarefa criada na proposta de refinamento (versão de trabalho), por divisão da Issue original I025 «Desenvolver Backend». Ainda não analisada em Backlog Refinement: orçamento, DoR e decisão por ratificar. 2026-10-21 15:30 — Versão de trabalho v03: registada a decisão do Backlog Refinement de 2026-10-19 (Aprovada como Ready; DoR = Sim; orçamento 50; ata m3-20261019-s04-ata-backlog-refinement-v01.pdf, secção 4 e deliberação 3). A redação desta Issue foi atualizada em 2026-10-20 na rebaseline M3 (retirada de F005/F007 do âmbito, requisitos RF, API v02). O Sprint Planning S04 (2026-10-20 a 2026-10-21) manteve o texto aprovado em 2026-10-19; a alteração de redação será apreciada no Backlog Refinement do Sprint 05. 2026-10-27 — Correção da referência à ata (proposta para o Backlog Refinement do Sprint 05): o ficheiro arquivado chama-se m3-s04-20261019-backlog-refinement-ata-v01.pdf; o nome anterior não correspondia a nenhum ficheiro. 2026-10-27 — Sprint Review do Sprint 04: sem resultado aproveitável à data da reunião (0 pontos no Sprint 04, m3-s04-20261027-sprint-review-ata-v01.pdf); a PR #203, aberta e integrada depois da reunião, é apreciada no Sprint Review do Sprint 05. A tarefa mantém-se Ready e transita para o Sprint 05.
A28: I073 | B28: Implementar o agendamento de Consultas sem sobreposição (RF021) | C28: Implementar RF021: agendamento de uma Consulta pela Rececionista para um paciente e Veterinário, com data/hora de início e duração positiva. A disponibilidade deve ser revalidada no momento da persistência; a Consulta nasce em Pendente e não pode sobrepor outra Consulta não cancelada do mesmo Veterinário. | D28: Criar Consultas agendadas de forma fiável, validando disponibilidade e impedindo sobreposição para o mesmo Veterinário. | E28: Desenvolvimento | F28: Operação da API v02 correspondente a RF021 implementada, integrada no repositório do backend e verificada manualmente (arquivo final em /projeto/04-artefactos-tecnicos/04.12-backend/m3-v01). | G28: 1 — Crítica | H28: m3 | I28: S05 | J28: 50 | K28: =IF(ISNUMBER(J28),J28*60%,IF(J28="","Por preencher",J28)) -> 30 | L28: =IF(ISNUMBER(J28),J28*30%,IF(J28="","Por preencher",J28)) -> 15 | M28: =IF(ISNUMBER(J28),J28*10%,IF(J28="","Por preencher",J28)) -> 5 | N28: 1. O Rececionista consegue agendar uma Consulta associando um paciente, um Veterinário e um período válido. 2. A criação só é aceite quando o Veterinário se encontra disponível segundo o horário da clínica, o horário regular do Veterinário e as Consultas não canceladas. 3. A Consulta criada fica no estado Pendente e mantém a associação ao paciente e ao Veterinário selecionados. 4. Um período indisponível ou dados obrigatórios inválidos fazem a operação ser rejeitada sem criar a Consulta. 5. Pedidos concorrentes para a mesma disponibilidade não podem originar duas Consultas sobrepostas. 6. Apenas o Rececionista possui autorização para executar o agendamento. | O28: 1. Merge Request com código, validações e descrição das verificações manuais. 2. Pedidos e respostas obtidos para operação correspondente da API v02 (ficheiro de pedidos ou capturas do Swagger/Postman). 3. Commits ligados à Issue e eventuais alterações ao esquema comunicadas à tarefa de scripts de base de dados. | P28: 1. Executar a API a partir de um clone limpo e repetir, no mínimo, um pedido válido e um pedido de erro por operação. 2. Disparar pedidos concorrentes (por exemplo com um script curto) e confirmar que só um é aceite e que a base fica coerente. 3. Confirmar que cada perfil autorizado consegue e um perfil não autorizado não consegue, que os códigos HTTP e as mensagens correspondem à Documentação de API e que as divergências foram registadas. | Q28: Checklist de auditoria 02.05 completa: independência dos três papéis, relatório de revisão 02.04, prazos de 48 h e 24 h, pontos, versão final e pasta. Confirmar que a proteção de concorrência está na base de dados e não apenas na aplicação. | R28: I069; I071; I018; I059. | S28: DoD G08 v01: resultado produzido e acessível; critérios de aceitação cumpridos; revisão e auditoria concluídas; versão final aprovada, corretamente nomeada e arquivada na pasta prevista. Em código: integrado no repositório por Merge Request aprovado pelo Revisor, conforme o regulamento interno do grupo; compila e passa na verificação local sem erros; sem segredos no repositório; divergências face à Documentação de API ou ao Modelo de Dados registadas e decididas. | T28: Documentação de API v02 (I018); Especificação de Requisitos v02 (I012), RF021; Casos de Uso v02 (I015); Modelo de Dados v02 (I016); Modelo de Classes Backend v02 (I020); Arquitetura v02 (I019); Regulamento de Funcionamento da UC v19; Regulamento Interno do Grupo G08 v02 (proposta). | U28: /projeto/04-artefactos-tecnicos/04.12-backend/m3-v01 (código desenvolvido no repositório Git do grupo e arquivado nesta pasta na entrega da M3) | V28: Sim | W28: Pendente | X28: Aprovada como Ready | Y28: 46314 | Z28: /projeto/01-artefactos-de-gestao/01.03-reunioes-de-grupo/m3-s04-20261019-backlog-refinement-ata-v01.pdf | AA28: 2026-10-14 23:05 — Tarefa criada na proposta de refinamento (versão de trabalho), por divisão da Issue original I025 «Desenvolver Backend». Ainda não analisada em Backlog Refinement: orçamento, DoR e decisão por ratificar. 2026-10-21 15:30 — Versão de trabalho v03: registada a decisão do Backlog Refinement de 2026-10-19 (Aprovada como Ready; DoR = Sim; orçamento 50; ata m3-20261019-s04-ata-backlog-refinement-v01.pdf, secção 4 e deliberação 3). A redação desta Issue foi atualizada em 2026-10-20 na rebaseline M3 (retirada de F005/F007 do âmbito, requisitos RF, API v02). O Sprint Planning S04 (2026-10-20 a 2026-10-21) manteve o texto aprovado em 2026-10-19; a alteração de redação será apreciada no Backlog Refinement do Sprint 05. 2026-10-27 — Correção da referência à ata (proposta para o Backlog Refinement do Sprint 05): o ficheiro arquivado chama-se m3-s04-20261019-backlog-refinement-ata-v01.pdf; o nome anterior não correspondia a nenhum ficheiro. 2026-10-27 — Sprint Review do Sprint 04: sem resultado aproveitável à data da reunião (0 pontos no Sprint 04, m3-s04-20261027-sprint-review-ata-v01.pdf); a tarefa mantém-se Ready e transita para o Sprint 05.
A29: I091 | B29: Criar a infraestrutura dos testes de integração | C29: Criar a infraestrutura comum dos testes de integração com WebApplicationFactory, arranque da API, SQL Server de teste isolado, aplicação das EF Core 10 Migrations, carregamento controlado de dados fictícios, autenticação por perfil e limpeza/reposição entre execuções. | D29: Permitir escrever e executar testes de integração isolados, reproduzíveis e independentes entre si sobre a aplicação e a base de dados reais de teste. | E29: Teste | F29: Infraestrutura comum dos testes de integração implementada no projeto de testes do backend e validada por execução local e na pipeline (arquivo final em /projeto/04-artefactos-tecnicos/04.12-backend/m3-v01). | G29: 1 — Crítica | H29: m3 | I29: S04 | J29: 50 | K29: =IF(ISNUMBER(J29),J29*60%,IF(J29="","Por preencher",J29)) -> 30 | L29: =IF(ISNUMBER(J29),J29*30%,IF(J29="","Por preencher",J29)) -> 15 | M29: =IF(ISNUMBER(J29),J29*10%,IF(J29="","Por preencher",J29)) -> 5 | N29: 1. Todos os casos da Especificação de Testes de Integração (I030) aplicáveis a estas áreas estão implementados com o identificador do caso no nome do teste. 2. Cada teste corre contra a API real em memória e uma base de dados SQL Server isolada e é independente da ordem de execução. 3. Uma classe base ou fixture fornece cliente HTTP autenticado para cada perfil com uma única linha. 4. A base de dados de teste é criada e destruída automaticamente, também na pipeline, sem instâncias partilhadas. 5. Um teste de demonstração de autenticação e um de isolamento entre testes passam e documentam o padrão. 6. A execução termina sem falhas, com resultados guardados em formato legível pela pipeline. | O29: 1. Merge Request com os testes. 2. Registo da execução local e na pipeline. 3. Tabela caso da especificação ↔ teste, com casos não implementados justificados. | P29: 1. Executar os testes num clone limpo e confirmar que passam em duas execuções consecutivas e em ordem aleatória. 2. Alterar deliberadamente uma validação ou uma política e confirmar que o teste correspondente falha. 3. Confirmar que dois testes executados em paralelo não partilham dados e que a base é criada de raiz em cada execução. | Q29: Checklist de auditoria 02.05 completa: independência dos três papéis, relatório de revisão 02.04, prazos de 48 h e 24 h, pontos, versão final e pasta. Confirmar a independência entre testes, a repetibilidade e a correspondência com os casos especificados. | R29: I058 — Criar a solução base do backend e a infraestrutura transversal da API; I059 — Implementar a camada de persistência com Entity Framework Core conforme Modelo de Dados v02; I060 — Gerar e validar o script SQL do esquema a partir das migrations EF Core; I061 — Preparar dados iniciais e de demonstração coerentes com o âmbito v02; I062 — Preparar migrations e reposição da base de dados por ambiente; I063 — Implementar autenticação JWT e controlo de acesso por perfil. | S29: DoD G08 v01: resultado produzido e acessível; critérios de aceitação cumpridos; revisão e auditoria concluídas; versão final aprovada, corretamente nomeada e arquivada na pasta prevista. Em testes: casos executáveis de forma repetível por qualquer elemento do grupo; resultados guardados com a versão do código testado; falhas registadas com a ação tomada; rastreabilidade aos requisitos atualizada. | T29: Especificação de Testes de Integração (I030); Documentação de API v02 (I018); Modelo de Dados v02 (I016); xUnit e WebApplicationFactory; Regulamento de Funcionamento da UC v19, secção 19 (03.01.03). | U29: /projeto/04-artefactos-tecnicos/04.12-backend/m3-v01 (código desenvolvido no repositório Git do grupo e arquivado nesta pasta na entrega da M3) | V29: Sim | W29: Done | X29: Aprovada como Ready | Y29: 46314 | Z29: /projeto/01-artefactos-de-gestao/01.03-reunioes-de-grupo/m3-s04-20261019-backlog-refinement-ata-v01.pdf | AA29: 2026-10-14 23:05 — Tarefa criada na proposta de refinamento (versão de trabalho), por divisão da Issue original I031 «Implementar e Executar Testes de Integração do Backend». Ainda não analisada em Backlog Refinement: orçamento, DoR e decisão por ratificar. 2026-10-21 15:30 — Versão de trabalho v03: registada a decisão do Backlog Refinement de 2026-10-19 (Aprovada como Ready; DoR = Sim; orçamento 50; ata m3-20261019-s04-ata-backlog-refinement-v01.pdf, secção 4 e deliberação 3). A redação desta Issue foi atualizada em 2026-10-20 na rebaseline M3 (retirada de F005/F007 do âmbito, requisitos RF, API v02). O Sprint Planning S04 (2026-10-20 a 2026-10-21) manteve o texto aprovado em 2026-10-19; a alteração de redação será apreciada no Backlog Refinement do Sprint 05. 2026-10-27 — Correção da referência à ata (proposta para o Backlog Refinement do Sprint 05): o ficheiro arquivado chama-se m3-s04-20261019-backlog-refinement-ata-v01.pdf; o nome anterior não correspondia a nenhum ficheiro. 2026-10-27 — Sprint Review do Sprint 04: tarefa aceite e estado alterado para Done (m3-s04-20261027-sprint-review-ata-v01.pdf).
... A34: I104 | B34: Disponibilizar o backend em ambiente público de avaliação com entrega contínua | C34: Disponibilizar o backend num ambiente público/de avaliação quando exigido pela entrega, através de processo automatizado após passagem dos quality gates. O ambiente deve usar HTTPS, configuração/segredos seguros, SQL Server próprio, EF Core 10 Migrations e dados fictícios adequados à demonstração. | D34: Disponibilizar o backend da M3 para avaliação e integração com os frontends num ambiente reproduzível e controlado, quando exigido pela entrega. | E34: DevOps / CI/CD | F34: Backend acessível por HTTPS num endereço público, com entrega automática pela pipeline e credenciais de avaliação limitadas. | G34: 1 — Crítica | H34: m3 | I34: S05 | J34: 50 | K34: =IF(ISNUMBER(J34),J34*60%,IF(J34="","Por preencher",J34)) -> 30 | L34: =IF(ISNUMBER(J34),J34*30%,IF(J34="","Por preencher",J34)) -> 15 | M34: =IF(ISNUMBER(J34),J34*10%,IF(J34="","Por preencher",J34)) -> 5 | N34: 1. O endereço público responde em HTTPS e o Swagger (ou equivalente) permite iniciar sessão com uma conta de avaliação. 2. A entrega só ocorre quando todas as etapas e quality gates da pipeline passam no ramo principal. 3. A base de dados pública é distinta das de desenvolvimento e das de defesa individual e está populada apenas com dados fictícios. 4. Chaves e cadeias de ligação estão apenas em segredos da plataforma e a documentação refere como rodá-los. 5. Existe um procedimento escrito para repor a base de dados pública e para reverter para a versão anterior. | O34: 1. Endereço público e capturas da resposta. 2. Execução da pipeline que fez o deploy. 3. Procedimento de reposição e reversão. | P34: 1. Aceder ao endereço a partir de rede externa e executar login e uma consulta com uma conta de avaliação. 2. Confirmar que um deploy falha quando o gate falha. 3. Confirmar a ausência de segredos no repositório. | Q34: Checklist de auditoria 02.05 completa: independência dos três papéis, relatório de revisão 02.04, prazos de 48 h e 24 h, pontos, versão final e pasta. Confirmar que as credenciais de avaliação são limitadas e documentadas no ficheiro de credenciais e que o ambiente público é isolado dos restantes. | R34: I103 — Integrar análise estática, cobertura e quality gates na pipeline; I061 — Escrever os scripts de dados iniciais e de demonstração; I062 — Preparar as migrações e a reposição da base de dados por ambiente. | S34: DoD G08 v01: resultado produzido e acessível; critérios de aceitação cumpridos; revisão e auditoria concluídas; versão final aprovada, corretamente nomeada e arquivada na pasta prevista. Em CI/CD: configuração versionada e reproduzível; execução real na plataforma adotada com a ligação da execução registada; etapas obrigatórias a bloquear a integração quando falham; sem credenciais no repositório. | T34: Regulamento de Funcionamento da UC v19, secção 20.2 e secção 19 (04.16-ci-cd; credenciais em 00-indice-e-submissao); Regulamento Interno do Grupo G08 v02 (proposta); documentação da plataforma de alojamento escolhida. | U34: /projeto/04-artefactos-tecnicos/04.16-ci-cd/m3-v01 | V34: Sim | W34: Pendente | X34: Aprovada como Ready | Y34: 46322 | Z34: /projeto/01-artefactos-de-gestao/01.03-reunioes-de-grupo/m3-s05-20261027-backlog-refinement-ata-v01.pdf | AA34: 2026-10-14 23:05 — Tarefa criada na proposta de refinamento (versão de trabalho), por divisão da Issue original I035 «Implementar a pipeline CI/CD do backend». Ainda não analisada em Backlog Refinement: orçamento, DoR e decisão por ratificar. Nota: Requisito de disponibilização pública referido na secção 20.2; confirmar o âmbito no enunciado Moodle da M3. 2026-10-27 — Backlog Refinement do Sprint 05: aprovada como Ready, com Definition of Ready confirmada, orçamento de 50 pontos e repartição 60% / 30% / 10%.
A35: I107 | B35: Criar a base do frontend web em React e TypeScript | C35: Criar a base técnica do Frontend Web com TypeScript 6.0, React 19.3, Node.js 24 LTS, Vite 8.3 e npm 12, incluindo routing, layout/menu por perfil, cliente HTTP centralizado com JWT, tratamento uniforme de erros, configuração da URL da API, ESLint/Prettier e estrutura por módulos ativos. | D35: Dar à equipa uma base Web comum e reutilizável, alinhada com React 19.3/TypeScript 6, para desenvolver os ecrãs em paralelo sem duplicar sessão, navegação e tratamento de erros. | E35: Desenvolvimento | F35: Projeto React 19.3/TypeScript 6.0 compilável e executável, com navegação por perfil e cliente HTTP funcionais, no repositório do frontend web (arquivo final em /projeto/04-artefactos-tecnicos/04.14-frontend-web/m4-v01). | G35: 1 — Crítica | H35: m4 | I35: S06 | J35: 50 | K35: =IF(ISNUMBER(J35),J35*60%,IF(J35="","Por preencher",J35)) -> 30 | L35: =IF(ISNUMBER(J35),J35*30%,IF(J35="","Por preencher",J35)) -> 15 | M35: =IF(ISNUMBER(J35),J35*10%,IF(J35="","Por preencher",J35)) -> 5 | N35: 1. npm ci, npm run build e npm run lint terminam sem erros num clone limpo; TypeScript em modo estrito sem erros. 2. O menu apresentado depende do perfil devolvido pelo backend e as rotas protegidas redirecionam utilizadores sem sessão para o início de sessão. 3. O cliente HTTP adiciona o token a todos os pedidos, regressa ao início de sessão perante 401 e traduz 400, 403, 404, 409 e 422 numa estrutura de erro única consumida pelos formulários. 4. A URL da API é lida da configuração por ambiente; o ficheiro de exemplo não contém valores reais. 5. Existem componentes comuns de formulário, tabela com lista vazia, carregamento e erro, documentados com um exemplo de utilização. 6. O README explica pré-requisitos, instalação, configuração e arranque. | O35: 1. Merge Request com a base do projeto. 2. Registo de npm ci, npm run build e npm run lint. 3. Captura do menu por perfil. | P35: 1. Clonar, instalar e arrancar apenas com o README. 2. Provocar 401 e 403 e confirmar o comportamento. 3. Verificar que o token não é escrito no registo da consola nem em armazenamento persistente além do decidido. 4. Rever a estrutura de pastas face ao Modelo de Classes do Frontend Web. | Q35: Checklist de auditoria 02.05 completa: independência dos três papéis, relatório de revisão 02.04, prazos de 48 h e 24 h, pontos, versão final e pasta. Confirmar que a decisão sobre o armazenamento do token está documentada e que a base cumpre o Modelo de Classes aprovado. | R35: I017 — Protótipo v02; I021 — Modelo de Classes Web v02; I018 — API v02. | S35: DoD G08 v01: resultado produzido e acessível; critérios de aceitação cumpridos; revisão e auditoria concluídas; versão final aprovada, corretamente nomeada e arquivada na pasta prevista. Em código: integrado no repositório por Merge Request aprovado pelo Revisor, conforme o regulamento interno do grupo; compila e passa na verificação local sem erros; sem segredos no repositório; divergências face à Documentação de API ou ao Modelo de Dados registadas e decididas. | T35: Modelo de Classes Frontend Web v02 (I021); Protótipo v02 (I017); Documentação de API v02 (I018); Regulamento Interno do Grupo G08 v02 (proposta); documentação oficial de React 19.3, TypeScript 6, Node.js 24 LTS e Vite 8.3; Regulamento de Funcionamento da UC v19, secção 19 (04.14). | U35: /projeto/04-artefactos-tecnicos/04.14-frontend-web/m4-v01 (código desenvolvido no repositório Git do grupo e arquivado nesta pasta na entrega da M4) | V35: Por verificar | W35: Pendente | X35: Não analisada | AA35: 2026-10-14 23:05 — Tarefa criada na proposta de refinamento (versão de trabalho), por divisão da Issue original I040 «Desenvolver Frontend Web». Ainda não analisada em Backlog Refinement: orçamento, DoR e decisão por ratificar.
A36: I108 | B36: Implementar a autenticação e a gestão de sessão no frontend web (RF001–RF005) | C36: Implementar no Frontend Web início e fim de sessão, recuperação da sessão, tratamento de token expirado/revogado e restrição de rotas, menus e ações conforme o perfil autenticado. A interface não substitui a autorização de referência do backend. | D36: Permitir acesso autenticado no Web e garantir que cada utilizador interno apenas vê e executa as funcionalidades compatíveis com o seu perfil. | E36: Desenvolvimento | F36: Ecrãs e fluxos que cobrem RF001 a RF005 integrados no frontend web e verificados manualmente contra o backend (arquivo final em /projeto/04-artefactos-tecnicos/04.14-frontend-web/m4-v01). | G36: 1 — Crítica | H36: m4 | I36: S06 | J36: 30 | K36: =IF(ISNUMBER(J36),J36*60%,IF(J36="","Por preencher",J36)) -> 18 | L36: =IF(ISNUMBER(J36),J36*30%,IF(J36="","Por preencher",J36)) -> 9 | M36: =IF(ISNUMBER(J36),J36*10%,IF(J36="","Por preencher",J36)) -> 3 | N36: 1. Os ecrãs desta tarefa consomem apenas as operações correspondentes da API v02 e estão disponíveis aos perfis internos Administrador, Rececionista, Veterinário e Auxiliar Veterinário; o perfil Cliente não acede ao frontend web interno. 2. Credenciais inválidas e conta bloqueada mostram a mensagem prevista sem revelar qual o campo incorreto. 3. O fim de sessão chama a operação correspondente da API v02 e impede a reutilização da sessão terminada. 4. Ao expirar ou ser revogada a credencial de acesso, o primeiro pedido não autorizado conduz ao início de sessão com mensagem de sessão terminada. 5. Os erros da API são traduzidos para mensagens em português europeu e os estados de carregamento e falha de ligação são tratados sem bloquear o ecrã. 6. O acesso a rotas e menus respeita o perfil autenticado e é verificado também por endereço direto. | O36: 1. Merge Request com código, capturas de ecrã dos fluxos principais e dos erros tratados. 2. Registo da verificação manual por perfil e por operação. 3. Eventuais divergências face à Documentação de API ou ao protótipo, com a decisão tomada. | P36: 1. Executar a aplicação web a partir de um clone limpo contra o backend com seed e percorrer cada fluxo com cada perfil indicado. 2. Testar sessão expirada, fim de sessão com o botão Voltar e acesso por endereço direto a rotas de outro perfil. 3. Confirmar que não há regras de negócio duplicadas no cliente nem chamadas a endpoints fora do contrato. | Q36: Checklist de auditoria 02.05 completa: independência dos três papéis, relatório de revisão 02.04, prazos de 48 h e 24 h, pontos, versão final e pasta. Confirmar que o acesso por perfil é imposto também por endereço direto e que as capturas correspondem à versão final. | R36: I107; I063; I064; I018. | S36: DoD G08 v01: resultado produzido e acessível; critérios de aceitação cumpridos; revisão e auditoria concluídas; versão final aprovada, corretamente nomeada e arquivada na pasta prevista. Em código: integrado no repositório por Merge Request aprovado pelo Revisor, conforme o regulamento interno do grupo; compila e passa na verificação local sem erros; sem segredos no repositório; divergências face à Documentação de API ou ao Modelo de Dados registadas e decididas. | T36: Protótipo v02 (I017); Modelo de Classes Frontend Web v02 (I021); Documentação de API v02 (I018); Especificação de Requisitos v02 (I012), RF001–RF005; Casos de Uso v02 (I015); Regulamento de Funcionamento da UC v19; Regulamento Interno do Grupo G08 v02 (proposta). | U36: /projeto/04-artefactos-tecnicos/04.14-frontend-web/m4-v01 (código desenvolvido no repositório Git do grupo e arquivado nesta pasta na entrega da M4) | V36: Por verificar | W36: Pendente | X36: Não analisada | AA36: 2026-10-14 23:05 — Tarefa criada na proposta de refinamento (versão de trabalho), por divisão da Issue original I040 «Desenvolver Frontend Web». Ainda não analisada em Backlog Refinement: orçamento, DoR e decisão por ratificar.
A37: I111 | B37: Implementar gestão de Clientes e contas de acesso no frontend web (RF010, RF011, RF053, RF054) | C37: Implementar no Web a gestão administrativa de Clientes e das respetivas contas de acesso: pesquisa/consulta, registo e atualização dos dados administrativos pela Rececionista e criação/atualização da conta por Administrador ou Rececionista, distinguindo claramente Cliente de Utilizador e permitindo Cliente sem conta. | D37: Dar à Rececionista uma gestão clara do Cliente administrativo e, separadamente, da respetiva conta de acesso opcional. | E37: Desenvolvimento | F37: Ecrãs e fluxos que cobrem RF010, RF011, RF053 e RF054 integrados no frontend web e verificados manualmente contra o backend (arquivo final em /projeto/04-artefactos-tecnicos/04.14-frontend-web/m4-v01). | G37: 1 — Crítica | H37: m4 | I37: S06 | J37: 30 | K37: =IF(ISNUMBER(J37),J37*60%,IF(J37="","Por preencher",J37)) -> 18 | L37: =IF(ISNUMBER(J37),J37*30%,IF(J37="","Por preencher",J37)) -> 9 | M37: =IF(ISNUMBER(J37),J37*10%,IF(J37="","Por preencher",J37)) -> 3 | N37: 1. O Rececionista consegue registar e atualizar os dados administrativos de um Cliente independentemente da existência de uma conta de acesso. 2. A criação ou atualização do Cliente administrativo não cria nem altera automaticamente a respetiva conta de acesso. 3. Administrador e Rececionista conseguem criar uma conta de acesso para um Cliente já existente e sem conta e atualizar posteriormente os dados editáveis dessa conta. 4. A criação de uma segunda conta para o mesmo Cliente é rejeitada. 5. A interface distingue claramente «dados do Cliente» de «conta de acesso». 6. As permissões apresentadas na interface respeitam os atores definidos para RF010, RF011, RF053 e RF054 e o acesso direto a operações não autorizadas é impedido. 7. Os erros e estados de carregamento são tratados segundo o contrato da API v02. | O37: 1. Merge Request com código, capturas de ecrã dos fluxos principais e dos erros tratados. 2. Registo da verificação manual por perfil e por operação. 3. Eventuais divergências face à Documentação de API ou ao protótipo, com a decisão tomada. | P37: 1. Executar a aplicação web a partir de um clone limpo contra o backend com seed. 2. Registar um Cliente administrativo sem criar conta de acesso, atualizá-lo e confirmar que os dados da conta não são alterados automaticamente; depois criar/atualizar separadamente uma conta de acesso e confirmar que não é permitida uma segunda conta para o mesmo Cliente. 3. Confirmar que a interface distingue claramente Cliente de conta de acesso e respeita as permissões definidas para RF010, RF011, RF053 e RF054. | Q37: Checklist de auditoria 02.05 completa: independência dos três papéis, relatório de revisão 02.04, prazos de 48 h e 24 h, pontos, versão final e pasta. Confirmar que o acesso por perfil é imposto também por endereço direto e que as capturas correspondem à versão final. | R37: I108; I068; I018. | S37: DoD G08 v01: resultado produzido e acessível; critérios de aceitação cumpridos; revisão e auditoria concluídas; versão final aprovada, corretamente nomeada e arquivada na pasta prevista. Em código: integrado no repositório por Merge Request aprovado pelo Revisor, conforme o regulamento interno do grupo; compila e passa na verificação local sem erros; sem segredos no repositório; divergências face à Documentação de API ou ao Modelo de Dados registadas e decididas. | T37: Protótipo v02 (I017); Modelo de Classes Frontend Web v02 (I021); Documentação de API v02 (I018); Especificação de Requisitos v02 (I012), RF010, RF011, RF053 e RF054; Casos de Uso v02 (I015); Regulamento de Funcionamento da UC v19; Regulamento Interno do Grupo G08 v02 (proposta). | U37: /projeto/04-artefactos-tecnicos/04.14-frontend-web/m4-v01 (código desenvolvido no repositório Git do grupo e arquivado nesta pasta na entrega da M4) | V37: Por verificar | W37: Pendente | X37: Não analisada | AA37: 2026-10-14 23:05 — Tarefa criada na proposta de refinamento (versão de trabalho), por divisão da Issue original I040 «Desenvolver Frontend Web». Ainda não analisada em Backlog Refinement: orçamento, DoR e decisão por ratificar.
A38: I112 | B38: Implementar a gestão de pacientes no frontend web (RF014–RF017) | C38: Implementar no Web o registo, pesquisa, consulta e atualização da ficha administrativa do paciente, associado ao respetivo Cliente, com espécie, raça, idade e peso e com ações disponibilizadas apenas aos perfis autorizados. | D38: Permitir identificar e manter os pacientes no Web, respeitando as permissões e a associação ao proprietário. | E38: Desenvolvimento | F38: Ecrãs e fluxos que cobrem RF014 a RF017 integrados no frontend web e verificados manualmente contra o backend (arquivo final em /projeto/04-artefactos-tecnicos/04.14-frontend-web/m4-v01). | G38: 1 — Crítica | H38: m4 | I38: S06 | J38: 30 | K38: =IF(ISNUMBER(J38),J38*60%,IF(J38="","Por preencher",J38)) -> 18 | L38: =IF(ISNUMBER(J38),J38*30%,IF(J38="","Por preencher",J38)) -> 9 | M38: =IF(ISNUMBER(J38),J38*10%,IF(J38="","Por preencher",J38)) -> 3 | N38: 1. Rececionista e Veterinário conseguem criar e atualizar fichas de pacientes com os dados administrativos da baseline v02, incluindo espécie, raça, idade e peso, associando cada paciente a um Cliente existente. 2. Rececionista, Veterinário e Auxiliar Veterinário conseguem consultar a ficha, mas o Auxiliar não possui ações de edição. 3. Rececionista e Veterinário conseguem pesquisar pacientes por proprietário. 4. A interface não apresenta informação clínica ao Rececionista como parte da ficha administrativa. 5. Dados administrativos inválidos são apresentados ao utilizador sem deixar o ecrã bloqueado. 6. As operações consumidas correspondem exclusivamente ao contrato da API v02. | O38: 1. Merge Request com código, capturas de ecrã dos fluxos principais e dos erros tratados. 2. Registo da verificação manual por perfil e por operação. 3. Eventuais divergências face à Documentação de API ou ao protótipo, com a decisão tomada. | P38: 1. Executar a aplicação web a partir de um clone limpo contra o backend com seed e criar, consultar, atualizar e pesquisar pacientes associados a um Cliente existente. 2. Testar dados administrativos inválidos e confirmar as permissões de Rececionista, Veterinário e Auxiliar Veterinário, incluindo a ausência de edição para o Auxiliar. 3. Confirmar que a ficha administrativa não apresenta ao Rececionista informação clínica indevida e que as chamadas respeitam a API v02. | Q38: Checklist de auditoria 02.05 completa: independência dos três papéis, relatório de revisão 02.04, prazos de 48 h e 24 h, pontos, versão final e pasta. Confirmar que o acesso por perfil é imposto também por endereço direto e que as capturas correspondem à versão final. | R38: I111; I069; I018. | S38: DoD G08 v01: resultado produzido e acessível; critérios de aceitação cumpridos; revisão e auditoria concluídas; versão final aprovada, corretamente nomeada e arquivada na pasta prevista. Em código: integrado no repositório por Merge Request aprovado pelo Revisor, conforme o regulamento interno do grupo; compila e passa na verificação local sem erros; sem segredos no repositório; divergências face à Documentação de API ou ao Modelo de Dados registadas e decididas. | T38: Protótipo v02 (I017); Modelo de Classes Frontend Web v02 (I021); Documentação de API v02 (I018); Especificação de Requisitos v02 (I012), RF014–RF017; Casos de Uso v02 (I015); Regulamento de Funcionamento da UC v19; Regulamento Interno do Grupo G08 v02 (proposta). | U38: /projeto/04-artefactos-tecnicos/04.14-frontend-web/m4-v01 (código desenvolvido no repositório Git do grupo e arquivado nesta pasta na entrega da M4) | V38: Por verificar | W38: Pendente | X38: Não analisada | AA38: 2026-10-14 23:05 — Tarefa criada na proposta de refinamento (versão de trabalho), por divisão da Issue original I040 «Desenvolver Frontend Web». Ainda não analisada em Backlog Refinement: orçamento, DoR e decisão por ratificar.
A39: I113 | B39: Implementar disponibilidade e gestão de Consultas no frontend web (RF020–RF023) | C39: Implementar no Web a consulta de disponibilidade, agendamento e alteração de Consultas e atualização de estado pela Rececionista, respeitando duração, horários da clínica/Veterinário, ausência de sobreposição e as transições de estado aprovadas. | D39: Permitir à Rececionista consultar disponibilidade, agendar/reagendar Consultas e gerir os respetivos estados sem sobreposições inválidas. | E39: Desenvolvimento | F39: Ecrãs e fluxos que cobrem RF020 a RF023 integrados no frontend web e verificados manualmente contra o backend (arquivo final em /projeto/04-artefactos-tecnicos/04.14-frontend-web/m4-v01). | G39: 1 — Crítica | H39: m4 | I39: S06 | J39: 50 | K39: =IF(ISNUMBER(J39),J39*60%,IF(J39="","Por preencher",J39)) -> 30 | L39: =IF(ISNUMBER(J39),J39*30%,IF(J39="","Por preencher",J39)) -> 15 | M39: =IF(ISNUMBER(J39),J39*10%,IF(J39="","Por preencher",J39)) -> 5 | N39: 1. O Rececionista consegue consultar a disponibilidade de um Veterinário e apenas são apresentados períodos válidos segundo o horário da clínica, o horário regular do Veterinário e as Consultas não canceladas. 2. O Rececionista consegue agendar uma Consulta apenas num período disponível; a Consulta criada fica no estado Pendente. 3. Uma alteração de Veterinário ou horário obriga a nova validação de disponibilidade. 4. A interface apresenta apenas as transições de estado permitidas: Pendente para Confirmada ou Cancelada e Confirmada para Realizada ou Cancelada; Realizada e Cancelada são finais. 5. Se uma vaga deixar de estar disponível antes da confirmação, a resposta do backend é apresentada e a disponibilidade é atualizada. 6. Apenas o Rececionista possui ações de agendamento, alteração e atualização de estado, e o acesso direto por outros perfis é impedido. | O39: 1. Merge Request com código, capturas de ecrã dos fluxos principais e dos erros tratados. 2. Registo da verificação manual por perfil e por operação. 3. Eventuais divergências face à Documentação de API ou ao protótipo, com a decisão tomada. | P39: 1. Executar a aplicação web a partir de um clone limpo contra o backend com seed e percorrer cada fluxo com cada perfil indicado. 2. Provocar uma Consulta concorrente em duas janelas e testar todas as transições. 3. Confirmar que não há regras de negócio duplicadas no cliente nem chamadas a endpoints fora do contrato. | Q39: Checklist de auditoria 02.05 completa: independência dos três papéis, relatório de revisão 02.04, prazos de 48 h e 24 h, pontos, versão final e pasta. Confirmar que o acesso por perfil é imposto também por endereço direto e que as capturas correspondem à versão final. | R39: I111; I112; I071; I073; I074; I018. | S39: DoD G08 v01: resultado produzido e acessível; critérios de aceitação cumpridos; revisão e auditoria concluídas; versão final aprovada, corretamente nomeada e arquivada na pasta prevista. Em código: integrado no repositório por Merge Request aprovado pelo Revisor, conforme o regulamento interno do grupo; compila e passa na verificação local sem erros; sem segredos no repositório; divergências face à Documentação de API ou ao Modelo de Dados registadas e decididas. | T39: Protótipo v02 (I017); Modelo de Classes Frontend Web v02 (I021); Documentação de API v02 (I018); Especificação de Requisitos v02 (I012), RF020–RF023; Casos de Uso v02 (I015); Regulamento de Funcionamento da UC v19; Regulamento Interno do Grupo G08 v02 (proposta). | U39: /projeto/04-artefactos-tecnicos/04.14-frontend-web/m4-v01 (código desenvolvido no repositório Git do grupo e arquivado nesta pasta na entrega da M4) | V39: Por verificar | W39: Pendente | X39: Não analisada | AA39: 2026-10-14 23:05 — Tarefa criada na proposta de refinamento (versão de trabalho), por divisão da Issue original I040 «Desenvolver Frontend Web». Ainda não analisada em Backlog Refinement: orçamento, DoR e decisão por ratificar.
A40: I120 | B40: Criar a base da aplicação móvel Android em Kotlin e Jetpack Compose | C40: Criar a base da aplicação Android em Kotlin 2.2 com Jetpack Compose e Material 3, Android SDK 37/minSdk 26, JDK 21, Gradle 9.6 e Android Gradle Plugin 9.4. Incluir navegação, arquitetura de apresentação, cliente HTTP, armazenamento seguro do token, tratamento de erros, configuração da API, ktlint/Android Lint e estrutura para os fluxos ativos do Cliente. | D40: Dar à equipa uma base Android comum em Kotlin/Jetpack Compose para construir os fluxos do Cliente com sessão, navegação, rede e qualidade tratados de forma consistente. | E40: Desenvolvimento | F40: Projeto Android em Kotlin 2.2 com Jetpack Compose/Material 3, compilável com Gradle e executável num emulador Android (minSdk 26), no repositório do frontend mobile (arquivo final em /projeto/04-artefactos-tecnicos/04.15-frontend-mobile/m4-v01). | G40: 1 — Crítica | H40: m4 | I40: S06 | J40: 50 | K40: =IF(ISNUMBER(J40),J40*60%,IF(J40="","Por preencher",J40)) -> 30 | L40: =IF(ISNUMBER(J40),J40*30%,IF(J40="","Por preencher",J40)) -> 15 | M40: =IF(ISNUMBER(J40),J40*10%,IF(J40="","Por preencher",J40)) -> 5 | N40: 1. ./gradlew assembleDebug, ./gradlew testDebugUnitTest, ./gradlew ktlintCheck e ./gradlew lintDebug terminam sem erros num clone limpo. 2. O projeto utiliza Kotlin 2.2, Jetpack Compose com Material 3, Android SDK API 37, minSdk 26 e JDK 21, conforme o Regulamento Interno. 3. A aplicação possui uma camada única de comunicação com a API, tratamento transversal de 401/403 e erros de rede e configuração da URL da API por ambiente. 4. A sessão do Cliente é tratada de forma segura e os dados de autenticação são removidos no fim de sessão. 5. O README técnico explica os pré-requisitos, instalação, configuração e execução num emulador Android. | O40: 1. Merge Request com a base da aplicação móvel. 2. Registo de ./gradlew assembleDebug, ./gradlew testDebugUnitTest, ./gradlew ktlintCheck e ./gradlew lintDebug. 3. Capturas da navegação inicial e evidência de execução num emulador Android. | P40: 1. A partir de um clone limpo, seguir apenas o README e executar ./gradlew assembleDebug, ./gradlew testDebugUnitTest, ./gradlew ktlintCheck e ./gradlew lintDebug, confirmando sucesso. 2. Executar a aplicação num emulador Android e confirmar a configuração da API, o tratamento da sessão e a remoção dos dados de autenticação no fim de sessão. 3. Simular falha de rede e confirmar o tratamento previsto sem bloqueio da aplicação. | Q40: Checklist de auditoria 02.05 completa: independência dos três papéis, relatório de revisão 02.04, prazos de 48 h e 24 h, pontos, versão final e pasta. Confirmar que o acesso por perfil é imposto também por endereço direto e que as capturas correspondem à versão final. | R40: I022 — Modelo de Classes Frontend Mobile v02; I017 — Protótipo de baixa fidelidade v02; I018 — Documentação de API v02. | S40: DoD G08 v01: resultado produzido e acessível; critérios de aceitação cumpridos; revisão e auditoria concluídas; versão final aprovada, corretamente nomeada e arquivada na pasta prevista. Em código: integrado no repositório por Merge Request aprovado pelo Revisor, conforme o regulamento interno do grupo; compila e passa na verificação local sem erros; sem segredos no repositório; divergências face à Documentação de API ou ao Modelo de Dados registadas e decididas. | T40: Modelo de Classes Frontend Mobile v02 (I022); Protótipo v02 (I017); Documentação de API v02 (I018); Regulamento Interno do Grupo G08 v02 (proposta); documentação oficial de Kotlin 2.2, Jetpack Compose, Material 3, Android API 37, JDK 21, Gradle 9.6 e AGP 9.4; Regulamento de Funcionamento da UC v19, secção 19 (04.15). | U40: /projeto/04-artefactos-tecnicos/04.15-frontend-mobile/m4-v01 (código desenvolvido no repositório Git do grupo e arquivado nesta pasta na entrega da M4) | V40: Por verificar | W40: Pendente | X40: Não analisada | AA40: 2026-10-14 23:05 — Tarefa criada na proposta de refinamento (versão de trabalho), por divisão da Issue original I041 «Desenvolver Frontend Mobile». Ainda não analisada em Backlog Refinement: orçamento, DoR e decisão por ratificar.
A41: I121 | B41: Implementar a autenticação do Cliente na aplicação móvel (RF001–RF005) | C41: Implementar na aplicação Android o início e fim de sessão do Cliente, manutenção/recuperação da sessão, tratamento de token expirado/revogado e rejeição de utilização por contas cujo perfil não seja Cliente. | D41: Permitir ao Cliente autenticar-se e terminar sessão em segurança na aplicação Android. | E41: Desenvolvimento | F41: Ecrãs e fluxos que cobrem RF001 a RF005 integrados no frontend mobile e verificados manualmente contra o backend (arquivo final em /projeto/04-artefactos-tecnicos/04.15-frontend-mobile/m4-v01). | G41: 1 — Crítica | H41: m4 | I41: S06 | J41: 30 | K41: =IF(ISNUMBER(J41),J41*60%,IF(J41="","Por preencher",J41)) -> 18 | L41: =IF(ISNUMBER(J41),J41*30%,IF(J41="","Por preencher",J41)) -> 9 | M41: =IF(ISNUMBER(J41),J41*10%,IF(J41="","Por preencher",J41)) -> 3 | N41: 1. A autenticação na aplicação móvel consome apenas as operações correspondentes da API v02 e destina-se exclusivamente ao perfil Cliente. 2. Contas de perfis internos são recusadas na aplicação com mensagem clara e sem conservar uma sessão válida. 3. A sessão é recuperada ao reabrir a aplicação enquanto a credencial permanecer válida e termina de forma controlada quando expira ou é invalidada. 4. O fim de sessão chama a operação correspondente da API v02 e remove os dados de autenticação armazenados. 5. Os erros da API e de rede são apresentados em português europeu sem expor informação sensível. 6. Os estados de carregamento, erro e sessão terminada são tratados sem bloquear a aplicação. | O41: 1. Merge Request com código, capturas de ecrã dos fluxos principais e dos erros tratados. 2. Registo da verificação manual por perfil e por operação. 3. Eventuais divergências face à Documentação de API ou ao protótipo, com a decisão tomada. | P41: 1. Executar a aplicação móvel a partir de um clone limpo contra o backend com seed e percorrer cada fluxo com cada perfil indicado. 2. Testar reabrir a aplicação, sessão expirada e início de sessão com um perfil interno. 3. Confirmar que não há regras de negócio duplicadas no cliente nem chamadas a endpoints fora do contrato. | Q41: Checklist de auditoria 02.05 completa: independência dos três papéis, relatório de revisão 02.04, prazos de 48 h e 24 h, pontos, versão final e pasta. Confirmar que o acesso por perfil é imposto também por endereço direto e que as capturas correspondem à versão final. | R41: I120 — Criar a base da aplicação móvel em Kotlin/Jetpack Compose; I063 — Implementar autenticação JWT e controlo de acesso por perfil; I064 — Implementar o fim de sessão com revogação do token. | S41: DoD G08 v01: resultado produzido e acessível; critérios de aceitação cumpridos; revisão e auditoria concluídas; versão final aprovada, corretamente nomeada e arquivada na pasta prevista. Em código: integrado no repositório por Merge Request aprovado pelo Revisor, conforme o regulamento interno do grupo; compila e passa na verificação local sem erros; sem segredos no repositório; divergências face à Documentação de API ou ao Modelo de Dados registadas e decididas. | T41: Protótipo v02 (I017); Modelo de Classes Frontend Mobile v02 (I022); Documentação de API v02 (I018); Especificação de Requisitos v02 (I012), RF001–RF005; Casos de Uso v02 (I015); Regulamento de Funcionamento da UC v19; Regulamento Interno do Grupo G08 v02 (proposta). | U41: /projeto/04-artefactos-tecnicos/04.15-frontend-mobile/m4-v01 (código desenvolvido no repositório Git do grupo e arquivado nesta pasta na entrega da M4) | V41: Por verificar | W41: Pendente | X41: Não analisada | AA41: 2026-10-14 23:05 — Tarefa criada na proposta de refinamento (versão de trabalho), por divisão da Issue original I041 «Desenvolver Frontend Mobile». Ainda não analisada em Backlog Refinement: orçamento, DoR e decisão por ratificar.
A42: I125 | B42: Validar e corrigir fluxos integrados do frontend web — identidade, registo, agenda e clínico | C42: Executar ponta a ponta os fluxos Web ativos contra o backend: autenticação, funcionários, clínica/horários, Clientes e contas, pacientes, disponibilidade/agendamento, agenda, chegada/apoio, registo e histórico clínico. Corrigir defeitos do Frontend Web e registar separadamente os defeitos do backend. | D42: Garantir que os principais fluxos Web ativos funcionam ponta a ponta com o backend real antes da execução final dos testes de sistema. | E42: Desenvolvimento | F42: Fluxos descritos validados no ambiente de integração, defeitos corrigidos ou registados e roteiro dos fluxos arquivado no Pull Request correspondente. | G42: 1 — Crítica | H42: m4 | I42: S07 | J42: 50 | K42: =IF(ISNUMBER(J42),J42*60%,IF(J42="","Por preencher",J42)) -> 30 | L42: =IF(ISNUMBER(J42),J42*30%,IF(J42="","Por preencher",J42)) -> 15 | M42: =IF(ISNUMBER(J42),J42*10%,IF(J42="","Por preencher",J42)) -> 5 | N42: 1. Estão documentados os fluxos de integração (passos, perfil e dados) e todos foram executados com sucesso do início ao fim no ambiente de integração. 2. Cada defeito encontrado tem Issue com origem (frontend ou backend), correção ou decisão de adiamento; não há defeitos bloqueadores abertos nestes fluxos. 3. O comportamento perante 401, 403, 422 e perda de ligação é igual em todos os ecrãs destes fluxos. 4. Se o backend foi alterado, a nova versão está arquivada como m4-v02 e a Documentação de API foi atualizada com autorização quando houve alteração de contrato. 5. Os fluxos são executáveis por outra pessoa com as contas e dados de teste documentados. | O42: 1. Roteiro dos fluxos executados com resultados. 2. Lista de Issues de defeitos com estado. 3. Capturas de ecrã ou gravação curta de cada fluxo. | P42: 1. Executar os fluxos com contas diferentes das do Executor, seguindo apenas o roteiro. 2. Confirmar o tratamento dos erros nos fluxos e a decisão tomada sobre cada defeito. | Q42: Checklist de auditoria 02.05 completa: independência dos três papéis, relatório de revisão 02.04, prazos de 48 h e 24 h, pontos, versão final e pasta. Confirmar rastreabilidade e a independência entre cenários. | R42: I108–I116; backend v02 correspondente. | S42: DoD G08 v01: resultado produzido e acessível; critérios de aceitação cumpridos; revisão e auditoria concluídas; versão final aprovada, corretamente nomeada e arquivada na pasta prevista. Em código: integrado no repositório por Merge Request aprovado pelo Revisor, conforme o regulamento interno do grupo; compila e passa na verificação local sem erros; sem segredos no repositório; divergências face à Documentação de API ou ao Modelo de Dados registadas e decididas. | T42: Documentação de API v02 (I018); Especificação de Requisitos v02 (I012); Casos de Uso v02 (I015); Protótipo v02 (I017); Regulamento de Funcionamento da UC v19, secção 19 (04.14 e/ou 04.15 conforme o componente); Regulamento Interno do Grupo G08 v02 (proposta). | U42: /projeto/04-artefactos-tecnicos/04.14-frontend-web/m4-v01 (código desenvolvido no repositório Git do grupo e arquivado nesta pasta na entrega da M4) | V42: Por verificar | W42: Pendente | X42: Não analisada | AA42: 2026-10-14 23:05 — Tarefa criada na proposta de refinamento (versão de trabalho), por divisão da Issue original I042 «Integrar Frontends com Backend». Ainda não analisada em Backlog Refinement: orçamento, DoR e decisão por ratificar.
A43: I142 | B43: Integrar a compilação, a análise estática e os testes do frontend web na pipeline | C43: Integrar no GitHub Actions as verificações do Frontend Web: Node.js 24 LTS/npm 12, npm build sem erros, ESLint sem warnings/errors, Prettier format:check sem alterações pendentes e testes de sistema Playwright a 100%, publicando os relatórios/evidências necessários. | D43: Garantir que o Frontend Web é compilado, analisado, formatado e testado automaticamente em cada alteração e que qualquer falha obrigatória bloqueia a integração. | E43: DevOps / CI/CD | F43: Workflow .github/workflows/frontend-ci.yml do GitHub Actions com formatação, análise estática, testes e build do frontend web, com configuração arquivada em 04.16-ci-cd/m4-v02. | G43: 1 — Crítica | H43: m4 | I43: S08 | J43: 30 | K43: =IF(ISNUMBER(J43),J43*60%,IF(J43="","Por preencher",J43)) -> 18 | L43: =IF(ISNUMBER(J43),J43*30%,IF(J43="","Por preencher",J43)) -> 9 | M43: =IF(ISNUMBER(J43),J43*10%,IF(J43="","Por preencher",J43)) -> 3 | N43: 1. Em cada push e Merge Request, a pipeline compila o web, executa a análise estática e os testes de sistema e publica os resultados como artefactos. 2. Os testes de sistema correm contra um backend e uma base de dados criados na execução, sem instâncias partilhadas. 3. Falha de compilação, de teste ou de quality gate do web bloqueia o merge, demonstrado com execuções provocadas. 4. A duração total da pipeline está dentro do limite acordado e a configuração não contém credenciais. | O43: 1. Workflows atualizados. 2. Execuções com sucesso e com falha provocada. 3. Relatórios anexados. | P43: 1. Provocar falhas de compilação, de teste e de gate e confirmar o bloqueio. 2. Confirmar a ausência de credenciais. | Q43: Checklist de auditoria 02.05 completa: independência dos três papéis, relatório de revisão 02.04, prazos de 48 h e 24 h, pontos, versão final e pasta. Confirmar que o ambiente de produção é distinto dos de defesa individual e que os dados são fictícios. | R43: I129 — Automatizar os testes de sistema do frontend web — identidade e registo; I130 — Automatizar os testes de sistema Web — Consultas, agenda e registo clínico; I131 — Automatizar testes de sistema Web — vacinação e desparasitação; I132 — Automatizar os testes de sessão, permissões e falhas de rede do frontend web; I046 — Executar a análise estática do frontend web e produzir o relatório; I103 — Integrar análise estática, cobertura e quality gates na pipeline. | S43: DoD G08 v01: resultado produzido e acessível; critérios de aceitação cumpridos; revisão e auditoria concluídas; versão final aprovada, corretamente nomeada e arquivada na pasta prevista. Em CI/CD: configuração versionada e reproduzível; execução real na plataforma adotada com a ligação da execução registada; etapas obrigatórias a bloquear a integração quando falham; sem credenciais no repositório. | T43: Regulamento Interno do Grupo G08 v02 (proposta); documentação oficial do GitHub Actions, Node.js/npm, ESLint/Prettier e Playwright; Regulamento de Funcionamento da UC v19, secções 17 e 19 (04.16-ci-cd). | U43: /projeto/04-artefactos-tecnicos/04.16-ci-cd/m4-v02 | V43: Por verificar | W43: Pendente | X43: Não analisada | AA43: 2026-10-14 23:05 — Tarefa criada na proposta de refinamento (versão de trabalho), por divisão da Issue original I052 «Atualizar Pipeline CI/CD para sistema completo». Ainda não analisada em Backlog Refinement: orçamento, DoR e decisão por ratificar.
A44: I143 | B44: Integrar a compilação, a análise estática e os testes do frontend mobile na pipeline | C44: Integrar no GitHub Actions as verificações da aplicação Android: JDK 21, Gradle 9.6/AGP 9.4, assembleDebug sem erros, ktlintCheck, lintDebug com warningsAsErrors e testes automáticos Compose UI Test/Robolectric/JUnit definidos, bloqueando o Pull Request perante qualquer falha. | D44: Garantir que a aplicação Android é compilada, analisada, formatada e testada automaticamente em cada alteração e que qualquer falha obrigatória bloqueia a integração. | E44: DevOps / CI/CD | F44: Workflow .github/workflows/mobile-ci.yml do GitHub Actions com ktlint, Android Lint, testes e build da aplicação móvel, com configuração arquivada em 04.16-ci-cd/m4-v02. | G44: 1 — Crítica | H44: m4 | I44: S08 | J44: 30 | K44: =IF(ISNUMBER(J44),J44*60%,IF(J44="","Por preencher",J44)) -> 18 | L44: =IF(ISNUMBER(J44),J44*30%,IF(J44="","Por preencher",J44)) -> 9 | M44: =IF(ISNUMBER(J44),J44*10%,IF(J44="","Por preencher",J44)) -> 3 | N44: 1. Em cada push e Merge Request, a pipeline analisa, testa e compila o APK e publica os resultados como artefactos. 2. Os testes de sistema correm em emulador sem interface contra um backend criado na execução. 3. Falha de análise, de teste ou de gate do mobile bloqueia o merge, demonstrado com execuções provocadas. 4. O APK gerado fica disponível como artefacto da execução. | O44: 1. Workflows atualizados. 2. Execuções com sucesso e com falha provocada. 3. APK e relatórios anexados. | P44: 1. Provocar falhas e confirmar o bloqueio. 2. Instalar o APK produzido num emulador. | Q44: Checklist de auditoria 02.05 completa: independência dos três papéis, relatório de revisão 02.04, prazos de 48 h e 24 h, pontos, versão final e pasta. Confirmar que não há credenciais pessoais e que o índice coincide com o ZIP. | R44: I137 — Automatizar os testes de sistema do frontend mobile; I138 — Automatizar os testes de sessão, permissões e falhas de rede do frontend mobile; I050 — Executar a análise estática do frontend mobile e produzir o relatório; I103 — Integrar análise estática, cobertura e quality gates na pipeline. | S44: DoD G08 v01: resultado produzido e acessível; critérios de aceitação cumpridos; revisão e auditoria concluídas; versão final aprovada, corretamente nomeada e arquivada na pasta prevista. Em CI/CD: configuração versionada e reproduzível; execução real na plataforma adotada com a ligação da execução registada; etapas obrigatórias a bloquear a integração quando falham; sem credenciais no repositório. | T44: Regulamento Interno do Grupo G08 v02 (proposta); documentação oficial do GitHub Actions, Kotlin/Gradle, ktlint, Android Lint e testes Android; Regulamento de Funcionamento da UC v19, secções 17 e 19 (04.16-ci-cd). | U44: /projeto/04-artefactos-tecnicos/04.16-ci-cd/m4-v02 | V44: Por verificar | W44: Pendente | X44: Não analisada | AA44: 2026-10-14 23:05 — Tarefa criada na proposta de refinamento (versão de trabalho), por divisão da Issue original I052 «Atualizar Pipeline CI/CD para sistema completo». Ainda não analisada em Backlog Refinement: orçamento, DoR e decisão por ratificar.
A45: I005 | B45: Elaborar Regulamento Interno do Grupo | C45: Concretizar o Regulamento Interno do Grupo G08 a partir do modelo oficial, definindo comunicação, organização, ferramentas, tecnologias, reuniões, regras internas e demais opções do grupo. | D45: Estabelecer uma referência comum para o funcionamento do grupo sem contrariar os documentos oficiais da UC. | E45: Gestão | F45: m1-regulamento-grupo-v01.pdf | G45: 2 — Alta | H45: m1 | I45: S01 | J45: 30 | K45: =IF(ISNUMBER(J45),J45*60%,IF(J45="","Por preencher",J45)) -> 18 | L45: =IF(ISNUMBER(J45),J45*30%,IF(J45="","Por preencher",J45)) -> 9 | M45: =IF(ISNUMBER(J45),J45*10%,IF(J45="","Por preencher",J45)) -> 3 | N45: Conteúdo fixo preservado; todos os campos obrigatórios concretizados; opções internas não contradizem a UC; identificação do grupo e versão corretas; documento aprovado e assinado. | O45: m1-regulamento-grupo-v01.pdf; versão de trabalho; registo das opções adotadas pelo grupo. | P45: Comparar com o modelo oficial; verificar campos obrigatórios, coerência das regras internas, tecnologias, prazos, nomenclatura e ausência de alterações ao conteúdo fixo. | Q45: Confirmar revisão, aprovação pelos quatro elementos, versão final, assinaturas aplicáveis e pasta de destino. | R45: Regulamento UC v19; constituição do Grupo G08. | S45: DoD G08 v01: resultado produzido e acessível; critérios de aceitação cumpridos; revisão e auditoria concluídas; versão final aprovada, corretamente nomeada e arquivada na pasta prevista. | T45: Regulamento de Funcionamento da UC v19; Regulamento Interno dos Grupos (proposta/template). | U45: /projeto/01-artefactos-de-gestao/01.02-regulamento-de-grupo | V45: Sim | W45: Done | X45: Aprovada como Ready | Y45: 46283 | Z45: /projeto/01-artefactos-de-gestao/01.03-reunioes-de-grupo/m1-20260918-backlog-refinement-ata-v01.pdf | AA45: 2026-09-30 — Regularização documental: esta linha reconstitui trabalho efetivamente realizado durante a M1 com base nos artefactos existentes. O registo foi preparado posteriormente para completar a rastreabilidade do processo e não altera o conteúdo técnico entregue.
A46: I006 | B46: Elaborar Plano de Qualidade do Processo | C46: Definir os objetivos, responsabilidades, procedimentos, métricas, verificações e quality gates aplicáveis ao processo de desenvolvimento do Grupo G08. | D46: Estabelecer um processo verificável para planeamento, execução, revisão, auditoria, controlo de versões, arquivo e rastreabilidade. | E46: Qualidade de processo | F46: m1-plano-qualidade-processo-v01.pdf | G46: 2 — Alta | H46: m1 | I46: S01 | J46: 50 | K46: =IF(ISNUMBER(J46),J46*60%,IF(J46="","Por preencher",J46)) -> 30 | L46: =IF(ISNUMBER(J46),J46*30%,IF(J46="","Por preencher",J46)) -> 15 | M46: =IF(ISNUMBER(J46),J46*10%,IF(J46="","Por preencher",J46)) -> 5 | N46: Plano identifica âmbito, referências, responsabilidades, procedimentos, métricas e quality gates; é coerente com Regulamento, PS, DA, CCA, DoR e DoD. | O46: m1-plano-qualidade-processo-v01.pdf; versão fonte; referências aos artefactos normativos do grupo. | P46: Verificar completude das secções, coerência com os documentos do grupo, aplicabilidade dos procedimentos e consistência das métricas/quality gates. | Q46: Confirmar revisão independente, referências corretas, versão final, inexistência de contradições e arquivo adequado. | R46: I005; I001; I002; I003. | S46: DoD G08 v01: resultado produzido e acessível; critérios de aceitação cumpridos; revisão e auditoria concluídas; versão final aprovada, corretamente nomeada e arquivada na pasta prevista. | T46: Regulamento de Funcionamento da UC v19; Regulamento G08; PS; DA; CCA. | U46: /projeto/02-artefactos-de-qualidade-de-processo/02.01-plano-de-qualidade | V46: Sim | W46: Done | X46: Aprovada como Ready | Y46: 46283 | Z46: /projeto/01-artefactos-de-gestao/01.03-reunioes-de-grupo/m1-20260918-backlog-refinement-ata-v01.pdf | AA46: 2026-09-30 — Regularização documental: esta linha reconstitui trabalho efetivamente realizado durante a M1 com base nos artefactos existentes. O registo foi preparado posteriormente para completar a rastreabilidade do processo e não altera o conteúdo técnico entregue.
A47: I007 | B47: Elaborar Definition of Ready | C47: Definir as condições mínimas que uma tarefa deve cumprir para poder ser aprovada como Ready e selecionada num Sprint Planning. | D47: Garantir que tarefas entram num sprint apenas quando possuem informação suficiente para execução, revisão e auditoria. | E47: Qualidade de processo | F47: m1-definition-of-ready-v01.pdf | G47: 2 — Alta | H47: m1 | I47: S01 | J47: 20 | K47: =IF(ISNUMBER(J47),J47*60%,IF(J47="","Por preencher",J47)) -> 12 | L47: =IF(ISNUMBER(J47),J47*30%,IF(J47="","Por preencher",J47)) -> 6 | M47: =IF(ISNUMBER(J47),J47*10%,IF(J47="","Por preencher",J47)) -> 2 | N47: DoR contém critérios objetivos e verificáveis para identificação, descrição, resultado, orçamento, aceitação, evidências, dependências, DoD, referências e destino. | O47: m1-definition-of-ready-v01.pdf; versão de trabalho; comparação com os campos obrigatórios do Backlog. | P47: Verificar que todos os critérios necessários ao Refinement/Planning estão cobertos e que não existem critérios ambíguos ou contraditórios. | Q47: Confirmar completude, aplicabilidade, coerência com o Backlog e Plano de Qualidade, versão final e arquivo. | R47: I006 — Plano de Qualidade do Processo. | S47: Critérios de conclusão documental da M1: conteúdo completo, revisto, aprovado, versionado e arquivado. | T47: Regulamento de Funcionamento da UC v19; Plano de Qualidade; template do Backlog de Projeto. | U47: /projeto/02-artefactos-de-qualidade-de-processo/02.02-definition-of-ready-e-done | V47: Sim | W47: Done | X47: Aprovada como Ready | Y47: 46283 | Z47: /projeto/01-artefactos-de-gestao/01.03-reunioes-de-grupo/m1-20260918-backlog-refinement-ata-v01.pdf | AA47: 2026-09-30 — Regularização documental: esta linha reconstitui trabalho efetivamente realizado durante a M1 com base nos artefactos existentes. O registo foi preparado posteriormente para completar a rastreabilidade do processo e não altera o conteúdo técnico entregue.
A48: I008 | B48: Elaborar Definition of Done | C48: Definir as condições que uma tarefa deve cumprir para poder ser considerada concluída e posteriormente aprovada como Done no Sprint Review. | D48: Uniformizar o critério de conclusão das tarefas e garantir produção, revisão, auditoria, aceitação, evidências e aprovação. | E48: Qualidade de processo | F48: m1-definition-of-done-v01.pdf | G48: 2 — Alta | H48: m1 | I48: S01 | J48: 20 | K48: =IF(ISNUMBER(J48),J48*60%,IF(J48="","Por preencher",J48)) -> 12 | L48: =IF(ISNUMBER(J48),J48*30%,IF(J48="","Por preencher",J48)) -> 6 | M48: =IF(ISNUMBER(J48),J48*10%,IF(J48="","Por preencher",J48)) -> 2 | N48: DoD define condições de produção, critérios de aceitação, revisão, auditoria, aceitação/integração, evidências, versionamento e aprovação em Sprint Review. | O48: m1-definition-of-done-v01.pdf; versão de trabalho; referências ao fluxo de qualidade. | P48: Verificar clareza e verificabilidade das condições de conclusão e coerência com o Plano de Qualidade e responsabilidades dos papéis. | Q48: Confirmar cobertura do ciclo Executor→Revisor→Auditor→aceitação→Review, versão final e arquivo. | R48: I006 — Plano de Qualidade do Processo. | S48: Critérios de conclusão documental da M1: conteúdo completo, revisto, aprovado, versionado e arquivado. | T48: Regulamento de Funcionamento da UC v19; Plano de Qualidade. | U48: /projeto/02-artefactos-de-qualidade-de-processo/02.02-definition-of-ready-e-done | V48: Sim | W48: Done | X48: Aprovada como Ready | Y48: 46283 | Z48: /projeto/01-artefactos-de-gestao/01.03-reunioes-de-grupo/m1-20260918-backlog-refinement-ata-v01.pdf | AA48: 2026-09-30 — Regularização documental: esta linha reconstitui trabalho efetivamente realizado durante a M1 com base nos artefactos existentes. O registo foi preparado posteriormente para completar a rastreabilidade do processo e não altera o conteúdo técnico entregue.
A49: I009 | B49: Definir Critérios de Qualidade dos Requisitos | C49: Definir os critérios objetivos de qualidade a utilizar na avaliação dos requisitos do sistema, incluindo correção, clareza, completude, consistência, necessidade, viabilidade, verificabilidade, rastreabilidade, singularidade, ausência de ambiguidade e independência da solução, quando aplicável. | D49: Estabelecer uma referência uniforme para verificar a qualidade e a consistência dos requisitos do sistema. | E49: Requisitos | F49: m1-criterios-qualidade-requisitos-v01.md | G49: 2 — Alta | H49: m1 | I49: S01 | J49: 30 | K49: =IF(ISNUMBER(J49),J49*60%,IF(J49="","Por preencher",J49)) -> 18 | L49: =IF(ISNUMBER(J49),J49*30%,IF(J49="","Por preencher",J49)) -> 9 | M49: =IF(ISNUMBER(J49),J49*10%,IF(J49="","Por preencher",J49)) -> 3 | N49: Documento inclui pelo menos correção, clareza, completude, consistência, necessidade, viabilidade, verificabilidade, rastreabilidade, singularidade, ausência de ambiguidade e independência da solução quando aplicável. | O49: m1-criterios-qualidade-requisitos-v01.md; histórico de alterações; referência na Checklist de Aprovação dos Requisitos. | P49: Verificar presença e definição objetiva dos 11 critérios, ausência de sobreposição contraditória e aplicabilidade à futura especificação de requisitos. | Q49: Confirmar revisão, completude, coerência com PS/DA, versão final e localização regulamentar. | R49: I001; I002; I006. | S49: DoD G08 v01: resultado produzido e acessível; critérios de aceitação cumpridos; revisão e auditoria concluídas; versão final aprovada, corretamente nomeada e arquivada na pasta prevista. | T49: Regulamento de Funcionamento da UC v19; PS; DA; Plano de Qualidade. | U49: /projeto/04-artefactos-tecnicos/04.03-requisitos-e-rtm | V49: Sim | W49: Done | X49: Aprovada como Ready | Y49: 46283 | Z49: /projeto/01-artefactos-de-gestao/01.03-reunioes-de-grupo/m1-20260918-backlog-refinement-ata-v01.pdf | AA49: 2026-09-30 — Regularização documental: esta linha reconstitui trabalho efetivamente realizado durante a M1 com base nos artefactos existentes. O registo foi preparado posteriormente para completar a rastreabilidade do processo e não altera o conteúdo técnico entregue.
A50: I014 | B50: Matriz de Rastreabilidade de Requisitos (RTM) v1 | C50: Criar a versão inicial da matriz de rastreabilidade (RTM) para estabelecer a ligação entre o âmbito aprovado, os requisitos, os casos de uso, a arquitetura e os testes previstos. | D50: Estabelecer a rastreabilidade inicial entre o âmbito, os requisitos, os casos de uso, a arquitetura e os testes previstos. | E50: Qualidade de processo | F50: m2-requirements-traceability-matrix-v01.xlsx | G50: 2 — Alta | H50: m2 | I50: S02 | J50: 30 | K50: =IF(ISNUMBER(J50),J50*60%,IF(J50="","Por preencher",J50)) -> 18 | L50: =IF(ISNUMBER(J50),J50*30%,IF(J50="","Por preencher",J50)) -> 9 | M50: =IF(ISNUMBER(J50),J50*10%,IF(J50="","Por preencher",J50)) -> 3 | N50: A RTM contém uma linha por requisito e permite relacionar os requisitos com os casos de uso, componentes da arquitetura e Issues ou tarefas associadas. São mantidas as colunas previstas no template oficial e os requisitos deixam-se identificados de forma consistente com a Especificação de Requisitos. | O50: m2-requirements-traceability-matrix-v01.xlsx preenchida; Especificação de Requisitos; especificações dos casos de uso e documentação de arquitetura utilizadas no preenchimento. | P50: Confirmar que todos os requisitos da Especificação de Requisitos estão representados na RTM; verificar os IDs e títulos; confirmar as ligações aos casos de uso, arquitetura e Issues ou tarefas e identificar relações em falta ou incoerentes. | Q50: Confirmar que a revisão foi realizada; verificar se todos os requisitos estão abrangidos; confirmar a utilização do template oficial, a coerência das ligações registadas e a versão e localização final do ficheiro. | R50: I012 — Especificação de Requisitos; I015 — Especificações dos Casos de Uso; documentação da arquitetura. | S50: DoD G08 v01: ficheiro produzido e acessível; critérios de aceitação cumpridos; revisão e auditoria concluídas; versão final confirmada e aprovada no Sprint Review. | T50: Regulamento de Funcionamento da UC v19; template oficial da Requirements Traceability Matrix; m2-especificacao-requisitos-v01.md; especificações dos casos de uso; documentação da arquitetura; Definition of Done G08 v01. | U50: /projeto/04-artefactos-tecnicos/04.03-requisitos-e-rtm | V50: Sim | W50: Done | X50: Aprovada como Ready | Y50: 46296 | Z50: /projeto/01-artefactos-de-gestao/01.03-reunioes-de-grupo/m2-s02-backlog-refinement-ata-v01.pdf | AA50: 2026-10-06 — Tarefa acrescentada ao Backlog durante a preparação da M2; aguarda análise em Backlog Refinement. 2026-10-19 18:56 — Atualização do registo: aprovada como Ready no Backlog Refinement de 2026-10-01 (ata m2-s02-backlog-refinement-ata-v01, secção 4) e passou a Done no Sprint Review de 2026-10-08 (ata m2-s02-20261008-sprint-review-ata-v01, secção 6.6). A entrada de 2026-10-06 sobre aguardar análise fica ultrapassada. 2026-10-27 — Correção da referência à ata (proposta para o Backlog Refinement do Sprint 05): o ficheiro arquivado chama-se m2-s02-backlog-refinement-ata-v01.pdf; o nome anterior não correspondia a nenhum ficheiro.
A51: I015 | B51: Especificação dos casos de uso | C51: Documentar os atores, objetivos, fluxos principais, fluxos de exceção e os requisitos associados aos casos de uso relevantes para o sistema. | D51: Documentar os atores, objetivos, fluxos, exceções e requisitos associados aos casos de uso relevantes. | E51: Documentação | F51: m2-especificacoes-casos-uso-v01.md | G51: 2 — Alta | H51: m2 | I51: S02 | J51: 50 | K51: =IF(ISNUMBER(J51),J51*60%,IF(J51="","Por preencher",J51)) -> 30 | L51: =IF(ISNUMBER(J51),J51*30%,IF(J51="","Por preencher",J51)) -> 15 | M51: =IF(ISNUMBER(J51),J51*10%,IF(J51="","Por preencher",J51)) -> 5 | N51: O documento identifica os atores e a fronteira do sistema; inclui um diagrama geral de casos de uso; cada caso de uso relevante identifica objetivo, atores, precondições, fluxo principal, alternativas ou exceções, pós-condições e requisitos relacionados; os casos de uso são coerentes com a Especificação de Requisitos. | O51: m2-especificacoes-casos-uso-v01.md; código-fonte do diagrama incluído no documento; Especificação de Requisitos utilizada como referência; histórico de alterações. | P51: Confirmar que os atores e casos de uso correspondem aos requisitos; verificar os fluxos, alternativas, exceções, precondições e pós-condições; confirmar que o diagrama corresponde às especificações escritas e que não existem casos de uso fora do âmbito. | Q51: Confirmar que a revisão foi realizada; verificar a cobertura dos casos de uso e respetivos requisitos; confirmar que o diagrama possui fonte textual editável; verificar versão, nomenclatura e pasta de destino. | R51: I012 — Especificação de Requisitos; I013 — Checklist de Aprovação dos Requisitos. | S51: DoD G08 v01: resultado produzido e acessível; critérios de aceitação cumpridos; evidências arquivadas; revisão e auditoria concluídas; versão final aceite e confirmada; aprovação no Sprint Review. | T51: Regulamento de Funcionamento da UC v19; m2-especificacao-requisitos-v01.md; m1-criterios-qualidade-requisitos-v01.md; Plano de Qualidade do Processo G08; Definition of Done G08 v01. | U51: /projeto/04-artefactos-tecnicos/04.04-casos-de-uso | V51: Sim | W51: Done | X51: Aprovada como Ready | Y51: 46296 | Z51: /projeto/01-artefactos-de-gestao/01.03-reunioes-de-grupo/m2-s02-backlog-refinement-ata-v01.pdf | AA51: 2026-10-06 — Tarefa acrescentada ao Backlog durante a preparação da M2; aguarda análise em Backlog Refinement. 2026-10-19 18:56 — Atualização do registo: aprovada como Ready no Backlog Refinement de 2026-10-01 (ata m2-s02-backlog-refinement-ata-v01, secção 4) e passou a Done no Sprint Review de 2026-10-08 (ata m2-s02-20261008-sprint-review-ata-v01, secção 6.6). A entrada de 2026-10-06 sobre aguardar análise fica ultrapassada. 2026-10-20 — A v01 mantém-se histórica; os Casos de Uso v02 são registados na rebaseline M3. 2026-10-27 — Correção da referência à ata (proposta para o Backlog Refinement do Sprint 05): o ficheiro arquivado chama-se m2-s02-backlog-refinement-ata-v01.pdf; o nome anterior não correspondia a nenhum ficheiro.
A52: I016 | B52: Modelo de Dados (Base de dados clinica-veterinaria) | C52: Conceber e documentar os modelos conceptual, lógico e físico, bem como o dicionário de dados da base de dados da clínica veterinária. | D52: Documentar os modelos conceptual, lógico e físico e o dicionário de dados da base de dados da clínica veterinária. | E52: Documentação | F52: m2-modelo-de-dados-clinica-veterinaria-v01.md | G52: 2 — Alta | H52: m2 | I52: S02 | J52: 50 | K52: =IF(ISNUMBER(J52),J52*60%,IF(J52="","Por preencher",J52)) -> 30 | L52: =IF(ISNUMBER(J52),J52*30%,IF(J52="","Por preencher",J52)) -> 15 | M52: =IF(ISNUMBER(J52),J52*10%,IF(J52="","Por preencher",J52)) -> 5 | N52: O documento inclui os modelos conceptual, lógico e físico da base de dados e o respetivo dicionário de dados; as entidades, atributos, relações e cardinalidades são coerentes entre os modelos; os dados necessários aos requisitos e casos de uso estão representados; os diagramas são legíveis e mantêm fonte textual editável. | O52: m2-modelo-de-dados-clinica-veterinaria-v01.md; código-fonte dos diagramas; Especificação de Requisitos e Casos de Uso utilizados como referência; histórico de alterações. | P52: Verificar se as entidades, atributos, relações e cardinalidades representam os dados necessários ao sistema; comparar os modelos conceptual, lógico e físico; confirmar a correspondência com o dicionário de dados e com os requisitos e casos de uso. | Q52: Confirmar que a revisão foi realizada; verificar a presença dos três modelos e do dicionário de dados; confirmar a coerência entre os modelos, a existência da fonte textual dos diagramas e a versão e localização do ficheiro. | R52: I012 — Especificação de Requisitos; I015 — Especificações dos Casos de Uso. | S52: DoD G08 v01: resultado produzido e acessível; critérios de aceitação cumpridos; evidências arquivadas; revisão e auditoria concluídas; versão final aceite e confirmada; aprovação no Sprint Review. | T52: Regulamento de Funcionamento da UC v19; m2-especificacao-requisitos-v01.md; m2-especificacoes-casos-uso-v01.md; Plano de Qualidade do Processo G08; Definition of Done G08 v01. | U52: /projeto/04-artefactos-tecnicos/04.06-modelos-de-dados | V52: Sim | W52: Done | X52: Aprovada como Ready | Y52: 46296 | Z52: /projeto/01-artefactos-de-gestao/01.03-reunioes-de-grupo/m2-s02-backlog-refinement-ata-v01.pdf | AA52: 2026-10-06 — Tarefa acrescentada ao Backlog durante a preparação da M2; aguarda análise em Backlog Refinement. 2026-10-19 18:56 — Atualização do registo: aprovada como Ready no Backlog Refinement de 2026-10-01 (ata m2-s02-backlog-refinement-ata-v01, secção 4) e passou a Done no Sprint Review de 2026-10-08 (ata m2-s02-20261008-sprint-review-ata-v01, secção 6.6). A entrada de 2026-10-06 sobre aguardar análise fica ultrapassada. 2026-10-20 — A v01 mantém-se histórica; o Modelo de Dados v02 é registado na rebaseline M3. 2026-10-27 — Correção da referência à ata (proposta para o Backlog Refinement do Sprint 05): o ficheiro arquivado chama-se m2-s02-backlog-refinement-ata-v01.pdf; o nome anterior não correspondia a nenhum ficheiro.
A53: I017 | B53: Protótipo de baixa fidelidade | C53: Desenhar os wireframes/protótipos para demonstrar a organização visual, a navegação e o conteúdo previsto para as interfaces, antes de se avançar para a implementação detalhada no código. | D53: Demonstra a organização, a navegação e o conteúdo visual previsto antes do início da implementação detalhada no código. | E53: Documentação | F53: m2-prototipo-baixa-fidelidade-v01.pdf | G53: 2 — Alta | H53: m2 | I53: S02 | J53: 50 | K53: =IF(ISNUMBER(J53),J53*60%,IF(J53="","Por preencher",J53)) -> 30 | L53: =IF(ISNUMBER(J53),J53*30%,IF(J53="","Por preencher",J53)) -> 15 | M53: =IF(ISNUMBER(J53),J53*10%,IF(J53="","Por preencher",J53)) -> 5 | N53: O protótipo representa os principais ecrãs e fluxos previstos para o sistema; a navegação entre os ecrãs é compreensível; os elementos principais de cada interface estão identificados; o conteúdo é coerente com os requisitos e casos de uso e permite perceber a organização das interfaces antes da implementação. | O53: m2-prototipo-baixa-fidelidade-v01.pdf; ficheiro editável do protótipo; versões ou histórico de alterações utilizados durante a elaboração. | P53: Comparar o protótipo com os requisitos e casos de uso; verificar se os principais ecrãs e fluxos estão representados; confirmar que a navegação é coerente e que não são apresentadas funcionalidades fora do âmbito. | Q53: Confirmar que a revisão foi realizada; verificar que o protótipo cobre os principais fluxos previstos; confirmar coerência com os requisitos e casos de uso, legibilidade do PDF, versão, nomenclatura e pasta de destino. | R53: I012 — Especificação de Requisitos; I015 — Especificações dos Casos de Uso. | S53: DoD G08 v01: resultado produzido e acessível; critérios de aceitação cumpridos; evidências arquivadas; revisão e auditoria concluídas; versão final aceite e confirmada; aprovação no Sprint Review. | T53: Regulamento de Funcionamento da UC v19; m2-especificacao-requisitos-v01.md; m2-especificacoes-casos-uso-v01.md; Declaração de Âmbito; Definition of Done G08 v01. | U53: /projeto/04-artefactos-tecnicos/04.10-prototipos-de-interfaces | V53: Sim | W53: Done | X53: Aprovada como Ready | Y53: 46296 | Z53: /projeto/01-artefactos-de-gestao/01.03-reunioes-de-grupo/m2-s02-backlog-refinement-ata-v01.pdf | AA53: 2026-10-06 — Tarefa acrescentada ao Backlog durante a preparação da M2; aguarda análise em Backlog Refinement. 2026-10-19 18:56 — Atualização do registo: aprovada como Ready no Backlog Refinement de 2026-10-01 (ata m2-s02-backlog-refinement-ata-v01, secção 4) e passou a Done no Sprint Review de 2026-10-08 (ata m2-s02-20261008-sprint-review-ata-v01, secção 6.6). A entrada de 2026-10-06 sobre aguardar análise fica ultrapassada. 2026-10-20 — A v01 mantém-se histórica; o Protótipo v02 será atualizado após a rebaseline funcional. 2026-10-27 — Correção da referência à ata (proposta para o Backlog Refinement do Sprint 05): o ficheiro arquivado chama-se m2-s02-backlog-refinement-ata-v01.pdf; o nome anterior não correspondia a nenhum ficheiro.
A54: I018 | B54: Documentação de API | C54: Descrever tecnicamente a API do sistema, incluindo os endpoints previstos, operações, autenticação, parâmetros, formatos de pedido e resposta, códigos de erro e exemplos de utilização. | D54: Definir de forma clara a API prevista para orientar a implementação do backend e a integração com as aplicações web e mobile. | E54: Documentação | F54: m2-documentacao-api-v01.md | G54: 2 — Alta | H54: m2 | I54: S02 | J54: 50 | K54: =IF(ISNUMBER(J54),J54*60%,IF(J54="","Por preencher",J54)) -> 30 | L54: =IF(ISNUMBER(J54),J54*30%,IF(J54="","Por preencher",J54)) -> 15 | M54: =IF(ISNUMBER(J54),J54*10%,IF(J54="","Por preencher",J54)) -> 5 | N54: A documentação identifica os endpoints previstos da API e, para cada um, indica a operação, método, rota, autenticação necessária, parâmetros ou dados de entrada, resposta esperada, códigos de erro e exemplo de utilização; a informação é coerente com os requisitos, casos de uso e arquitetura definidos para o sistema. | O54: m2-documentacao-api-v01.md; exemplos de pedidos e respostas; Especificação de Requisitos, Casos de Uso e documentação da arquitetura utilizados como referência; histórico de alterações. | P54: Confirmar que os endpoints previstos estão documentados; verificar métodos, rotas, parâmetros, autenticação, respostas e erros; comparar a documentação com os requisitos e casos de uso e identificar operações em falta ou incoerentes. | Q54: Confirmar que a revisão foi realizada; verificar a cobertura das operações previstas da API; confirmar coerência entre autenticação, parâmetros, respostas e erros; verificar versão, nomenclatura e pasta de destino. | R54: I012 — Especificação de Requisitos; I015 — Especificações dos Casos de Uso; Documentação da Arquitetura. | S54: DoD G08 v01: resultado produzido e acessível; critérios de aceitação cumpridos; evidências arquivadas; revisão e auditoria concluídas; versão final aceite e confirmada; aprovação no Sprint Review. | T54: Regulamento de Funcionamento da UC v19; m2-especificacao-requisitos-v01.md; m2-especificacoes-casos-uso-v01.md; documentação da arquitetura; Definition of Done G08 v01. | U54: /projeto/04-artefactos-tecnicos/04.11-documentacao-de-api | V54: Sim | W54: Done | X54: Aprovada como Ready | Y54: 46296 | Z54: /projeto/01-artefactos-de-gestao/01.03-reunioes-de-grupo/m2-s02-backlog-refinement-ata-v01.pdf | AA54: 2026-10-06 — Tarefa acrescentada ao Backlog durante a preparação da M2; aguarda análise em Backlog Refinement. 2026-10-19 18:56 — Atualização do registo: aprovada como Ready no Backlog Refinement de 2026-10-01 (ata m2-s02-backlog-refinement-ata-v01, secção 4) e passou a Done no Sprint Review de 2026-10-08 (ata m2-s02-20261008-sprint-review-ata-v01, secção 6.6). A entrada de 2026-10-06 sobre aguardar análise fica ultrapassada. 2026-10-20 — A v01 mantém-se histórica; a Documentação de API v02 deve ser refeita antes de utilizar identificadores de operações da API no trabalho restante. 2026-10-27 — Correção da referência à ata (proposta para o Backlog Refinement do Sprint 05): o ficheiro arquivado chama-se m2-s02-backlog-refinement-ata-v01.pdf; o nome anterior não correspondia a nenhum ficheiro.
A55: I019 | B55: Documentação da Arquitetura | C55: Documentar a arquitetura prevista do sistema, identificando os principais componentes, responsabilidades, relações, tecnologias, interfaces, restrições e decisões técnicas. | D55: Definir uma visão comum da arquitetura do sistema e das ligações entre backend, frontend web, frontend mobile e base de dados. | E55: Arquitetura e desenho | F55: m2-documentacao-arquitetura-v01.md | G55: 2 — Alta | H55: m2 | I55: S02 | J55: 50 | K55: =IF(ISNUMBER(J55),J55*60%,IF(J55="","Por preencher",J55)) -> 30 | L55: =IF(ISNUMBER(J55),J55*30%,IF(J55="","Por preencher",J55)) -> 15 | M55: =IF(ISNUMBER(J55),J55*10%,IF(J55="","Por preencher",J55)) -> 5 | N55: O documento identifica os componentes principais do sistema, as responsabilidades e relações entre eles, as tecnologias previstas, as interfaces, restrições e decisões relevantes; inclui diagramas de arquitetura com fonte textual editável e é coerente com os requisitos e casos de uso. | O55: m2-documentacao-arquitetura-v01.md; código-fonte dos diagramas; requisitos e casos de uso usados como referência; histórico de alterações. | P55: Verificar se os componentes, responsabilidades, tecnologias e interfaces estão identificados e coerentes com os requisitos e casos de uso; confirmar que os diagramas correspondem à descrição. | Q55: Confirmar que a revisão foi realizada; verificar coerência entre texto e diagramas, existência da fonte textual, versão, nomenclatura e pasta de destino. | R55: I012 — Especificação de Requisitos; I015 — Especificações dos Casos de Uso. | S55: DoD G08 v01: resultado produzido e acessível; critérios de aceitação cumpridos; evidências arquivadas; revisão e auditoria concluídas; versão final aceite e confirmada; aprovação no Sprint Review. | T55: Regulamento de Funcionamento da UC v19; m2-especificacao-requisitos-v01.md; m2-especificacoes-casos-uso-v01.md; Definition of Done G08 v01. | U55: /projeto/04-artefactos-tecnicos/04.05-arquitetura | V55: Sim | W55: Done | X55: Aprovada como Ready | Y55: 46296 | Z55: /projeto/01-artefactos-de-gestao/01.03-reunioes-de-grupo/m2-s02-backlog-refinement-ata-v01.pdf | AA55: 2026-10-06 — Tarefa acrescentada ao Backlog durante a preparação da M2; aguarda análise em Backlog Refinement. 2026-10-19 18:56 — Atualização do registo: aprovada como Ready no Backlog Refinement de 2026-10-01 (ata m2-s02-backlog-refinement-ata-v01, secção 4) e passou a Done no Sprint Review de 2026-10-08 (ata m2-s02-20261008-sprint-review-ata-v01, secção 6.6). A entrada de 2026-10-06 sobre aguardar análise fica ultrapassada. 2026-10-20 — A v01 mantém-se histórica; a Arquitetura v02 foi revista para Domain/Application/Infrastructure/Api. 2026-10-27 — Correção da referência à ata (proposta para o Backlog Refinement do Sprint 05): o ficheiro arquivado chama-se m2-s02-backlog-refinement-ata-v01.pdf; o nome anterior não correspondia a nenhum ficheiro.
A56: I020 | B56: Modelo de Classes - Backend | C56: Elaborar o modelo de classes do backend, representando as classes relevantes, responsabilidades, atributos, operações, relações e multiplicidades. | D56: Representar a estrutura de classes prevista para o backend de forma coerente com os requisitos, arquitetura e modelo de dados. | E56: Arquitetura e desenho | F56: m2-modelo-classes-backend-v01.md | G56: 2 — Alta | H56: m2 | I56: S02 | J56: 30 | K56: =IF(ISNUMBER(J56),J56*60%,IF(J56="","Por preencher",J56)) -> 18 | L56: =IF(ISNUMBER(J56),J56*30%,IF(J56="","Por preencher",J56)) -> 9 | M56: =IF(ISNUMBER(J56),J56*10%,IF(J56="","Por preencher",J56)) -> 3 | N56: O modelo representa as classes relevantes do backend, com responsabilidades, atributos, operações, relações e multiplicidades; é coerente com a arquitetura, requisitos e modelo de dados e inclui fonte textual editável. | O56: m2-modelo-classes-backend-v01.md; código-fonte do diagrama; arquitetura, requisitos e modelo de dados usados como referência; histórico de alterações. | P56: Verificar classes, responsabilidades, atributos, operações, relações e multiplicidades; confirmar coerência com a arquitetura, requisitos e modelo de dados. | Q56: Confirmar que a revisão foi realizada; verificar completude e coerência do modelo, existência da fonte textual, versão, nomenclatura e pasta de destino. | R56: I012 — Especificação de Requisitos; I015 — Especificações dos Casos de Uso; I016 — Modelo de Dados; I019 — Documentação da Arquitetura. | S56: DoD G08 v01: resultado produzido e acessível; critérios de aceitação cumpridos; evidências arquivadas; revisão e auditoria concluídas; versão final aceite e confirmada; aprovação no Sprint Review. | T56: Regulamento de Funcionamento da UC v19; m2-especificacao-requisitos-v01.md; m2-documentacao-arquitetura-v01.md; m2-modelo-de-dados-clinica-veterinaria-v01.md; Definition of Done G08 v01. | U56: /projeto/04-artefactos-tecnicos/04.07-modelos-de-classes | V56: Sim | W56: Done | X56: Aprovada como Ready | Y56: 46296 | Z56: /projeto/01-artefactos-de-gestao/01.03-reunioes-de-grupo/m2-s02-backlog-refinement-ata-v01.pdf | AA56: 2026-10-06 — A tarefa anterior de Modelo de Classes foi separada por módulo; esta linha fica dedicada ao backend e aguarda nova estimativa e análise em Backlog Refinement. 2026-10-19 18:56 — Atualização do registo: aprovada como Ready no Backlog Refinement de 2026-10-01 (ata m2-s02-backlog-refinement-ata-v01, secção 4) e passou a Done no Sprint Review de 2026-10-08 (ata m2-s02-20261008-sprint-review-ata-v01, secção 6.6). A entrada de 2026-10-06 sobre aguardar análise fica ultrapassada. 2026-10-20 — A v01 mantém-se histórica; o Modelo de Classes Backend v02 será atualizado após a API/Arquitetura v02. 2026-10-27 — Correção da referência à ata (proposta para o Backlog Refinement do Sprint 05): o ficheiro arquivado chama-se m2-s02-backlog-refinement-ata-v01.pdf; o nome anterior não correspondia a nenhum ficheiro.
... A62: I028 | B62: Especificar os Testes Unitários do Backend | C62: Atualizar a especificação dos testes unitários do backend para as regras da baseline funcional ativa F001, F002, F003, F004 e F006. Cada caso deve identificar pré-condições/dados, ação, resultado esperado, tipo de teste e rastreabilidade aos RF aplicáveis, cobrindo especialmente autorização, Cliente versus conta de acesso, horários/disponibilidade, Consultas, registo clínico e vacinação/desparasitação. | D62: Definir de forma verificável os testes unitários necessários para proteger as regras de negócio ativas do backend contra regressões. | E62: Teste | F62: m3-especificacao-testes-unitarios-backend-v01.md, em 03.01.02-testes-unitarios. | G62: 2 — Alta | H62: m3 | I62: S04 | J62: 50 | K62: =IF(ISNUMBER(J62),J62*60%,IF(J62="","Por preencher",J62)) -> 30 | L62: =IF(ISNUMBER(J62),J62*30%,IF(J62="","Por preencher",J62)) -> 15 | M62: =IF(ISNUMBER(J62),J62*10%,IF(J62="","Por preencher",J62)) -> 5 | N62: 1. Cada regra de negócio relevante do contrato da API v02 possui pelo menos um caso positivo e, quando aplicável, casos negativos e de fronteira. 2. As unidades críticas incluem autenticação e autorização, separação Cliente/conta de acesso, disponibilidade, horários dos Veterinários, estados das Consultas, registo clínico e cálculo/recalculo da próxima administração. 3. Cada caso possui identificador, unidade sob teste, pré-condições, dados, passos e resultado esperado. 4. Não são especificados testes para F005 ou F007. | O62: 1. Ficheiro Markdown v01. 2. Matriz de rastreabilidade casos ↔ RF/EP. 3. Lista de unidades não testáveis unitariamente e justificação. | P62: 1. Confirmar que as regras de negócio, validações e autorizações relevantes do contrato da API v02 possuem casos unitários positivos, negativos e de fronteira quando aplicável. 2. Amostrar casos de áreas diferentes e verificar que são executáveis tal como estão escritos. 3. Confirmar a coerência com o Modelo de Classes Backend v02 (I020), com os Requisitos v02 e com o Plano de Testes. | Q62: Checklist de auditoria 02.05 completa: independência dos três papéis, relatório de revisão 02.04, prazos de 48 h e 24 h, pontos, versão final e pasta. Confirmar a rastreabilidade entre requisitos e operações da API v02, a coerência com o plano de testes e que existem casos de fronteira nas unidades críticas. | R62: I012, I015, I016, I019, I018 e I020. | S62: DoD G08 v01: resultado produzido e acessível; critérios de aceitação cumpridos; revisão e auditoria concluídas; versão final aprovada, corretamente nomeada e arquivada na pasta prevista. Em documento: ficheiro final no formato e com o nome da secção 19 do regulamento; versão e data indicadas; coerente com os artefactos de origem; sem campos por preencher; PDF gerado a partir da versão final quando o formato exigir. | T62: Plano de Testes do Backend (I027); Especificação de Requisitos v02 (I012); Documentação de API v02 (I018); Modelo de Classes Backend v02 (I020); Regulamento de Funcionamento da UC v19, secção 19 (03.01.02). | U62: /projeto/03-artefactos-de-qualidade-de-produto/03.01-backend/03.01.02-testes-unitarios | V62: Sim | W62: Done | X62: Aprovada como Ready | Y62: 46314 | Z62: /projeto/01-artefactos-de-gestao/01.03-reunioes-de-grupo/m3-s04-20261019-backlog-refinement-ata-v01.pdf | AA62: 2026-10-14 23:05 — Proposta de refinamento preparada como versão de trabalho. Mantém o identificador e o âmbito da Issue original «Especificar Testes Unitários do Backend »; descrição, critérios, evidências, dependências e orçamento propostos. Ainda não analisada em Backlog Refinement: orçamento, DoR e decisão por ratificar. 2026-10-19 18:56 — Removidas a data e a ata de decisão: a tarefa não foi apreciada no Backlog Refinement de 2026-10-12 (ata m3-s03-20261012-backlog-refinement-ata-v01, secção 5: as restantes tarefas mantêm a decisão «Não analisada»); a v01 citava um nome de ata inexistente (m3-20261012…). 2026-10-21 15:30 — Versão de trabalho v03: registada a decisão do Backlog Refinement de 2026-10-19 (Aprovada como Ready; DoR = Sim; orçamento 50; ata m3-20261019-s04-ata-backlog-refinement-v01.pdf, secção 4 e deliberação 3). A redação desta Issue foi atualizada em 2026-10-20 na rebaseline M3 (retirada de F005/F007 do âmbito, requisitos RF, API v02). O Sprint Planning S04 (2026-10-20 a 2026-10-21) manteve o texto aprovado em 2026-10-19; a alteração de redação será apreciada no Backlog Refinement do Sprint 05. 2026-10-27 — Correção da referência à ata (proposta para o Backlog Refinement do Sprint 05): o ficheiro arquivado chama-se m3-s04-20261019-backlog-refinement-ata-v01.pdf; o nome anterior não correspondia a nenhum ficheiro. 2026-10-27 — Sprint Review do Sprint 04: tarefa aceite e estado alterado para Done (m3-s04-20261027-sprint-review-ata-v01.pdf).
A63: I029 | B63: Implementar e Executar Testes Unitários do Backend | C63: Contentor da implementação e execução dos testes unitários do backend em xUnit 2.6, organizados pelas áreas funcionais ativas e alinhados com a Especificação de Testes Unitários revista. A tarefa fica concluída apenas quando as tarefas filhas e a execução formal estiverem terminadas e os resultados estiverem registados. | D63: Comprovar automaticamente, ao nível unitário, as regras de negócio ativas do backend e disponibilizar resultados utilizáveis pela cobertura e pela pipeline. | E63: Teste | F63: Código dos testes unitários no projeto de testes do backend (04.12-backend/m3-v01) e m3-resultados-testes-unitarios-backend-v01.pdf. | G63: 2 — Alta | H63: m3 | I63: Não definido | J63: Não aprovado | K63: =IF(ISNUMBER(J63),J63*60%,IF(J63="","Por preencher",J63)) -> Não aprovado | L63: =IF(ISNUMBER(J63),J63*30%,IF(J63="","Por preencher",J63)) -> Não aprovado | M63: =IF(ISNUMBER(J63),J63*10%,IF(J63="","Por preencher",J63)) -> Não aprovado | N63: Contentor: sem critérios próprios. Fica concluído quando todas as tarefas filhas indicadas na descrição estiverem em Done e o resultado agregado descrito em «Resultado esperado» estiver completo e coerente. | O63: Não aplicável — as evidências são produzidas nas tarefas filhas. | P63: Não aplicável — a revisão é feita nas tarefas filhas. | Q63: Não aplicável — a auditoria é feita nas tarefas filhas. Confirmar apenas, no fecho, que nenhuma filha ficou por concluir. | R63: I028; implementação backend ativa. | S63: Contentor, sem DoD própria: fica Done quando todas as tarefas filhas estiverem Done. Cada filha cumpre a DoD G08 v01 (resultado produzido e acessível; critérios de aceitação cumpridos; revisão e auditoria concluídas; versão final aprovada, corretamente nomeada e arquivada na pasta prevista). O contentor não é executado, revisto nem auditado como tarefa autónoma. | T63: Regulamento de Funcionamento da UC v19, secção 19 (03.01.02-testes-unitarios); Plano de Testes do Backend (I027); Especificação de Testes Unitários (I028); implementação backend ativa. | U63: /projeto/03-artefactos-de-qualidade-de-produto/03.01-backend/03.01.02-testes-unitarios | V63: Não | W63: Pendente | X63: Não analisada | AA63: 2026-10-14 23:05 — Proposta de refinamento preparada como versão de trabalho. Esta Issue original passa a contentor (épico) e deixa de ser executada diretamente: o trabalho foi dividido nas tarefas I086, I087, I088, I089, I090. Não tem pontos próprios, para que os pontos não sejam contados em duplicado. Ainda não analisada em Backlog Refinement; a divisão e as decisões estão por ratificar. 2026-10-19 18:56 — Removidas a data e a ata de decisão: esta Issue-contentor não recebeu decisão de Ready no Backlog Refinement de 2026-10-12, por não ser executada diretamente; a v01 citava um nome de ata inexistente (m3-20261012…). A divisão desta Issue em tarefas executáveis foi aprovada no Backlog Refinement de 2026-10-12 (ata m3-s03-20261012-backlog-refinement-ata-v01, secção 6, deliberação 2).
A64: I030 | B64: Especificar os Testes de Integração do Backend | C64: Atualizar a especificação dos testes de integração para o fluxo real API → Application → Infrastructure → SQL Server, autenticação/autorização por perfil, isolamento de dados do Cliente, migrations, transações e concorrência relevante. A especificação deve cobrir todas as operações ativas da API v02, incluindo sucesso e erros previstos, sem depender da antiga numeração EP como contrato normativo. | D64: Definir de forma verificável os testes de integração necessários para comprovar a colaboração entre API, aplicação, persistência, segurança e SQL Server no âmbito ativo. | E64: Teste | F64: m3-especificacao-testes-integracao-backend-v01.md, em 03.01.03-testes-de-integracao. | G64: 2 — Alta | H64: m3 | I64: S04 | J64: 50 | K64: =IF(ISNUMBER(J64),J64*60%,IF(J64="","Por preencher",J64)) -> 30 | L64: =IF(ISNUMBER(J64),J64*30%,IF(J64="","Por preencher",J64)) -> 15 | M64: =IF(ISNUMBER(J64),J64*10%,IF(J64="","Por preencher",J64)) -> 5 | N64: 1. Cada operação da API v02 abrangida pelos testes de integração possui cenário de sucesso e cenários de erro relevantes definidos no contrato. 2. São especificados cenários de concorrência para o agendamento de Consultas e cenários de autorização entre perfis e de isolamento entre Clientes. 3. Os dados de teste e o estado inicial da base são reproduzíveis. 4. Não existem cenários relativos a pagamentos, contas financeiras, alojamentos ou internamentos. 5. Cada cenário mantém rastreabilidade para o requisito e operação correspondente. | O64: 1. Ficheiro Markdown v01. 2. Matriz de rastreabilidade casos ↔ EP/RF. 3. Descrição do conjunto de dados de teste. | P64: 1. Confirmar que nenhuma operação ativa da API v02 ou erro relevante do contrato ficou sem cenário de integração aplicável. 2. Verificar a viabilidade dos cenários de concorrência, autorização por perfil e isolamento entre Clientes e a coerência dos dados com o ambiente de teste. 3. Confirmar coerência com o Modelo de Dados v02 e com o Plano de Testes. | Q64: Checklist de auditoria 02.05 completa: independência dos três papéis, relatório de revisão 02.04, prazos de 48 h e 24 h, pontos, versão final e pasta. Confirmar cobertura das operações ativas da API v02 e dos códigos de erro relevantes, bem como a rastreabilidade aos requisitos correspondentes. | R64: I012, I015, I016, I019, I018; I027. | S64: DoD G08 v01: resultado produzido e acessível; critérios de aceitação cumpridos; revisão e auditoria concluídas; versão final aprovada, corretamente nomeada e arquivada na pasta prevista. Em documento: ficheiro final no formato e com o nome da secção 19 do regulamento; versão e data indicadas; coerente com os artefactos de origem; sem campos por preencher; PDF gerado a partir da versão final quando o formato exigir. | T64: Plano de Testes do Backend (I027); Especificação de Requisitos v02 (I012); Modelo de Dados v02 (I016); Documentação de API v02 (I018); Regulamento de Funcionamento da UC v19, secção 19 (03.01.03). | U64: /projeto/03-artefactos-de-qualidade-de-produto/03.01-backend/03.01.03-testes-de-integracao | V64: Sim | W64: Done | X64: Aprovada como Ready | Y64: 46314 | Z64: /projeto/01-artefactos-de-gestao/01.03-reunioes-de-grupo/m3-s04-20261019-backlog-refinement-ata-v01.pdf | AA64: 2026-10-14 23:05 — Proposta de refinamento preparada como versão de trabalho. Mantém o identificador e o âmbito da Issue original «Especificar Testes de Integração do Backend»; descrição, critérios, evidências, dependências e orçamento propostos. Ainda não analisada em Backlog Refinement: orçamento, DoR e decisão por ratificar. 2026-10-19 18:56 — Removidas a data e a ata de decisão: a tarefa não foi apreciada no Backlog Refinement de 2026-10-12 (ata m3-s03-20261012-backlog-refinement-ata-v01, secção 5: as restantes tarefas mantêm a decisão «Não analisada»); a v01 citava um nome de ata inexistente (m3-20261012…). 2026-10-21 15:30 — Versão de trabalho v03: registada a decisão do Backlog Refinement de 2026-10-19 (Aprovada como Ready; DoR = Sim; orçamento 50; ata m3-20261019-s04-ata-backlog-refinement-v01.pdf, secção 4 e deliberação 3). A redação desta Issue foi atualizada em 2026-10-20 na rebaseline M3 (retirada de F005/F007 do âmbito, requisitos RF, API v02). O Sprint Planning S04 (2026-10-20 a 2026-10-21) manteve o texto aprovado em 2026-10-19; a alteração de redação será apreciada no Backlog Refinement do Sprint 05. 2026-10-27 — Correção da referência à ata (proposta para o Backlog Refinement do Sprint 05): o ficheiro arquivado chama-se m3-s04-20261019-backlog-refinement-ata-v01.pdf; o nome anterior não correspondia a nenhum ficheiro. 2026-10-27 — Sprint Review do Sprint 04: tarefa aceite e estado alterado para Done (m3-s04-20261027-sprint-review-ata-v01.pdf).
A65: I032 | B65: Produzir o Relatório de Cobertura do Backend | C65: Produzir o relatório de cobertura do backend a partir da execução dos testes unitários e de integração, usando Coverlet 6.0 e ReportGenerator 5.5. A medição deve abranger Domínio e Serviços, aplicar apenas as exclusões justificadas no Regulamento e demonstrar cobertura de linhas igual ou superior a 70%. | D65: Demonstrar objetivamente o nível de cobertura do backend e confirmar o cumprimento do limiar mínimo de 70% definido pelo grupo. | E65: Documentação | F65: m3-relatorio-cobertura-testes-backend-v01.pdf, acompanhado dos relatórios produzidos pelas ferramentas, em 03.01.04-cobertura-de-testes. | G65: 2 — Alta | H65: m3 | I65: S05 | J65: 30 | K65: =IF(ISNUMBER(J65),J65*60%,IF(J65="","Por preencher",J65)) -> 18 | L65: =IF(ISNUMBER(J65),J65*30%,IF(J65="","Por preencher",J65)) -> 9 | M65: =IF(ISNUMBER(J65),J65*10%,IF(J65="","Por preencher",J65)) -> 3 | N65: 1. O relatório indica ferramenta, método de recolha, âmbito medido e as exclusões, cada uma justificada. 2. Apresenta cobertura de linhas e de ramos por projeto e por área funcional e compara com os limites do plano de testes. 3. Identifica as áreas abaixo do limite, a causa e a ação decidida (testes adicionais ou exceção justificada). 4. Os números correspondem aos relatórios gerados na pipeline, que ficam anexados em formato HTML ou equivalente. | O65: 1. PDF do relatório. 2. Relatórios gerados pelas ferramentas. 3. Ligação à execução da pipeline que os produziu. | P65: 1. Gerar localmente a cobertura e comparar com o PDF. 2. Verificar a justificação de cada exclusão. 3. Confirmar que os limites usados são os do plano de testes. | Q65: Checklist de auditoria 02.05 completa: independência dos três papéis, relatório de revisão 02.04, prazos de 48 h e 24 h, pontos, versão final e pasta. Confirmar que o relatório não depende do seu próprio nome nem de artefactos em falta e que os números correspondem à versão entregue. | R65: I090 — Executar os testes unitários e produzir o relatório de resultados; I097 — Executar os testes de integração e produzir o relatório de resultados; I103 — Integrar análise estática, cobertura e quality gates na pipeline. | S65: DoD G08 v01: resultado produzido e acessível; critérios de aceitação cumpridos; revisão e auditoria concluídas; versão final aprovada, corretamente nomeada e arquivada na pasta prevista. Em documento: ficheiro final no formato e com o nome da secção 19 do regulamento; versão e data indicadas; coerente com os artefactos de origem; sem campos por preencher; PDF gerado a partir da versão final quando o formato exigir. | T65: Plano de Testes do Backend (I027); resultados dos testes unitários e de integração; Regulamento de Funcionamento da UC v19, secção 19 (03.01.04-cobertura-de-testes); Regulamento Interno do Grupo G08 v02 (proposta), quality gates de cobertura. | U65: /projeto/03-artefactos-de-qualidade-de-produto/03.01-backend/03.01.04-cobertura-de-testes | V65: Sim | W65: Pendente | X65: Aprovada como Ready | Y65: 46322 | Z65: /projeto/01-artefactos-de-gestao/01.03-reunioes-de-grupo/m3-s05-20261027-backlog-refinement-ata-v01.pdf | AA65: 2026-10-14 23:05 — Proposta de refinamento preparada como versão de trabalho. Mantém o identificador e o âmbito da Issue original «Produzir Relatório de Cobertura do Backend»; descrição, critérios, evidências, dependências e orçamento propostos. Ainda não analisada em Backlog Refinement: orçamento, DoR e decisão por ratificar. 2026-10-19 18:56 — Removidas a data e a ata de decisão: a tarefa não foi apreciada no Backlog Refinement de 2026-10-12 (ata m3-s03-20261012-backlog-refinement-ata-v01, secção 5: as restantes tarefas mantêm a decisão «Não analisada»); a v01 citava um nome de ata inexistente (m3-20261012…). 2026-10-27 — Backlog Refinement do Sprint 05: aprovada como Ready, com Definition of Ready confirmada, orçamento de 30 pontos e repartição 60% / 30% / 10%.
A66: I033 | B66: Preparar a Collection Postman | C66: Contentor da preparação de uma Collection Postman única para todas as operações ativas da API v02, com ambiente/variáveis, autenticação Bearer por perfil, pedidos de sucesso e erro e organização por F001, F002, F003, F004 e F006. Não devem existir pedidos ativos de financeiro ou internamento. | D66: Disponibilizar uma coleção executável e reproduzível que permita validar manualmente e na pipeline todas as operações ativas da API v02. | E66: Documentação | F66: m3-collection-postman-v01.json, importável, com ambiente de variáveis e sem credenciais pessoais, em 03.01.05-postman. | G66: 2 — Alta | H66: m3 | I66: Não definido | J66: Não aprovado | K66: =IF(ISNUMBER(J66),J66*60%,IF(J66="","Por preencher",J66)) -> Não aprovado | L66: =IF(ISNUMBER(J66),J66*30%,IF(J66="","Por preencher",J66)) -> Não aprovado | M66: =IF(ISNUMBER(J66),J66*10%,IF(J66="","Por preencher",J66)) -> Não aprovado | N66: Contentor: sem critérios próprios. Fica concluído quando todas as tarefas filhas indicadas na descrição estiverem em Done e o resultado agregado descrito em «Resultado esperado» estiver completo e coerente. | O66: Não aplicável — as evidências são produzidas nas tarefas filhas. | P66: Não aplicável — a revisão é feita nas tarefas filhas. | Q66: Não aplicável — a auditoria é feita nas tarefas filhas. Confirmar apenas, no fecho, que nenhuma filha ficou por concluir. | R66: I018; implementação dos endpoints ativos. | S66: Contentor, sem DoD própria: fica Done quando todas as tarefas filhas estiverem Done. Cada filha cumpre a DoD G08 v01 (resultado produzido e acessível; critérios de aceitação cumpridos; revisão e auditoria concluídas; versão final aprovada, corretamente nomeada e arquivada na pasta prevista). O contentor não é executado, revisto nem auditado como tarefa autónoma. | T66: Documentação de API v02 (I018); documentação oficial do Postman e Newman; Regulamento de Funcionamento da UC v19, secção 19 (03.01.05-postman). | U66: /projeto/03-artefactos-de-qualidade-de-produto/03.01-backend/03.01.05-postman | V66: Não | W66: Pendente | X66: Não analisada | AA66: 2026-10-14 23:05 — Proposta de refinamento preparada como versão de trabalho. Esta Issue original passa a contentor (épico) e deixa de ser executada diretamente: o trabalho foi dividido nas tarefas I098, I099, I100. Não tem pontos próprios, para que os pontos não sejam contados em duplicado. Ainda não analisada em Backlog Refinement; a divisão e as decisões estão por ratificar. 2026-10-19 18:56 — Removidas a data e a ata de decisão: esta Issue-contentor não recebeu decisão de Ready no Backlog Refinement de 2026-10-12, por não ser executada diretamente; a v01 citava um nome de ata inexistente (m3-20261012…). A divisão desta Issue em tarefas executáveis foi aprovada no Backlog Refinement de 2026-10-12 (ata m3-s03-20261012-backlog-refinement-ata-v01, secção 6, deliberação 2).
A67: I034 | B67: Executar a análise estática do backend e produzir o relatório | C67: Executar a análise estática do backend com Roslyn Analyzers/Microsoft.CodeAnalysis.NetAnalyzers no perfil recomendado do .NET 10, respeitando a configuração versionada em .editorconfig. Warnings e Errors devem bloquear o quality gate; apenas código gerado por EF Core Migrations pode ser excluído quando justificado. Produzir relatório formal das ocorrências, correções e exceções aceites. | D67: Demonstrar que o backend cumpre as regras de análise estática definidas no Regulamento e que todas as ocorrências bloqueantes foram tratadas ou justificadas. | E67: Qualidade de processo | F67: m3-relatorio-analise-estatica-backend-v01.pdf, acompanhado dos resultados das ferramentas, em 03.01.06-analise-estatica. | G67: 2 — Alta | H67: m3 | I67: S05 | J67: 50 | K67: =IF(ISNUMBER(J67),J67*60%,IF(J67="","Por preencher",J67)) -> 30 | L67: =IF(ISNUMBER(J67),J67*30%,IF(J67="","Por preencher",J67)) -> 15 | M67: =IF(ISNUMBER(J67),J67*10%,IF(J67="","Por preencher",J67)) -> 5 | N67: 1. O relatório identifica ferramenta, versão, configuração, regras, âmbito e commit analisado. 2. Todas as ocorrências de severidade alta ou crítica estão corrigidas ou justificadas por escrito e aceites pelo Revisor. 3. O resultado final da execução cumpre o quality gate, comprovado por log da pipeline. 4. Os falsos positivos e exceções têm justificação e referência à regra. 5. O relatório apresenta o antes e o depois, com o número de problemas por severidade. | O67: 1. PDF do relatório. 2. Relatórios da ferramenta. 3. Merge Requests de correção ligados às ocorrências. | P67: 1. Reexecutar a análise sobre o commit indicado e comparar contagens. 2. Amostrar 5 falsos positivos e confirmar a justificação. 3. Confirmar que as correções não alteraram comportamento (testes verdes). | Q67: Checklist de auditoria 02.05 completa: independência dos três papéis, relatório de revisão 02.04, prazos de 48 h e 24 h, pontos, versão final e pasta. Confirmar que o commit analisado é o da versão entregue e que as justificações são coerentes. | R67: I101 — Configurar a análise estática e o quality gate do backend; I025 — Desenvolver Backend; I103 — Integrar análise estática, cobertura e quality gates na pipeline. | S67: DoD G08 v01: resultado produzido e acessível; critérios de aceitação cumpridos; revisão e auditoria concluídas; versão final aprovada, corretamente nomeada e arquivada na pasta prevista. Em documento: ficheiro final no formato e com o nome da secção 19 do regulamento; versão e data indicadas; coerente com os artefactos de origem; sem campos por preencher; PDF gerado a partir da versão final quando o formato exigir. | T67: Plano de Qualidade do Processo (I006); Regulamento de Funcionamento da UC v19, secção 19 (03.01.06-analise-estatica); Regulamento Interno do Grupo G08 v02 (proposta), linters e quality gates do backend. | U67: /projeto/03-artefactos-de-qualidade-de-produto/03.01-backend/03.01.06-analise-estatica | V67: Sim | W67: Pendente | X67: Aprovada como Ready | Y67: 46322 | Z67: /projeto/01-artefactos-de-gestao/01.03-reunioes-de-grupo/m3-s05-20261027-backlog-refinement-ata-v01.pdf | AA67: 2026-10-14 23:05 — Proposta de refinamento preparada como versão de trabalho. Mantém o identificador e o âmbito da Issue original «Executar a Análise Estática do Backend»; descrição, critérios, evidências, dependências e orçamento propostos. Ainda não analisada em Backlog Refinement: orçamento, DoR e decisão por ratificar. 2026-10-19 18:56 — Removidas a data e a ata de decisão: a tarefa não foi apreciada no Backlog Refinement de 2026-10-12 (ata m3-s03-20261012-backlog-refinement-ata-v01, secção 5: as restantes tarefas mantêm a decisão «Não analisada»); a v01 citava um nome de ata inexistente (m3-20261012…). 2026-10-27 — Backlog Refinement do Sprint 05: aprovada como Ready, com Definition of Ready confirmada, orçamento de 50 pontos e repartição 60% / 30% / 10%.
